{
  "newspaper_id": "lankadeepa-lk",
  "url": "https://www.lankadeepa.lk/world_news/\u0da2\u0db1\u0dad\u0dcf-\u0dc3\u0dda\u0dc0\u0dba\u0dda\u0daf\u0dd3-\u0dc4\u0dd2\u0db1\u0dcf\u0dc0-\u0d95\u0db1\u0dd1:-\u0db1\u0dd0\u0dad\u0dd2\u0db1\u0db8\u0dca-\u0daf\u0da9/14-616457",
  "time_ut": 1657865648,
  "original_lang": "si",
  "original_title": "\u0da2\u0db1\u0dad\u0dcf \u0dc3\u0dda\u0dc0\u0dba\u0dda\u0daf\u0dd3 \u0dc4\u0dd2\u0db1\u0dcf\u0dc0 \u0d95\u0db1\u0dd1: \u0db1\u0dd0\u0dad\u0dd2\u0db1\u0db8\u0dca \u0daf\u0da9",
  "text_idx": {
    "en": {
      "title": "Laughter is required in public service: or fine",
      "author": "unknown",
      "body_lines": [
        "Public servants who do not serve the people with a smile will be fined, said Aristotle Aguirre, the mayor of the city of Mulane, Philippines.",
        "The mayor pointed out that this decision was taken with the aim of improving the quality of public service by creating a friendly environment for the people who come to get the public service.",
        "People are frustrated with the public service. There are complaints from many residents who go to the public servants for their duties. Confidence in public service has been lost. Therefore, from now on, when public servants provide services to the people, they should do so with a smile. There is no room for complaints or complaints from the people. If such complaints are received, the relevant government officials will be punished. Public servants or officers who disregard this order will be subject to a maximum fine equal to 6 months' salary or suspension from work. Mayor Aristotle Aguirre has explained.",
        "Aristotle Aguirre has been mayor for 8 months. Even while running for the position of mayor, Aristotle Aguirre has resisted to create a quality public servant. Accordingly, considering the complaints from the people, he has introduced this 'smile policy'.",
        "Fishermen, agriculturists and people from remote areas come to the city for their work. They hustle for hours and days to get the job done. Complaints are received daily regarding the harassment of government employees. According to that, we should provide the kind of service that the people are satisfied with.''"
      ],
      "title_ents": [],
      "body_line_ents_list": [
        [
          {
            "text": "Aristotle Aguirre",
            "label": "PERSON"
          },
          {
            "text": "Mulane",
            "label": "GPE"
          },
          {
            "text": "Philippines",
            "label": "GPE"
          }
        ],
        [],
        [
          {
            "text": "6 months'",
            "label": "DATE"
          },
          {
            "text": "Aristotle Aguirre",
            "label": "PERSON"
          }
        ],
        [
          {
            "text": "Aristotle Aguirre",
            "label": "PERSON"
          },
          {
            "text": "8 months",
            "label": "DATE"
          },
          {
            "text": "Aristotle Aguirre",
            "label": "PERSON"
          }
        ],
        [
          {
            "text": "daily",
            "label": "DATE"
          }
        ]
      ]
    },
    "si": {
      "title": "\u0da2\u0db1\u0dad\u0dcf \u0dc3\u0dda\u0dc0\u0dba\u0dda\u0daf\u0dd3 \u0dc4\u0dd2\u0db1\u0dcf\u0dc0 \u0d95\u0db1\u0dd1: \u0db1\u0dd0\u0dad\u0dd2\u0db1\u0db8\u0dca \u0daf\u0da9",
      "author": "unknown",
      "body_lines": [
        "\u0dc3\u0dd2\u0db1\u0dc4\u0db8\u0dd4\u0dc3\u0dd4\u0dc0 \u0da2\u0db1\u0dad\u0dcf \u0dc3\u0dda\u0dc0\u0dba \u0db1\u0ddc\u0d9a\u0dbb\u0db1 \u0dbb\u0dcf\u0da2\u0dca\u200d\u0dba \u0dc3\u0dda\u0dc0\u0d9a\u0dba\u0db1\u0dca\u0d9c\u0dd9\u0db1\u0dca \u0daf\u0da9 \u0d85\u0dba \u0d9a\u0dbb \u0d9c\u0db1\u0dca\u0db1\u0dcf \u0db6\u0dc0, \u0db4\u0dd2\u0dbd\u0dd2\u0db4\u0dd3\u0db1\u0dba\u0dda \u0db8\u0dd4\u0dbd\u0dcf\u0db1\u0dda \u0db1\u0d9c\u0dbb\u0dba\u0dda \u0db1\u0d9c\u0dbb\u0dcf\u0db0\u0dd2\u0db4\u0dad\u0dd2 \u0d87\u0dbb\u0dd2\u0dc3\u0dca\u0da7\u0ddd\u0da7\u0dbd\u0dca \u0d87\u0d9c\u0dca\u0dc0\u0dba\u0dbb\u0dca \u0db4\u0dc0\u0dc3\u0dcf \u0dad\u0dd2\u0db6\u0dda.",
        "\u0dbb\u0dcf\u0da2\u0dca\u200d\u0dba \u0dc3\u0dda\u0dc0\u0dba \u0dbd\u0db6\u0dcf \u0d9c\u0dd0\u0db1\u0dd3\u0db8\u0da7 \u0db4\u0dd0\u0db8\u0dd2\u0dab\u0dd9\u0db1 \u0da2\u0db1\u0dad\u0dcf\u0dc0 \u0dc0\u0dd9\u0db1\u0dd4\u0dc0\u0dd9\u0db1\u0dca \u0db8\u0dd2\u0dad\u0dca\u200d\u0dbb\u0dc1\u0dd3\u0dbd\u0dd2 \u0dc0\u0da7\u0db4\u0dd2\u0da7\u0dcf\u0dc0\u0d9a\u0dca \u0d87\u0dad\u0dd2 \u0d9a\u0dbb\u0db8\u0dd2\u0db1\u0dca, \u0dbb\u0dcf\u0da2\u0dca\u200d\u0dba \u0dc3\u0dda\u0dc0\u0dba\u0dda \u0d9c\u0dd4\u0dab\u0dcf\u0dad\u0dca\u0db8\u0d9a\u0db7\u0dcf\u0dc0\u0dba \u0d89\u0dc4\u0dc5 \u0db1\u0dd0\u0d82\u0dc0\u0dd3\u0db8\u0dda \u0d85\u0dbb\u0db8\u0dd4\u0dab\u0dd2\u0db1\u0dca \u0db8\u0dd9\u0db8 \u0dad\u0dd3\u0dbb\u0dab\u0dba \u0d9c\u0dad\u0dca \u0db6\u0dc0 \u0db1\u0d9c\u0dbb\u0dcf\u0db0\u0dd2\u0db4\u0dad\u0dd2\u0dc0\u0dbb\u0dba\u0dcf \u0db4\u0dd9\u0db1\u0dca\u0dc0\u0dcf \u0daf\u0dd3 \u0d87\u0dad.",
        "\u2018\u0dbb\u0dcf\u0da2\u0dca\u200d\u0dba \u0dc3\u0dda\u0dc0\u0dba \u0d9c\u0dd0\u0db1 \u0da2\u0db1\u0dad\u0dcf\u0dc0 \u0dc3\u0dd2\u0da7\u0dd2\u0db1\u0dca\u0db1\u0dda \u0d9a\u0dbd\u0d9a\u0dd2\u0dbb\u0dd3\u0db8\u0dd9\u0db1\u0dca. \u0dad\u0db8 \u0dad\u0db8\u0db1\u0dca\u0d9c\u0dda \u0dbb\u0dcf\u0da2\u0d9a\u0dcf\u0dbb\u0dd2 \u0dc3\u0db3\u0dc4\u0dcf \u0dbb\u0dcf\u0da2\u0dca\u200d\u0dba \u0dc3\u0dda\u0dc0\u0d9a\u0dba\u0db1\u0dca \u0dc4\u0db8\u0dd4\u0dc0\u0da7 \u0dba\u0db1 \u0dc0\u0dd0\u0dc3\u0dd2\u0dba\u0db1\u0dca \u0db6\u0ddc\u0dc4\u0ddd \u0daf\u0dd9\u0db1\u0d9a\u0dd4\u0d9c\u0dd9\u0db1\u0dca \u0db8\u0dd0\u0dc3\u0dd2\u0dc0\u0dd2\u0dbd\u0dd2 \u0db1\u0d9c\u0db1\u0dc0\u0dcf. \u0dbb\u0dcf\u0da2\u0dca\u200d\u0dba \u0dc3\u0dda\u0dc0\u0dba \u0d9a\u0dd9\u0dbb\u0dd9\u0dc4\u0dd2 \u0d87\u0dad\u0dd2 \u0dc0\u0dd2\u0dc1\u0dca\u0dc0\u0dcf\u0dc3\u0dba \u0d9c\u0dd2\u0dbd\u0dd2\u0dc4\u0dd3 \u0d9c\u0dd2\u0dc4\u0dd2\u0db1\u0dca. \u0d92 \u0db1\u0dd2\u0dc3\u0dcf \u0db8\u0dd2\u0db1\u0dca \u0d89\u0daf\u0dd2\u0dbb\u0dd2\u0dba\u0da7 \u0dbb\u0dcf\u0da2\u0dca\u200d\u0dba \u0dc3\u0dda\u0dc0\u0d9a\u0dba\u0db1\u0dca \u0da2\u0db1\u0dad\u0dcf\u0dc0\u0da7 \u0dc3\u0dda\u0dc0\u0dba \u0dc3\u0db4\u0dba\u0db1 \u0dc0\u0dd2\u0da7 \u0dc3\u0dd2\u0db1\u0dc4\u0db8\u0dd4\u0dc3\u0dd4 \u0db8\u0dd4\u0dc4\u0dd4\u0dab\u0dd2\u0db1\u0dca \u0dc3\u0dda\u0dc0\u0dba \u0dbd\u0db6\u0dcf \u0daf\u0dd3\u0db8 \u0d9a\u0dc5 \u0dba\u0dd4\u0dad\u0dd4\u0dba\u0dd2. \u0da2\u0db1\u0dad\u0dcf\u0dc0\u0d9c\u0dd9\u0db1\u0dca \u0db8\u0dd0\u0dc3\u0dd2\u0dc0\u0dd2\u0dbd\u0dd2 \u0dc4\u0ddd \u0db4\u0dd0\u0db8\u0dd2\u0dab\u0dd2\u0dbd\u0dd2 \u0dc4\u0ddd \u0db1\u0dd0\u0d9c\u0dd9\u0db1\u0dca\u0db1 \u0d89\u0da9\u0d9a\u0dca \u0db1\u0dd0\u0dc4\u0dd0. \u0d91\u0dc3\u0dda \u0db4\u0dd0\u0db8\u0dd2\u0dab\u0dd2\u0dbd\u0dd2 \u0dbd\u0dd0\u0db6\u0dd9\u0db1\u0dca\u0db1\u0dda \u0db1\u0db8\u0dca, \u0d85\u0daf\u0dcf\u0dc5 \u0dbb\u0dcf\u0da2\u0dca\u200d\u0dba \u0db1\u0dd2\u0dbd\u0db0\u0dcf\u0dbb\u0dd3\u0db1\u0dca\u0da7 \u0daf\u0da9\u0dd4\u0dc0\u0db8\u0dca \u0dbd\u0dd0\u0db6\u0dd9\u0db1\u0dc0\u0dcf. \u0dad\u0db8\u0db1\u0dca\u0d9c\u0dda \u0db8\u0dd9\u0db8 \u0db1\u0dd2\u0dba\u0ddd\u0d9c\u0dba \u0db1\u0ddc\u0dc3\u0dc5\u0d9a\u0dcf \u0d9a\u0da7\u0dba\u0dd4\u0dad\u0dd4 \u0d9a\u0dbb\u0db1 \u0dbb\u0dcf\u0da2\u0dca\u200d\u0dba \u0dc3\u0dda\u0dc0\u0db1\u0dba\u0db1\u0dca \u0dc4\u0ddd \u0db1\u0dd2\u0dbd\u0db0\u0dcf\u0dbb\u0dd3\u0db1\u0dca \u0db8\u0dcf\u0dc3 6\u0d9a \u0dc0\u0dd0\u0da7\u0dd4\u0db4\u0d9a\u0da7 \u0dc3\u0db8\u0dcf\u0db1 \u0d8b\u0db4\u0dbb\u0dd2\u0db8 \u0daf\u0da9\u0dba\u0d9a\u0da7 \u0dc4\u0ddd \u0dc0\u0dd0\u0da9 \u0dad\u0dc4\u0db1\u0db8\u0d9a\u0da7 \u0dc4\u0ddd \u0dbd\u0d9a\u0dca\u00a0 \u0d9a\u0dd9\u0dbb\u0dd9\u0db1\u0dd4 \u0d87\u0dad.\u2019 \u0dba\u0dd0\u0dba\u0dd2 \u0db1\u0d9c\u0dbb\u0dcf\u0db0\u0dd2\u0db4\u0dad\u0dd2 \u0d87\u0dbb\u0dd2\u0dc3\u0dca\u0da7\u0ddd\u0da7\u0dbd\u0dca \u0d87\u0d9c\u0dca\u0dc0\u0dba\u0dbb\u0dca \u0db4\u0dd0\u0dc4\u0dd0\u0daf\u0dd2\u0dbd\u0dd2 \u0d9a\u0dbb \u0dad\u0dd2\u0db6\u0dda.",
        "\u0d87\u0dbb\u0dd2\u0dc3\u0dca\u0da7\u0ddd\u0da7\u0dbd\u0dca \u0d87\u0d9c\u0dca\u0dc0\u0dba\u0dbb\u0dca, \u0db1\u0d9c\u0dbb\u0dcf\u0db0\u0dd2\u0db4\u0dad\u0dd2 \u0db0\u0dd4\u0dbb\u0dba\u0da7 \u0db4\u0dad\u0dca\u0dc0\u0dd3 \u0db8\u0dcf\u0dc3 8 \u0d9a\u0dd2. \u0db1\u0d9c\u0dbb\u0dcf\u0db0\u0dd2\u0db4\u0dad\u0dd2 \u0db0\u0dd4\u0dbb\u0dba\u0da7 \u0dad\u0dbb\u0d9c \u0dc0\u0daf\u0dd2\u0daf\u0dca\u0daf\u0dd3 \u0db4\u0dc0\u0dcf \u0d87\u0dbb\u0dd2\u0dc3\u0dca\u0da7\u0ddd\u0da7\u0dbd\u0dca \u0d87\u0d9c\u0dca\u0dc0\u0dba\u0dbb\u0dca \u0d9c\u0dd4\u0dab\u0dcf\u0dad\u0dca\u0db8\u0d9a \u0dbb\u0dcf\u0da2\u0dca\u200d\u0dba\u0da8 \u0dc3\u0dda\u0dc0\u0d9a\u0dba\u0d9a\u0dca \u0d87\u0dad\u0dd2 \u0d9a\u0dd2\u0dbb\u0dd3\u0db8\u0da7 \u0db4\u0dca\u200d\u0dbb\u0dad\u0dd2\u0db3\u0dcf \u0daf\u0dd3 \u0dad\u0dd2\u0db6\u0dda. \u0d92 \u0d85\u0db1\u0dd4\u0dc0, \u0da2\u0db1\u0dad\u0dcf\u0dc0\u0d9c\u0dd9\u0db1\u0dca \u0d91\u0dbd\u0dca\u0dbd \u0dc0\u0db1 \u0db4\u0dd0\u0db8\u0dd2\u0dab\u0dd2\u0dbd\u0dd2 \u0dc3\u0dd0\u0dbd\u0d9a\u0dd2\u0dbd\u0dca\u0dbd\u0da7 \u0d9c\u0db1\u0dd2\u0db8\u0dd2\u0db1\u0dca \u0d94\u0dc4\u0dd4 \u0db8\u0dd9\u0db8 \u2018\u0dc3\u0dd2\u0db1\u0dcf\u0dc3\u0dd3\u0db8\u0dda \u0db4\u0dca\u200d\u0dbb\u0dad\u0dd2\u0db4\u0dad\u0dca\u0dad\u0dd2\u0dba\u2019 \u0dc4\u0db3\u0dd4\u0db1\u0dca\u0dc0\u0dcf \u0daf\u0dd3 \u0dad\u0dd2\u0db6\u0dda.",
        "\u2018\u0db0\u0dd3\u0dc0\u0dbb\u0dba\u0db1\u0dca, \u0d9a\u0dd8\u0dc2\u0dd2 \u0d9a\u0dbb\u0dca\u0db8\u0dcf\u0db1\u0dca\u0dad\u0dba\u0dda \u0db1\u0dd2\u0dba\u0dd0\u0dc5\u0dd9\u0db1\u0dca\u0db1\u0db1\u0dca \u0dc3\u0dc4 \u0daf\u0dd4\u0dc2\u0dca\u0d9a\u0dbb \u0db4\u0dc5\u0dcf\u0dad\u0dca\u0dc0\u0dbd \u0dc0\u0dd0\u0dc3\u0dd2\u0dba\u0db1\u0dca \u0d94\u0dc0\u0dd4\u0db1\u0dca\u0d9c\u0dda \u0d9a\u0da7\u0dba\u0dd4\u0dad\u0dd4 \u0dc3\u0db3\u0dc4\u0dcf \u0db1\u0d9c\u0dbb\u0dba\u0da7 \u0db4\u0dd0\u0db8\u0dd2\u0dab\u0dd9\u0db1\u0dc0\u0dcf. \u0d85\u0dc0\u0dc1\u0dca\u200d\u0dba \u0dc0\u0dd0\u0da9\u0dda \u0d9a\u0dbb \u0d9c\u0db1\u0dca\u0db1 \u0d94\u0dc0\u0dd4\u0db1\u0dca \u0db4\u0dd0\u0dba \u0d9c\u0dab\u0db1\u0d9a\u0dca \u0daf\u0dd2\u0db1 \u0d9c\u0dab\u0db1\u0d9a\u0dca \u0dbb\u0dc3\u0dca\u0dad\u0dd2\u0dba\u0dcf\u0daf\u0dd4 \u0dc0\u0dd9\u0db1\u0dc0\u0dcf.\u00a0 \u0dbb\u0dcf\u0da2\u0dca\u200d\u0dba \u0dc3\u0dda\u0dc0\u0d9a\u0dba\u0db1\u0dca\u0d9c\u0dd9\u0db1\u0dca \u0dc3\u0dd2\u0daf\u0dd4\u0dc0\u0db1 \u0d9a\u0dd9\u0dab\u0dd9\u0dc4\u0dd2\u0dbd\u0dd2\u0d9a\u0db8\u0dca \u0dc3\u0db8\u0dca\u0db6\u0db1\u0dca\u0db0\u0dc0 \u0daf\u0dd2\u0db1\u0db4\u0dad\u0dcf \u0db4\u0dd0\u0db8\u0dd2\u0dab\u0dd2\u0dbd\u0dd2 \u0dbd\u0dd0\u0db6\u0dd9\u0db1\u0dc0\u0dcf. \u0d92 \u0d85\u0db1\u0dd4\u0dc0 \u0da2\u0db1\u0dad\u0dcf\u0dc0 \u0dc3\u0dd1\u0dc4\u0dd3\u0db8\u0d9a\u0da7 \u0db4\u0dad\u0dca\u0dc0\u0db1 \u0d86\u0d9a\u0dcf\u0dbb\u0dba\u0dda \u0dc3\u0dda\u0dc0\u0dba\u0d9a\u0dca \u0dc3\u0dd0\u0db4\u0dba\u0dd2\u0dba \u0d9a\u0dc5 \u0dba\u0dd4\u0dad\u0dd4\u0dba\u0dd2.\u2019 \u0dba\u0dd0\u0dba\u0dd2 \u0db1\u0d9c\u0dbb\u0dcf\u0db0\u0dd2\u0db4\u0dad\u0dd2\u0dc0\u0dbb\u0dba\u0dcf \u0db4\u0dd0\u0dc4\u0dd0\u0daf\u0dd2\u0dbd\u0dd2 \u0dad\u0dd2\u0db6\u0dda."
      ],
      "title_ents": [],
      "body_line_ents_list": [
        [
          {
            "text": "\u0d87\u0dbb\u0dd2\u0dc3\u0dca\u0da7\u0ddd\u0da7\u0dbd\u0dca \u0d87\u0d9c\u0dd4\u0dbb\u0dda",
            "label": "PERSON"
          },
          {
            "text": "\u0db8\u0dd4\u0dbd\u0db1\u0dda",
            "label": "GPE"
          },
          {
            "text": "\u0db4\u0dd2\u0dbd\u0dd2\u0db4\u0dd3\u0db1\u0dba",
            "label": "GPE"
          }
        ],
        [],
        [
          {
            "text": "\u0db8\u0dcf\u0dc3 6'",
            "label": "DATE"
          },
          {
            "text": "\u0d87\u0dbb\u0dd2\u0dc3\u0dca\u0da7\u0ddd\u0da7\u0dbd\u0dca \u0d87\u0d9c\u0dd4\u0dbb\u0dda",
            "label": "PERSON"
          }
        ],
        [
          {
            "text": "\u0d87\u0dbb\u0dd2\u0dc3\u0dca\u0da7\u0ddd\u0da7\u0dbd\u0dca \u0d87\u0d9c\u0dd4\u0dbb\u0dda",
            "label": "PERSON"
          },
          {
            "text": "\u0db8\u0dcf\u0dc3 8 \u0dba\u0dd2",
            "label": "DATE"
          },
          {
            "text": "\u0d87\u0dbb\u0dd2\u0dc3\u0dca\u0da7\u0ddd\u0da7\u0dbd\u0dca \u0d87\u0d9c\u0dd4\u0dbb\u0dda",
            "label": "PERSON"
          }
        ],
        [
          {
            "text": "\u0daf\u0dd2\u0db1\u0db4\u0dad\u0dcf",
            "label": "DATE"
          }
        ]
      ]
    },
    "ta": {
      "title": "\u0baa\u0bca\u0ba4\u0bc1\u0b9a\u0bcd \u0b9a\u0bc7\u0bb5\u0bc8\u0baf\u0bbf\u0bb2\u0bcd \u0b9a\u0bbf\u0bb0\u0bbf\u0baa\u0bcd\u0baa\u0bc1 \u0b85\u0bb5\u0b9a\u0bbf\u0baf\u0bae\u0bcd: \u0b85\u0bb2\u0bcd\u0bb2\u0ba4\u0bc1 \u0ba8\u0bb2\u0bcd\u0bb2\u0ba4\u0bc1",
      "author": "\u0ba4\u0bc6\u0bb0\u0bbf\u0baf\u0bb5\u0bbf\u0bb2\u0bcd\u0bb2\u0bc8",
      "body_lines": [
        "\u0baa\u0bc1\u0ba9\u0bcd\u0ba9\u0b95\u0bc8\u0baf\u0bc1\u0b9f\u0ba9\u0bcd \u0bae\u0b95\u0bcd\u0b95\u0bb3\u0bc1\u0b95\u0bcd\u0b95\u0bc1 \u0b9a\u0bc7\u0bb5\u0bc8 \u0b9a\u0bc6\u0baf\u0bcd\u0baf\u0bbe\u0ba4 \u0b85\u0bb0\u0b9a\u0bc1 \u0b8a\u0bb4\u0bbf\u0baf\u0bb0\u0bcd\u0b95\u0bb3\u0bc1\u0b95\u0bcd\u0b95\u0bc1 \u0b85\u0baa\u0bb0\u0bbe\u0ba4\u0bae\u0bcd \u0bb5\u0bbf\u0ba4\u0bbf\u0b95\u0bcd\u0b95\u0baa\u0bcd\u0baa\u0b9f\u0bc1\u0bae\u0bcd \u0b8e\u0ba9 \u0baa\u0bbf\u0bb2\u0bbf\u0baa\u0bcd\u0baa\u0bc8\u0ba9\u0bcd\u0bb8\u0bcd \u0ba8\u0bbe\u0b9f\u0bcd\u0b9f\u0bbf\u0ba9\u0bcd \u0bae\u0bc1\u0bb2\u0bc7\u0ba9\u0bcd \u0ba8\u0b95\u0bb0 \u0bae\u0bc7\u0baf\u0bb0\u0bcd \u0b85\u0bb0\u0bbf\u0bb8\u0bcd\u0b9f\u0bbe\u0b9f\u0bcd\u0b9f\u0bbf\u0bb2\u0bcd \u0b85\u0b95\u0bc1\u0baf\u0bb0\u0bcd \u0ba4\u0bc6\u0bb0\u0bbf\u0bb5\u0bbf\u0ba4\u0bcd\u0ba4\u0bc1\u0bb3\u0bcd\u0bb3\u0bbe\u0bb0\u0bcd.",
        "\u0b85\u0bb0\u0b9a \u0b9a\u0bc7\u0bb5\u0bc8\u0baf\u0bc8 \u0baa\u0bc6\u0bb1\u0bcd\u0bb1\u0bc1\u0b95\u0bcd \u0b95\u0bca\u0bb3\u0bcd\u0bb3 \u0bb5\u0bb0\u0bc1\u0bae\u0bcd \u0bae\u0b95\u0bcd\u0b95\u0bb3\u0bc1\u0b9f\u0ba9\u0bcd \u0ba8\u0b9f\u0bcd\u0baa\u0bc1\u0bb1\u0bb5\u0bbe\u0ba9 \u0b9a\u0bc2\u0bb4\u0bb2\u0bc8 \u0b8f\u0bb1\u0bcd\u0baa\u0b9f\u0bc1\u0ba4\u0bcd\u0ba4\u0bbf \u0b85\u0bb0\u0b9a \u0b9a\u0bc7\u0bb5\u0bc8\u0baf\u0bbf\u0ba9\u0bcd \u0ba4\u0bb0\u0ba4\u0bcd\u0ba4\u0bc8 \u0bae\u0bc7\u0bae\u0bcd\u0baa\u0b9f\u0bc1\u0ba4\u0bcd\u0ba4\u0bc1\u0bae\u0bcd \u0ba8\u0bcb\u0b95\u0bcd\u0b95\u0bbf\u0bb2\u0bcd \u0b87\u0ba8\u0bcd\u0ba4 \u0ba4\u0bc0\u0bb0\u0bcd\u0bae\u0bbe\u0ba9\u0bae\u0bcd \u0b8e\u0b9f\u0bc1\u0b95\u0bcd\u0b95\u0baa\u0bcd\u0baa\u0b9f\u0bcd\u0b9f\u0bc1\u0bb3\u0bcd\u0bb3\u0ba4\u0bbe\u0b95 \u0bae\u0bc7\u0baf\u0bb0\u0bcd \u0b9a\u0bc1\u0b9f\u0bcd\u0b9f\u0bbf\u0b95\u0bcd\u0b95\u0bbe\u0b9f\u0bcd\u0b9f\u0bbf\u0ba9\u0bbe\u0bb0\u0bcd.",
        "\u0baa\u0bca\u0ba4\u0bc1\u0baa\u0bcd\u0baa\u0ba3\u0bbf\u0ba4\u0bcd\u0ba4\u0bc1\u0bb1\u0bc8\u0baf\u0bbf\u0bb2\u0bcd \u0bae\u0b95\u0bcd\u0b95\u0bb3\u0bcd \u0bb5\u0bbf\u0bb0\u0b95\u0bcd\u0ba4\u0bbf\u0baf\u0b9f\u0bc8\u0ba8\u0bcd\u0ba4\u0bc1\u0bb3\u0bcd\u0bb3\u0ba9\u0bb0\u0bcd. \u0baa\u0bca\u0ba4\u0bc1\u0baa\u0bcd\u0baa\u0ba3\u0bbf\u0ba4\u0bcd\u0ba4\u0bc1\u0bb1\u0bc8 \u0b85\u0ba4\u0bbf\u0b95\u0bbe\u0bb0\u0bbf\u0b95\u0bb3\u0bbf\u0b9f\u0bae\u0bcd \u0baa\u0ba3\u0bbf \u0ba8\u0bbf\u0bae\u0bbf\u0ba4\u0bcd\u0ba4\u0bae\u0bcd \u0b9a\u0bc6\u0bb2\u0bcd\u0bb5\u0ba4\u0bbe\u0b95 \u0baa\u0bca\u0ba4\u0bc1\u0bae\u0b95\u0bcd\u0b95\u0bb3\u0bcd \u0baa\u0bb2\u0bb0\u0bcd \u0baa\u0bc1\u0b95\u0bbe\u0bb0\u0bcd \u0ba4\u0bc6\u0bb0\u0bbf\u0bb5\u0bbf\u0b95\u0bcd\u0b95\u0bbf\u0ba9\u0bcd\u0bb1\u0ba9\u0bb0\u0bcd. \u0baa\u0bca\u0ba4\u0bc1\u0b9a\u0bcd \u0b9a\u0bc7\u0bb5\u0bc8\u0baf\u0bbf\u0bb2\u0bcd \u0ba8\u0bae\u0bcd\u0baa\u0bbf\u0b95\u0bcd\u0b95\u0bc8 \u0b87\u0bb4\u0ba8\u0bcd\u0ba4\u0bc1\u0bb5\u0bbf\u0b9f\u0bcd\u0b9f\u0ba4\u0bc1. \u0b8e\u0ba9\u0bb5\u0bc7 \u0b87\u0ba9\u0bbf\u0bae\u0bc7\u0bb2\u0bbe\u0bb5\u0ba4\u0bc1 \u0b85\u0bb0\u0b9a \u0b89\u0ba4\u0bcd\u0ba4\u0bbf\u0baf\u0bcb\u0b95\u0ba4\u0bcd\u0ba4\u0bb0\u0bcd\u0b95\u0bb3\u0bcd \u0bae\u0b95\u0bcd\u0b95\u0bb3\u0bc1\u0b95\u0bcd\u0b95\u0bc1 \u0b9a\u0bc7\u0bb5\u0bc8\u0b95\u0bb3\u0bc8 \u0bb5\u0bb4\u0b99\u0bcd\u0b95\u0bc1\u0bae\u0bcd\u0baa\u0bcb\u0ba4\u0bc1 \u0baa\u0bc1\u0ba9\u0bcd\u0ba9\u0b95\u0bc8\u0baf\u0bc1\u0b9f\u0ba9\u0bcd \u0b9a\u0bc6\u0baf\u0bcd\u0baf \u0bb5\u0bc7\u0ba3\u0bcd\u0b9f\u0bc1\u0bae\u0bcd. \u0bae\u0b95\u0bcd\u0b95\u0bb3\u0bbf\u0ba9\u0bcd \u0baa\u0bc1\u0b95\u0bbe\u0bb0\u0bcd\u0b95\u0bb3\u0bc1\u0b95\u0bcd\u0b95\u0bcb, \u0baa\u0bc1\u0b95\u0bbe\u0bb0\u0bcd\u0b95\u0bb3\u0bc1\u0b95\u0bcd\u0b95\u0bcb \u0b87\u0b9f\u0bae\u0bbf\u0bb2\u0bcd\u0bb2\u0bc8. \u0b85\u0baa\u0bcd\u0baa\u0b9f\u0bbf \u0baa\u0bc1\u0b95\u0bbe\u0bb0\u0bcd\u0b95\u0bb3\u0bcd \u0bb5\u0ba8\u0bcd\u0ba4\u0bbe\u0bb2\u0bcd \u0b9a\u0bae\u0bcd\u0baa\u0ba8\u0bcd\u0ba4\u0baa\u0bcd\u0baa\u0b9f\u0bcd\u0b9f \u0b85\u0bb0\u0b9a\u0bc1 \u0b85\u0ba4\u0bbf\u0b95\u0bbe\u0bb0\u0bbf\u0b95\u0bb3\u0bcd \u0ba4\u0ba3\u0bcd\u0b9f\u0bbf\u0b95\u0bcd\u0b95\u0baa\u0bcd\u0baa\u0b9f\u0bc1\u0bb5\u0bbe\u0bb0\u0bcd\u0b95\u0bb3\u0bcd. \u0b87\u0ba8\u0bcd\u0ba4 \u0b89\u0ba4\u0bcd\u0ba4\u0bb0\u0bb5\u0bc8 \u0bae\u0ba4\u0bbf\u0b95\u0bcd\u0b95\u0bbe\u0ba4 \u0b85\u0bb0\u0b9a\u0bc1 \u0b8a\u0bb4\u0bbf\u0baf\u0bb0\u0bcd\u0b95\u0bb3\u0bcd \u0b85\u0bb2\u0bcd\u0bb2\u0ba4\u0bc1 \u0b85\u0ba4\u0bbf\u0b95\u0bbe\u0bb0\u0bbf\u0b95\u0bb3\u0bcd \u0b85\u0ba4\u0bbf\u0b95\u0baa\u0b9f\u0bcd\u0b9a\u0bae\u0bbe\u0b95 6 \u0bae\u0bbe\u0ba4 \u0b9a\u0bae\u0bcd\u0baa\u0bb3\u0ba4\u0bcd\u0ba4\u0bbf\u0bb1\u0bcd\u0b95\u0bc1 \u0b9a\u0bae\u0bae\u0bbe\u0ba9 \u0b85\u0baa\u0bb0\u0bbe\u0ba4\u0bae\u0bcd \u0b85\u0bb2\u0bcd\u0bb2\u0ba4\u0bc1 \u0baa\u0ba3\u0bbf\u0baf\u0bbf\u0bb2\u0bcd \u0b87\u0bb0\u0bc1\u0ba8\u0bcd\u0ba4\u0bc1 \u0b87\u0b9f\u0bc8\u0ba8\u0bc0\u0b95\u0bcd\u0b95\u0bae\u0bcd \u0b9a\u0bc6\u0baf\u0bcd\u0baf\u0baa\u0bcd\u0baa\u0b9f\u0bc1\u0bb5\u0bbe\u0bb0\u0bcd\u0b95\u0bb3\u0bcd \u0b8e\u0ba9 \u0bae\u0bc7\u0baf\u0bb0\u0bcd \u0b85\u0bb0\u0bbf\u0bb8\u0bcd\u0b9f\u0bbe\u0b9f\u0bcd\u0b9f\u0bbf\u0bb2\u0bcd \u0b85\u0b95\u0bc1\u0baf\u0bb0\u0bcd \u0bb5\u0bbf\u0bb3\u0b95\u0bcd\u0b95\u0bae\u0bb3\u0bbf\u0ba4\u0bcd\u0ba4\u0bc1\u0bb3\u0bcd\u0bb3\u0bbe\u0bb0\u0bcd.",
        "\u0b85\u0bb0\u0bbf\u0bb8\u0bcd\u0b9f\u0bbe\u0b9f\u0bcd\u0b9f\u0bbf\u0bb2\u0bcd \u0b85\u0b95\u0bc1\u0baf\u0bb0\u0bcd 8 \u0bae\u0bbe\u0ba4\u0b99\u0bcd\u0b95\u0bb3\u0bcd \u0bae\u0bc7\u0baf\u0bb0\u0bbe\u0b95 \u0b87\u0bb0\u0bc1\u0ba8\u0bcd\u0ba4\u0bc1\u0bb3\u0bcd\u0bb3\u0bbe\u0bb0\u0bcd. \u0bae\u0bc7\u0baf\u0bb0\u0bcd \u0baa\u0ba4\u0bb5\u0bbf\u0b95\u0bcd\u0b95\u0bc1 \u0baa\u0bcb\u0b9f\u0bcd\u0b9f\u0bbf\u0baf\u0bbf\u0b9f\u0bc1\u0bae\u0bcd \u0baa\u0bcb\u0ba4\u0bc1 \u0b95\u0bc2\u0b9f, \u0b85\u0bb0\u0bbf\u0bb8\u0bcd\u0b9f\u0bbe\u0b9f\u0bcd\u0b9f\u0bbf\u0bb2\u0bcd \u0b85\u0b95\u0bc1\u0baf\u0bb0\u0bcd \u0b92\u0bb0\u0bc1 \u0ba4\u0bb0\u0bae\u0bbe\u0ba9 \u0baa\u0bca\u0ba4\u0bc1 \u0b8a\u0bb4\u0bbf\u0baf\u0bb0\u0bc8 \u0b89\u0bb0\u0bc1\u0bb5\u0bbe\u0b95\u0bcd\u0b95 \u0b8e\u0ba4\u0bbf\u0bb0\u0bcd\u0ba4\u0bcd\u0ba4\u0bbe\u0bb0\u0bcd. \u0b85\u0ba4\u0ba9\u0bcd\u0baa\u0b9f\u0bbf, \u0bae\u0b95\u0bcd\u0b95\u0bb3\u0bbf\u0b9f\u0bae\u0bcd \u0b87\u0bb0\u0bc1\u0ba8\u0bcd\u0ba4\u0bc1 \u0bb5\u0bb0\u0bc1\u0bae\u0bcd \u0baa\u0bc1\u0b95\u0bbe\u0bb0\u0bcd\u0b95\u0bb3\u0bc8 \u0b95\u0bb0\u0bc1\u0ba4\u0bcd\u0ba4\u0bbf\u0bb2\u0bcd \u0b95\u0bca\u0ba3\u0bcd\u0b9f\u0bc1, \u0b87\u0ba8\u0bcd\u0ba4 '\u0bb8\u0bcd\u0bae\u0bc8\u0bb2\u0bcd \u0baa\u0bbe\u0bb2\u0bbf\u0b9a\u0bbf'\u0baf\u0bc8 \u0b85\u0bb1\u0bbf\u0bae\u0bc1\u0b95\u0bae\u0bcd \u0b9a\u0bc6\u0baf\u0bcd\u0ba4\u0bc1\u0bb3\u0bcd\u0bb3\u0bbe\u0bb0\u0bcd.",
        "\u0bae\u0bc0\u0ba9\u0bb5\u0bb0\u0bcd\u0b95\u0bb3\u0bcd, \u0bb5\u0bbf\u0bb5\u0b9a\u0bbe\u0baf\u0bae\u0bcd \u0b9a\u0bc6\u0baf\u0bcd\u0baa\u0bb5\u0bb0\u0bcd\u0b95\u0bb3\u0bcd \u0bae\u0bb1\u0bcd\u0bb1\u0bc1\u0bae\u0bcd \u0ba4\u0bca\u0bb2\u0bc8\u0ba4\u0bc2\u0bb0 \u0baa\u0b95\u0bc1\u0ba4\u0bbf\u0b95\u0bb3\u0bbf\u0bb2\u0bcd \u0b87\u0bb0\u0bc1\u0ba8\u0bcd\u0ba4\u0bc1 \u0bae\u0b95\u0bcd\u0b95\u0bb3\u0bcd \u0ba4\u0b99\u0bcd\u0b95\u0bb3\u0bcd \u0bb5\u0bc7\u0bb2\u0bc8\u0b95\u0bcd\u0b95\u0bbe\u0b95 \u0ba8\u0b95\u0bb0\u0ba4\u0bcd\u0ba4\u0bbf\u0bb1\u0bcd\u0b95\u0bc1 \u0bb5\u0bb0\u0bc1\u0b95\u0bbf\u0bb1\u0bbe\u0bb0\u0bcd\u0b95\u0bb3\u0bcd. \u0bb5\u0bc7\u0bb2\u0bc8\u0baf\u0bc8 \u0bae\u0bc1\u0b9f\u0bbf\u0b95\u0bcd\u0b95 \u0bae\u0ba3\u0bbf\u0b95\u0bcd\u0b95\u0ba3\u0b95\u0bcd\u0b95\u0bbf\u0bb2\u0bcd \u0bae\u0bc1\u0bae\u0bcd\u0bae\u0bc1\u0bb0\u0bae\u0bbe\u0b95 \u0b85\u0bb2\u0bc8\u0b95\u0bbf\u0bb1\u0bbe\u0bb0\u0bcd\u0b95\u0bb3\u0bcd. \u0b85\u0bb0\u0b9a\u0bc1 \u0b8a\u0bb4\u0bbf\u0baf\u0bb0\u0bcd\u0b95\u0bb3\u0bbf\u0ba9\u0bcd \u0b85\u0bb2\u0bc8\u0b95\u0bcd\u0b95\u0bb4\u0bbf\u0baa\u0bcd\u0baa\u0bc1 \u0b95\u0bc1\u0bb1\u0bbf\u0ba4\u0bcd\u0ba4\u0bc1 \u0ba4\u0bbf\u0ba9\u0bae\u0bc1\u0bae\u0bcd \u0baa\u0bc1\u0b95\u0bbe\u0bb0\u0bcd\u0b95\u0bb3\u0bcd \u0bb5\u0bb0\u0bc1\u0b95\u0bbf\u0ba9\u0bcd\u0bb1\u0ba9. \u0b85\u0ba4\u0ba9\u0bcd\u0baa\u0b9f\u0bbf, \u0bae\u0b95\u0bcd\u0b95\u0bb3\u0bcd \u0ba4\u0bbf\u0bb0\u0bc1\u0baa\u0bcd\u0ba4\u0bbf \u0b85\u0b9f\u0bc8\u0baf\u0bc1\u0bae\u0bcd \u0bb5\u0b95\u0bc8\u0baf\u0bbf\u0bb2\u0bcd \u0b9a\u0bc7\u0bb5\u0bc8 \u0bb5\u0bb4\u0b99\u0bcd\u0b95 \u0bb5\u0bc7\u0ba3\u0bcd\u0b9f\u0bc1\u0bae\u0bcd\u2019\u2019 \u0b8e\u0ba9\u0bcd\u0bb1\u0bbe\u0bb0\u0bcd."
      ],
      "title_ents": [],
      "body_line_ents_list": [
        [
          {
            "text": "\u0b85\u0bb0\u0bbf\u0bb8\u0bcd\u0b9f\u0bbe\u0b9f\u0bcd\u0b9f\u0bbf\u0bb2\u0bcd \u0b85\u0b95\u0bc1\u0baf\u0bb0\u0bcd",
            "label": "PERSON"
          },
          {
            "text": "\u0bae\u0bc1\u0bb2\u0bc7\u0ba9\u0bcd",
            "label": "GPE"
          },
          {
            "text": "\u0baa\u0bbf\u0bb2\u0bbf\u0baa\u0bcd\u0baa\u0bc8\u0ba9\u0bcd\u0bb8\u0bcd",
            "label": "GPE"
          }
        ],
        [],
        [
          {
            "text": "6 \u0bae\u0bbe\u0ba4\u0b99\u0bcd\u0b95\u0bb3\u0bcd'",
            "label": "DATE"
          },
          {
            "text": "\u0b85\u0bb0\u0bbf\u0bb8\u0bcd\u0b9f\u0bbe\u0b9f\u0bcd\u0b9f\u0bbf\u0bb2\u0bcd \u0b85\u0b95\u0bc1\u0baf\u0bb0\u0bcd",
            "label": "PERSON"
          }
        ],
        [
          {
            "text": "\u0b85\u0bb0\u0bbf\u0bb8\u0bcd\u0b9f\u0bbe\u0b9f\u0bcd\u0b9f\u0bbf\u0bb2\u0bcd \u0b85\u0b95\u0bc1\u0baf\u0bb0\u0bcd",
            "label": "PERSON"
          },
          {
            "text": "8 \u0bae\u0bbe\u0ba4\u0b99\u0bcd\u0b95\u0bb3\u0bcd",
            "label": "DATE"
          },
          {
            "text": "\u0b85\u0bb0\u0bbf\u0bb8\u0bcd\u0b9f\u0bbe\u0b9f\u0bcd\u0b9f\u0bbf\u0bb2\u0bcd \u0b85\u0b95\u0bc1\u0baf\u0bb0\u0bcd",
            "label": "PERSON"
          }
        ],
        [
          {
            "text": "\u0ba4\u0bbf\u0ba9\u0b9a\u0bb0\u0bbf",
            "label": "DATE"
          }
        ]
      ]
    }
  }
}