{
  "newspaper_id": "lankadeepa-lk",
  "url": "https://www.lankadeepa.lk/latest_news/\u0dc0\u0dd2\u0daf\u0dca\u200d\u0dba\u0ddd\u0daf\u0dba-\u0dc3\u0dcf\u0dc4\u0dd2\u0dad\u0dca\u200d\u0dba-\u0dc3\u0db8\u0dca\u0db8\u0dcf\u0db1-\u0dc3\u0db3\u0dc4\u0dcf-\u0db1\u0dd2\u0dbb\u0dca\u0daf\u0dda\u0dc1\u0dd2\u0dad-\u0d9a\u0dd8\u0dad\u0dd3\u0db1\u0dca-\u0db4\u0dca\u200d\u0dbb\u0d9a\u0dcf\u0dc1\u0dba\u0da7-\u0db4\u0dad\u0dca\u0d9a\u0dd9\u0dbb\u0dda/1-618732",
  "time_ut": 1661415689,
  "original_lang": "si",
  "original_title": "\u0dc0\u0dd2\u0daf\u0dca\u200d\u0dba\u0ddd\u0daf\u0dba \u0dc3\u0dcf\u0dc4\u0dd2\u0dad\u0dca\u200d\u0dba \u0dc3\u0db8\u0dca\u0db8\u0dcf\u0db1 \u0dc3\u0db3\u0dc4\u0dcf \u0db1\u0dd2\u0dbb\u0dca\u0daf\u0dda\u0dc1\u0dd2\u0dad \u0d9a\u0dd8\u0dad\u0dd3\u0db1\u0dca \u0db4\u0dca\u200d\u0dbb\u0d9a\u0dcf\u0dc1\u0dba\u0da7 \u0db4\u0dad\u0dca\u0d9a\u0dd9\u0dbb\u0dda",
  "text_idx": {
    "en": {
      "title": "Recommended works for Vidyodaya Sahitya Awards will be announced",
      "author": "unknown",
      "body_lines": [
        "The Vidyodaya Sahitya Award Ceremony will be held at Sumangala Hall of Sri Jayawardenepura University on September 1st at 3:00 PM and the works recommended for the final round of awards have been announced by now.",
        "Awards will be presented for the best novel, short story collection, poetry collection, lyric collection, column collection and academic collection of the year.",
        "This year's best novel of the year is 'Hin Dos Male' written by Mrs. Sepali Mayadunne, 'Sandhyanandaya' written by Mr. Keerthi Welisarage, 'My Chicago Heart' written by Mrs. Shamel Jayakodi, 'Premanishansa' written by Mr. Chandraratne Bandara and 'Nakula' written by Mr. Eric Ilayaparachchi. Muni' novels have been recommended.",
        "Also for the award for the best short story collection of the year, 'International Confessions' by Mr. Eric Ilayapaarachchi, 'Because of being the daughter of a toilet washer' by Mr. Mahinda Ratnayake, 'Gini Some and other short stories' by Mr. Upali Ubayasekara, 'Memories of Man Mawathaka Miminilla' by Mr. Malindu Kavinda Kumarasinghe and Mr. Prince Senadheera's works 'Black Tall Man' have been recommended.",
        "Five works have been nominated for the best poetry anthology of the year award, Mr. Lakshantha Athukorala's 'Liyasav Lihi Gaya Ganasamadulu', Mrs. Sureka Samarasena's 'Vam Piyavura', Mrs. Anuradha Nilmini's 'Nari Sutra (Poetry), Mrs. Sandarasee Sudusingha's 'Fire-hit Wings', Eric Ilayaparachi's 'Prometheus Island' is one of those works.",
        "For the best lyric collection of the year, the three works 'Pramayai Manaram' written by Mrs. Yamuna Malini Perera, 'Pama Vee Pipunu Mal Mihanai' written by Mr. Wasantha Kumara Kobawaka, and 'Sandamadala Vee' by Pallegama Hemarathana Thero have been recommended, and the best columns of the year. Recommended works for the anthology are 'Vannige Kolama' by Mr. Nayanasena Vanninayake, 'Close Images' by Mr. Buddhadasa Galappatti and 'Ninnada' by Harshini Pushpamala Arachchi.",
        "For the best academic collection of the year award, Dr. Premasiri Nagasinghe's 'Sinhala Upasakapnalankaraya Edition and Critical Study', Mr. Saman Panapitiya's 'Sinhala Folk Singing Styles', Senior Professor Mahinda Somathilaka's 'Keulgama Dalada Chama Maligaya', Mahinda K. Five works have been recommended, Mr. Wimalasiri's 'Kadawara Adahima' and Mrs. Sandhya Kahandagama's 'Sankya Purana'.",
        "Organized by the faculty committee of the Faculty of Humanities and Social Sciences of the University of Sri Jayawardenepura, this literary award ceremony is being held for the 13th time this year.",
        "This time Mr. Ananda Tissa Kumara, Senior Professor of Sinhala Department of Sri Jayewardenepura University will be the chief guest."
      ],
      "title_ents": [],
      "body_line_ents_list": [
        [
          {
            "text": "Sumangala Hall of Sri Jayawardenepura University",
            "label": "FAC"
          },
          {
            "text": "September 1st",
            "label": "DATE"
          },
          {
            "text": "3:00 PM",
            "label": "TIME"
          }
        ],
        [
          {
            "text": "the year",
            "label": "DATE"
          }
        ],
        [
          {
            "text": "year",
            "label": "DATE"
          },
          {
            "text": "the year",
            "label": "DATE"
          },
          {
            "text": "Sepali Mayadunne",
            "label": "PERSON"
          },
          {
            "text": "Sandhyanandaya",
            "label": "PERSON"
          },
          {
            "text": "Keerthi Welisarage",
            "label": "PERSON"
          },
          {
            "text": "Shamel Jayakodi",
            "label": "PERSON"
          },
          {
            "text": "Premanishansa",
            "label": "PERSON"
          },
          {
            "text": "Chandraratne Bandara",
            "label": "PERSON"
          },
          {
            "text": "Nakula",
            "label": "PERSON"
          },
          {
            "text": "Eric Ilayaparachchi",
            "label": "PERSON"
          }
        ],
        [
          {
            "text": "the year",
            "label": "DATE"
          },
          {
            "text": "'International Confessions'",
            "label": "ORG"
          },
          {
            "text": "Eric Ilayapaarachchi",
            "label": "PERSON"
          },
          {
            "text": "Mahinda Ratnayake",
            "label": "PERSON"
          },
          {
            "text": "Upali Ubayasekara",
            "label": "PERSON"
          },
          {
            "text": "Mawathaka Miminilla'",
            "label": "PERSON"
          },
          {
            "text": "Malindu Kavinda Kumarasinghe",
            "label": "PERSON"
          },
          {
            "text": "Prince Senadheera",
            "label": "PERSON"
          },
          {
            "text": "Black Tall Man'",
            "label": "WORK_OF_ART"
          }
        ],
        [
          {
            "text": "Five",
            "label": "CARDINAL"
          },
          {
            "text": "the year award",
            "label": "DATE"
          },
          {
            "text": "Lakshantha Athukorala's",
            "label": "PERSON"
          },
          {
            "text": "Liyasav Lihi",
            "label": "PERSON"
          },
          {
            "text": "Gaya Ganasamadulu'",
            "label": "PERSON"
          },
          {
            "text": "Sureka Samarasena",
            "label": "PERSON"
          },
          {
            "text": "'Vam Piyavura'",
            "label": "WORK_OF_ART"
          },
          {
            "text": "Anuradha Nilmini",
            "label": "PERSON"
          },
          {
            "text": "'Nari Sutra (Poetry",
            "label": "WORK_OF_ART"
          },
          {
            "text": "Sandarasee Sudusingha's",
            "label": "PERSON"
          },
          {
            "text": "Wings'",
            "label": "ORG"
          },
          {
            "text": "Eric Ilayaparachi's",
            "label": "PERSON"
          },
          {
            "text": "Prometheus Island",
            "label": "LOC"
          }
        ],
        [
          {
            "text": "the year",
            "label": "DATE"
          },
          {
            "text": "three",
            "label": "CARDINAL"
          },
          {
            "text": "Pramayai Manaram'",
            "label": "WORK_OF_ART"
          },
          {
            "text": "Yamuna Malini Perera",
            "label": "PERSON"
          },
          {
            "text": "Wasantha",
            "label": "PERSON"
          },
          {
            "text": "Kumara Kobawaka",
            "label": "PERSON"
          },
          {
            "text": "Sandamadala Vee'",
            "label": "PERSON"
          },
          {
            "text": "Pallegama",
            "label": "GPE"
          },
          {
            "text": "Hemarathana Thero",
            "label": "PERSON"
          },
          {
            "text": "the year",
            "label": "DATE"
          },
          {
            "text": "Vannige Kolama'",
            "label": "PERSON"
          },
          {
            "text": "Nayanasena Vanninayake",
            "label": "PERSON"
          },
          {
            "text": "Buddhadasa Galappatti",
            "label": "PERSON"
          },
          {
            "text": "Ninnada",
            "label": "PERSON"
          },
          {
            "text": "Harshini Pushpamala Arachchi",
            "label": "PERSON"
          }
        ],
        [
          {
            "text": "the year award",
            "label": "DATE"
          },
          {
            "text": "Premasiri Nagasinghe",
            "label": "PERSON"
          },
          {
            "text": "Sinhala Upasakapnalankaraya Edition and Critical Study'",
            "label": "WORK_OF_ART"
          },
          {
            "text": "Saman Panapitiya",
            "label": "PERSON"
          },
          {
            "text": "Mahinda Somathilaka's",
            "label": "PERSON"
          },
          {
            "text": "Keulgama Dalada",
            "label": "PERSON"
          },
          {
            "text": "Mahinda K. Five",
            "label": "ORG"
          },
          {
            "text": "Wimalasiri",
            "label": "PERSON"
          },
          {
            "text": "Kadawara Adahima'",
            "label": "PERSON"
          },
          {
            "text": "Sandhya Kahandagama's",
            "label": "PERSON"
          },
          {
            "text": "Sankya Purana'",
            "label": "WORK_OF_ART"
          }
        ],
        [
          {
            "text": "the faculty committee of the Faculty of Humanities and Social Sciences",
            "label": "ORG"
          },
          {
            "text": "the University of Sri Jayawardenepura",
            "label": "ORG"
          },
          {
            "text": "the 13th",
            "label": "DATE"
          },
          {
            "text": "this year",
            "label": "DATE"
          }
        ],
        [
          {
            "text": "Ananda Tissa Kumara",
            "label": "PERSON"
          },
          {
            "text": "Sinhala Department of Sri Jayewardenepura University",
            "label": "ORG"
          }
        ]
      ]
    },
    "si": {
      "title": "\u0dc0\u0dd2\u0daf\u0dca\u200d\u0dba\u0ddd\u0daf\u0dba \u0dc3\u0dcf\u0dc4\u0dd2\u0dad\u0dca\u200d\u0dba \u0dc3\u0db8\u0dca\u0db8\u0dcf\u0db1 \u0dc3\u0db3\u0dc4\u0dcf \u0db1\u0dd2\u0dbb\u0dca\u0daf\u0dda\u0dc1\u0dd2\u0dad \u0d9a\u0dd8\u0dad\u0dd3\u0db1\u0dca \u0db4\u0dca\u200d\u0dbb\u0d9a\u0dcf\u0dc1\u0dba\u0da7 \u0db4\u0dad\u0dca\u0d9a\u0dd9\u0dbb\u0dda",
      "author": "unknown",
      "body_lines": [
        "\u0dc0\u0dd2\u0daf\u0dca\u200d\u0dba\u0ddd\u0daf\u0dba \u0dc3\u0dcf\u0dc4\u0dd2\u0dad\u0dca\u200d\u0dba \u0dc3\u0db8\u0dca\u0db8\u0dcf\u0db1 \u0d8b\u0dc5\u0dd9\u0dbd \u0dc1\u0dca\u200d\u0dbb\u0dd3 \u0da2\u0dba\u0dc0\u0dbb\u0dca\u0db0\u0db1\u0db4\u0dd4\u0dbb \u0dc0\u0dd2\u0dc1\u0dca\u0dc0 \u0dc0\u0dd2\u0daf\u0dca\u200d\u0dba\u0dcf\u0dbd\u0dba\u0dd3\u0dba \u0dc3\u0dd4\u0db8\u0d82\u0d9c\u0dbd \u0dc1\u0dcf\u0dbd\u0dcf\u0dc0\u0dda\u0daf\u0dd3 \u0dc3\u0dd0\u0db4\u0dca\u0dad\u0dd0\u0db8\u0dca\u0db6\u0dbb\u0dca \u0db8\u0dc3 1 \u0dc0\u0dd0\u0db1\u0dd2\u0daf\u0dcf \u0db4\u0dc3\u0dca\u0dc0\u0dbb\u0dd4 3.00\u0da7 \u0db4\u0dd0\u0dc0\u0dd0\u0dad\u0dca\u0dc0\u0dd9\u0db1 \u0d85\u0dad\u0dbb \u0d91\u0dc4\u0dd2 \u0dc3\u0db8\u0dca\u0db8\u0dcf\u0db1 \u0dc3\u0db3\u0dc4\u0dcf \u0d85\u0dc0\u0dc3\u0db1\u0dca \u0dc0\u0da7\u0dba\u0da7 \u0db1\u0dd2\u0dbb\u0dca\u0daf\u0dda\u0dc1\u0dd2\u0dad \u0d9a\u0dd8\u0dad\u0dd3\u0db1\u0dca \u0db8\u0dda \u0dc0\u0db1 \u0dc0\u0dd2\u0da7 \u0db4\u0dca\u200d\u0dbb\u0d9a\u0dcf\u0dc1\u0dba\u0da7 \u0db4\u0dad\u0dca\u0d9a\u0dbb \u0d87\u0dad.",
        "\u0dc0\u0dc3\u0dbb\u0dda \u0dc0\u0dd2\u0dc1\u0dd2\u0dc2\u0dca\u0da7\u0dad\u0db8 \u0db1\u0dc0\u0d9a\u0dad\u0dcf\u0dc0, \u0d9a\u0dd9\u0da7\u0dd2\u0d9a\u0dad\u0dcf \u0dc3\u0d82\u0d9c\u0dca\u200d\u0dbb\u0dc4\u0dba, \u0db4\u0daf\u0dca\u200d\u0dba \u0dc3\u0d82\u0d9c\u0dca\u200d\u0dbb\u0dc4\u0dba, \u0d9c\u0dda\u0dba \u0db4\u0daf \u0dc3\u0d82\u0d9c\u0dca\u200d\u0dbb\u0dc4\u0dba, \u0dad\u0dd3\u0dbb\u0dd4 \u0dbd\u0dd2\u0db4\u0dd2 \u0dc3\u0d82\u0d9c\u0dca\u200d\u0dbb\u0dc4\u0dba \u0dc3\u0dc4 \u0dc1\u0dcf\u0dc3\u0dca\u0dad\u0dca\u200d\u0dbb\u0dd3\u0dba \u0dc3\u0d82\u0d9c\u0dca\u200d\u0dbb\u0dc4\u0dba \u0dc3\u0db3\u0dc4\u0dcf \u0db8\u0dd9\u0dc4\u0dd2\u0daf\u0dd3 \u0dc3\u0db8\u0dca\u0db8\u0dcf\u0db1 \u0db4\u0dd2\u0dbb\u0dd2\u0db1\u0dd0\u0db8\u0dda.",
        "\u0db8\u0dd9\u0dc0\u0dbb \u0dc0\u0dc3\u0dbb\u0dda \u0dc0\u0dd2\u0dc1\u0dd2\u0dc2\u0dca\u0da7\u0dad\u0db8 \u0db1\u0dc0\u0d9a\u0dad\u0dcf\u0dc0 \u0dc3\u0db3\u0dc4\u0dcf \u0dc3\u0dda\u0db4\u0dcf\u0dbd\u0dd2 \u0db8\u0dcf\u0dba\u0dcf\u0daf\u0dd4\u0db1\u0dca\u0db1\u0dda \u0db8\u0dc4\u0dad\u0dca\u0db8\u0dd2\u0dba \u0dbb\u0da0\u0db1\u0dcf \u0d9a\u0dc5 \u2018\u0dc4\u0dd2\u0db1\u0dca \u0daf\u0ddc\u0dc3\u0dca \u0db8\u0dcf\u0dbd\u0dda\u2019, \u0d9a\u0dd3\u0dbb\u0dca\u0dad\u0dd2 \u0dc0\u0dd0\u0dbd\u0dd2\u0dc3\u0dbb\u0d9c\u0dda \u0db8\u0dc4\u0dad\u0dcf \u0dbb\u0da0\u0db1\u0dcf \u0d9a\u0dc5 \u2018\u0dc3\u0db1\u0dca\u0db0\u0dca\u200d\u0dba\u0dcf\u0db1\u0db1\u0dca\u0daf\u0dba\u2019, \u0dc1\u0db8\u0dd9\u0dbd\u0dca \u0da2\u0dba\u0d9a\u0ddc\u0da9\u0dd2 \u0db8\u0dc4\u0dad\u0dca\u0db8\u0dd2\u0dba \u0dbb\u0da0\u0db1\u0dcf \u0d9a\u0dc5 \u2018\u0db8\u0d9c\u0dda \u0da0\u0dd2\u0d9a\u0dcf\u0d9c\u0ddd \u0dc4\u0daf\u0dc0\u0dad\u2019, \u0da0\u0db1\u0dca\u0daf\u0dca\u200d\u0dbb\u0dbb\u0dad\u0dca\u0db1 \u0db6\u0dab\u0dca\u0da9\u0dcf\u0dbb \u0db8\u0dc4\u0dad\u0dcf \u0dbb\u0da0\u0db1\u0dcf \u0d9a\u0dc5 \u2018\u0db4\u0dca\u200d\u0dbb\u0dda\u0db8\u0dcf\u0db1\u0dd2\u0dc1\u0d82\u0dc3\u2019 \u0dc3\u0dc4 \u0d91\u0dbb\u0dd2\u0d9a\u0dca \u0d89\u0dbd\u0dba\u0db4\u0dca\u0d86\u0dbb\u0da0\u0dca\u0da0\u0dd2 \u0db8\u0dc4\u0dad\u0dcf\u0d9c\u0dda \u2018\u0db1\u0d9a\u0dd4\u0dbd \u0db8\u0dd4\u0db1\u0dd2\u2019 \u0dba\u0db1 \u0db1\u0dc0\u0d9a\u0dad\u0dcf \u0db1\u0dd2\u0dbb\u0dca\u0daf\u0dda\u0dc1 \u0dc0\u0dd3 \u0d87\u0dad.",
        "\u0d91\u0db8\u0dd9\u0db1\u0dca\u0db8 \u0dc0\u0dc3\u0dbb\u0dda \u0dc0\u0dd2\u0dc1\u0dd2\u0dc2\u0dca\u0da7\u0dad\u0db8 \u0d9a\u0dd9\u0da7\u0dd2 \u0d9a\u0dad\u0dcf \u0dc3\u0d82\u0d9c\u0dca\u200d\u0dbb\u0dc4\u0dba\u0da7 \u0dc4\u0dd2\u0db8\u0dd2 \u0dc3\u0db8\u0dca\u0db8\u0dcf\u0db1\u0dba \u0dc3\u0db3\u0dc4\u0dcf \u0d91\u0dbb\u0dd2\u0d9a\u0dca \u0d89\u0dbd\u0dba\u0db4\u0dca\u0d86\u0dbb\u0da0\u0dca\u0da0\u0dd2 \u0db8\u0dc4\u0dad\u0dcf\u0d9c\u0dda \u2018\u0da2\u0dcf\u0dad\u0dca\u200d\u0dba\u0db1\u0dca\u0dad\u0dbb \u0db4\u0dcf\u0db4\u0ddc\u0da0\u0dca\u0da0\u0dcf\u0dbb\u0dab\u0dba\u2019, \u0db8\u0dc4\u0dd2\u0db1\u0dca\u0daf \u0dbb\u0dad\u0dca\u0db1\u0dcf\u0dba\u0d9a \u0db8\u0dc4\u0dad\u0dcf\u0d9c\u0dda \u2018\u0dc0\u0dd0\u0dc3\u0dd2\u0d9a\u0dd2\u0dc5\u0dd2 \u0dc3\u0ddd\u0daf\u0db1\u0dca\u0db1\u0dcf\u0d9c\u0dda \u0daf\u0dd4\u0dc0 \u0dc0\u0dd3\u0db8 \u0db1\u0dd2\u0dc3\u0dcf\u2019, \u0d8b\u0db4\u0dcf\u0dbd\u0dd2 \u0d8b\u0db6\u0dba\u0dc3\u0dda\u0d9a\u0dbb \u0db8\u0dc4\u0dad\u0dcf\u0d9c\u0dda \u2018\u0d9c\u0dd2\u0db1\u0dd2 \u0dc3\u0ddd\u0db8\u0dd9 \u0dc3\u0dc4 \u0dad\u0dc0\u0dad\u0dca \u0d9a\u0dd9\u0da7\u0dd2\u0d9a\u0dad\u0dcf\u2019, \u0db8\u0dbd\u0dd2\u0db3\u0dd4 \u0d9a\u0dcf\u0dc0\u0dd2\u0db1\u0dca\u0daf \u0d9a\u0dd4\u0db8\u0dcf\u0dbb\u0dc3\u0dd2\u0d82\u0dc4 \u0db8\u0dc4\u0dad\u0dcf\u0d9c\u0dda \u2018\u0db8\u0d82 \u0db8\u0dcf\u0dc0\u0dad\u0d9a \u0db8\u0dad\u0d9a \u0db8\u0dd2\u0db8\u0dd2\u0dab\u0dd2\u0dbd\u0dca\u0dbd\u2019 \u0dc3\u0dc4 \u0db4\u0dca\u200d\u0dbb\u0dd2\u0db1\u0dca\u0dc3\u0dca \u0dc3\u0dda\u0db1\u0dcf\u0db0\u0dd3\u0dbb \u0db8\u0dc4\u0dad\u0dcf\u0d9c\u0dda \u2018\u0d9a\u0dc5\u0dd4 \u0d8b\u0dc3 \u0db8\u0db1\u0dd4\u0dc3\u0dca\u0dc3\u0dba\u0dd9\u0d9a\u0dca\u2019 \u0dba\u0db1 \u0d9a\u0dd8\u0dad\u0dd3\u0db1\u0dca \u0db1\u0dd2\u0dbb\u0dca\u0daf\u0dda\u0dc1 \u0dc0\u0dd3 \u0dad\u0dd2\u0db6\u0dda.",
        "\u0dc0\u0dc3\u0dbb\u0dda \u0dc0\u0dd2\u0dc1\u0dd2\u0dc2\u0dca\u0da7\u0dad\u0db8 \u0db4\u0daf\u0dca\u200d\u0dba \u0dc3\u0d82\u0d9c\u0dca\u200d\u0dbb\u0dc4\u0dba \u0dc3\u0db8\u0dca\u0db8\u0dcf\u0db1\u0dba \u0dc3\u0db3\u0dc4\u0dcf \u0d9a\u0dd8\u0dad\u0dd2 \u0db4\u0dc4\u0d9a\u0dca \u0db1\u0dd2\u0dbb\u0dca\u0daf\u0dda\u0dc1 \u0dc0\u0dd3 \u0d87\u0dad\u0dd2 \u0d85\u0dad\u0dbb, \u0dbd\u0d9a\u0dca\u0dc1\u0dcf\u0db1\u0dca\u0dad \u0d85\u0dad\u0dd4\u0d9a\u0ddd\u0dbb\u0dbd \u0db8\u0dc4\u0dad\u0dcf\u0d9c\u0dda \u2018\u0dbd\u0dd2\u0dba\u0dc3\u0dd0\u0dc0\u0dca \u0dbd\u0dd2\u0dc4\u0dd3 \u0d9c\u0dd2\u0dba \u0d9c\u0db1\u0dc3\u0dcf\u0db8\u0da9\u0dd4\u0dbd\u0dd4\u2019, \u0dc3\u0dd4\u0dbb\u0dda\u0d9a\u0dcf \u0dc3\u0db8\u0dbb\u0dc3\u0dda\u0db1 \u0db8\u0dc4\u0dad\u0dca\u0db8\u0dd2\u0dba\u0d9c\u0dda \u2018\u0dc0\u0db8\u0dca \u0db4\u0dd2\u0dba\u0dc0\u0dd4\u0dbb\u2019, \u0d85\u0db1\u0dd4\u0dbb\u0dcf\u0db0\u0dcf \u0db1\u0dd2\u0dbd\u0dca\u0db8\u0dd2\u0dab\u0dd2 \u0db8\u0dc4\u0dad\u0dca\u0db8\u0dd2\u0dba\u0d9c\u0dda \u2018\u0db1\u0dcf\u0dbb\u0dd2 \u0dc3\u0dd6\u0dad\u0dca\u200d\u0dbb\u0dba (\u0d9a\u0dcf\u0dc0\u0dca\u200d\u0dba\u0dcf\u0dbd\u0dda\u0d9b\u0dba), \u0dc3\u0db3\u0dbb\u0dd0\u0dc3\u0dd3 \u0dc3\u0dd4\u0daf\u0dd4\u0dc3\u0dd2\u0d82\u0dc4 \u0db8\u0dc4\u0dad\u0dca\u0db8\u0dd2\u0dba\u0d9c\u0dda \u2018\u0d9c\u0dd2\u0db1\u0dd2 \u0dc0\u0dd0\u0daf\u0dd4\u0dab\u0dd4 \u0db4\u0dd2\u0dba\u0dcf\u0db4\u0dad\u0dca\u2019, \u0d91\u0dbb\u0dd2\u0d9a\u0dca \u0d89\u0dbd\u0dba\u0db4\u0dca\u0d86\u0dbb\u0da0\u0dca\u0da0\u0dd2 \u0db8\u0dc4\u0dad\u0dcf\u0d9c\u0dda \u2018\u0db4\u0dca\u200d\u0dbb\u0ddc\u0db8\u0dd2\u0dad\u0dd2\u0dba\u0dc3\u0dca \u0daf\u0dd6\u0db4\u0dad\u2019 \u0d91\u0db8 \u0d9a\u0dd8\u0dad\u0dd3\u0db1\u0dca \u0dc0\u0dda.",
        "\u0dc0\u0dc3\u0dbb\u0dda \u0dc0\u0dd2\u0dc1\u0dd2\u0dc2\u0dca\u0da7\u0dad\u0db8 \u0d9c\u0dda\u0dba \u0db4\u0daf \u0dc3\u0d82\u0d9c\u0dca\u200d\u0dbb\u0dc4\u0dba \u0dc3\u0db3\u0dc4\u0dcf \u0dba\u0db8\u0dd4\u0db1\u0dcf \u0db8\u0dcf\u0dbd\u0dd2\u0db1\u0dd3 \u0db4\u0dd9\u0dbb\u0dda\u0dbb\u0dcf \u0db8\u0dc4\u0dad\u0dca\u0db8\u0dd2\u0dba \u0dbb\u0da0\u0db1\u0dcf \u0d9a\u0dc5 \u2018\u0db4\u0dca\u200d\u0dbb\u0dda\u0db8\u0dba\u0dba\u0dd2 \u0db8\u0db1\u0dbb\u0db8\u0dca\u2019, \u0dc0\u0dc3\u0db1\u0dca\u0dad \u0d9a\u0dd4\u0db8\u0dcf\u0dbb \u0d9a\u0ddc\u0db6\u0dc0\u0d9a \u0db8\u0dc4\u0dad\u0dcf \u0dbb\u0da0\u0db1\u0dcf \u0d9a\u0dc5 \u2018\u0db4\u0db8\u0dcf \u0dc0\u0dd3 \u0db4\u0dd2\u0db4\u0dd4\u0dab\u0dd4 \u0db8\u0dbd\u0dca \u0dc3\u0dd4\u0dc0\u0db3\u0dba\u0dd2\u2019, \u0db4\u0dbd\u0dca\u0dbd\u0dda\u0d9c\u0db8 \u0dc4\u0dda\u0db8\u0dbb\u0dad\u0db1 \u0dc4\u0dd2\u0db8\u0dd2\u0dba\u0db1\u0dca\u0d9c\u0dda \u2018\u0dc3\u0db3\u0db8\u0da9\u0dbd \u0dc0\u0dd3\u2019 \u0dba\u0db1 \u0d9a\u0dd8\u0dad\u0dd3\u0db1\u0dca \u0dad\u0dca\u200d\u0dbb\u0dd2\u0dad\u0dca\u0dc0\u0dba \u0db1\u0dd2\u0dbb\u0dca\u0daf\u0dda\u0dc1 \u0dc0\u0dd3 \u0d87\u0dad\u0dd2 \u0d85\u0dad\u0dbb, \u0dc0\u0dc3\u0dbb\u0dda \u0dc0\u0dd2\u0dc1\u0dd2\u0dc2\u0dca\u0da7\u0dad\u0db8 \u0dad\u0dd3\u0dbb\u0dd4 \u0dbd\u0dd2\u0db4\u0dd2 \u0dc3\u0d82\u0d9c\u0dca\u200d\u0dbb\u0dc4\u0dba \u0dc3\u0db3\u0dc4\u0dcf \u0db1\u0dba\u0db1\u0dc3\u0dda\u0db1 \u0dc0\u0db1\u0dca\u0db1\u0dd2\u0db1\u0dcf\u0dba\u0d9a \u0db8\u0dc4\u0dad\u0dcf\u0d9c\u0dda \u2018\u0dc0\u0db1\u0dca\u0db1\u0dd2\u0d9c\u0dda \u0d9a\u0ddc\u0dbd\u0db8\u2019, \u0db6\u0dd4\u0daf\u0dca\u0db0\u0daf\u0dcf\u0dc3 \u0d9c\u0dbd\u0db4\u0dca\u0db4\u0dad\u0dca\u0dad\u0dd2 \u0db8\u0dc4\u0dad\u0dcf\u0d9c\u0dda \u2018\u0dc3\u0db8\u0dd3\u0db4 \u0dbb\u0dd6\u0db4\u2019 \u0dc3\u0dc4 \u0dc4\u0dbb\u0dca\u0dc2\u0dd2\u0db1\u0dd3 \u0db4\u0dd4\u0dc2\u0dca\u0db4\u0db8\u0dcf\u0dbd\u0dcf \u0d86\u0dbb\u0da0\u0dca\u0da0\u0dd2\u0d9c\u0dda \u2018\u0db1\u0dd2\u0db1\u0dca\u0db1\u0dcf\u0daf\u2019 \u0dba\u0db1 \u0d9a\u0dd8\u0dad\u0dd3\u0db1\u0dca \u0db1\u0dd2\u0dbb\u0dca\u0daf\u0dda\u0dc1\u0dd2\u0dad\u0dba.",
        "\u0dc0\u0dc3\u0dbb\u0dda \u0dc0\u0dd2\u0dc1\u0dd2\u0dc2\u0dca\u0da7\u0dad\u0db8 \u0dc1\u0dcf\u0dc3\u0dca\u0dad\u0dca\u200d\u0dbb\u0dd3\u0dba \u0dc3\u0d82\u0d9c\u0dca\u200d\u0dbb\u0dc4\u0dba \u0dc3\u0db8\u0dca\u0db8\u0dcf\u0db1\u0dba \u0dc3\u0db3\u0dc4\u0dcf \u0d86\u0da0\u0dcf\u0dbb\u0dca\u0dba \u0db4\u0dca\u200d\u0dbb\u0dda\u0db8\u0dc3\u0dd2\u0dbb\u0dd2 \u0db1\u0dcf\u0d9c\u0dc3\u0dd2\u0d82\u0dc4 \u0db8\u0dc4\u0dad\u0dcf\u0d9c\u0dda \u2018\u0dc3\u0dd2\u0d82\u0dc4\u0dbd \u0d8b\u0db4\u0dcf\u0dc3\u0d9a\u0db4\u0dca\u0db1\u0dcf\u0dbd\u0d82\u0d9a\u0dcf\u0dbb\u0dba \u0dc3\u0d82\u0dc3\u0dca\u0d9a\u0dbb\u0dab\u0dba \u0dc3\u0dc4 \u0dc0\u0dd2\u0da0\u0dcf\u0dbb\u0dcf\u0dad\u0dca\u0db8\u0d9a \u0d85\u0db0\u0dca\u200d\u0dba\u0dba\u0db1\u0dba\u0d9a\u0dca\u2019, \u0dc3\u0db8\u0db1\u0dca \u0db4\u0db1\u0dcf\u0db4\u0dd2\u0da7\u0dd2\u0dba \u0db8\u0dc4\u0dad\u0dcf\u0d9c\u0dda \u2018\u0dc3\u0dd2\u0d82\u0dc4\u0dbd \u0da2\u0db1 \u0d9c\u0dcf\u0dba\u0db1 \u0dc1\u0ddb\u0dbd\u0dd3\u2019, \u0da2\u0dca\u200d\u0dba\u0dd9\u0dc2\u0dca\u0da8 \u0db8\u0dc4\u0dcf\u0da0\u0dcf\u0dbb\u0dca\u0dba \u0db8\u0dc4\u0dd2\u0db1\u0dca\u0daf \u0dc3\u0ddd\u0db8\u0dad\u0dd2\u0dbd\u0d9a \u0db8\u0dc4\u0dad\u0dcf \u0dbb\u0da0\u0db1\u0dcf \u0d9a\u0dc5 \u2018\u0d9a\u0dd9\u0dc0\u0dd4\u0dbd\u0dca\u0d9c\u0db8 \u0daf\u0dc5\u0daf\u0dcf \u0d9c\u0db8\u0db1\u0dca \u0db8\u0dcf\u0dbd\u0dd2\u0d9c\u0dba\u2019, \u0db8\u0dc4\u0dd2\u0db1\u0dca\u0daf \u0d9a\u0dda. \u0dc0\u0dd2\u0db8\u0dbd\u0dc3\u0dd2\u0dbb\u0dd2 \u0db8\u0dc4\u0dad\u0dcf\u0d9c\u0dda \u2018\u0d9a\u0da9\u0dc0\u0dbb \u0d87\u0daf\u0dc4\u0dd3\u0db8\u2019, \u0dc3\u0db1\u0dca\u0db0\u0dca\u200d\u0dba\u0dcf \u0d9a\u0dc4\u0db3\u0d9c\u0db8 \u0db8\u0dc4\u0dad\u0dca\u0db8\u0dd2\u0dba\u0d9c\u0dda \u2018\u0dc3\u0d82\u0d9b\u0dca\u200d\u0dba\u0dcf \u0db4\u0dd4\u0dbb\u0dcf\u0dab\u0dba\u2019 \u0dba\u0db1 \u0d9a\u0dd8\u0dad\u0dd3\u0db1\u0dca \u0db4\u0dc4 \u0db1\u0dd2\u0dbb\u0dca\u0daf\u0dda\u0dc1 \u0dc0\u0dd3 \u0d87\u0dad.",
        "\u0dc1\u0dca\u200d\u0dbb\u0dd3 \u0da2\u0dba\u0dc0\u0dbb\u0dca\u0db0\u0db1\u0db4\u0dd4\u0dbb \u0dc0\u0dd2\u0dc1\u0dca\u0dc0 \u0dc0\u0dd2\u0daf\u0dca\u200d\u0dba\u0dcf\u0dbd\u0dba\u0dda \u0db8\u0dcf\u0db1\u0dc0 \u0dc1\u0dcf\u0dc3\u0dca\u0dad\u0dca\u200d\u0dbb \u0dc4\u0dcf \u0dc3\u0db8\u0dcf\u0da2\u0dd3\u0dba \u0dc0\u0dd2\u0daf\u0dca\u200d\u0dba\u0dcf \u0db4\u0dd3\u0da8\u0dba\u0dd9\u0dc4\u0dd2 \u0db4\u0dd3\u0da8 \u0d9a\u0db8\u0dd2\u0da7\u0dd4\u0dc0 \u0db8\u0d9c\u0dd2\u0db1\u0dca \u0dc0\u0dcf\u0dbb\u0dca\u0dc2\u0dd2\u0d9a\u0dc0 \u0dc3\u0d82\u0dc0\u0dd2\u0db0\u0dcf\u0db1\u0dba \u0d9a\u0dbb\u0db1 \u0db8\u0dd9\u0db8 \u0dc3\u0dcf\u0dc4\u0dd2\u0dad\u0dca\u200d\u0dba \u0dc3\u0db8\u0dca\u0db8\u0dcf\u0db1 \u0d8b\u0dc5\u0dd9\u0dbd \u0db8\u0dd9\u0dc0\u0dbb \u0db4\u0dd0\u0dc0\u0dd0\u0dad\u0dca\u0dc0\u0dd9\u0db1\u0dca\u0db1\u0dda \u0db8\u0dd9\u0dc0\u0dbb 13 \u0dc0\u0dd0\u0db1\u0dd2 \u0dc0\u0dbb\u0da7\u0dba.",
        "\u0db8\u0dd9\u0dc0\u0dbb \u0d91\u0dc4\u0dd2 \u0db4\u0dca\u200d\u0dbb\u0db0\u0dcf\u0db1 \u0d86\u0dbb\u0dcf\u0db0\u0dd2\u0dad\u0dba\u0dcf \u0dbd\u0dd9\u0dc3 \u0dc1\u0dca\u200d\u0dbb\u0dd3 \u0da2\u0dba\u0dc0\u0dbb\u0dca\u0db0\u0db1\u0db4\u0dd4\u0dbb \u0dc0\u0dd2\u0dc1\u0dca\u0dc0 \u0dc0\u0dd2\u0daf\u0dca\u200d\u0dba\u0dcf\u0dbd\u0dba\u0dda \u0dc3\u0dd2\u0d82\u0dc4\u0dbd \u0d85\u0db0\u0dca\u200d\u0dba\u0dba\u0db1\u0dcf\u0d82\u0dc1\u0dba\u0dda \u0da2\u0dca\u200d\u0dba\u0dd9\u0dc2\u0dca\u0da8 \u0db8\u0dc4\u0dcf\u0da0\u0dcf\u0dbb\u0dca\u0dba \u0d86\u0db1\u0db1\u0dca\u0daf \u0dad\u0dd2\u0dc3\u0dca\u0dc3 \u0d9a\u0dd4\u0db8\u0dcf\u0dbb \u0db8\u0dc4\u0dad\u0dcf \u0dc3\u0dc4\u0db7\u0dcf\u0d9c\u0dd3\u0dc0\u0dd3\u0db8\u0da7 \u0db1\u0dd2\u0dba\u0db8\u0dd2\u0dad\u0dba."
      ],
      "title_ents": [],
      "body_line_ents_list": [
        [
          {
            "text": "\u0dc1\u0dca\u200d\u0dbb\u0dd3 \u0da2\u0dba\u0dc0\u0dbb\u0dca\u0db0\u0db1\u0db4\u0dd4\u0dbb \u0dc0\u0dd2\u0dc1\u0dca\u0dc0\u0dc0\u0dd2\u0daf\u0dca\u200d\u0dba\u0dcf\u0dbd\u0dba\u0dda \u0dc3\u0dd4\u0db8\u0d82\u0d9c\u0dbd \u0dc1\u0dcf\u0dbd\u0dcf\u0dc0",
            "label": "FAC"
          },
          {
            "text": "\u0dc3\u0dd0\u0db4\u0dca\u0dad\u0dd0\u0db8\u0dca\u0db6\u0dbb\u0dca 1 \u0dc0\u0dd0\u0db1\u0dd2\u0daf\u0dcf",
            "label": "DATE"
          },
          {
            "text": "3:00 \u0db4.\u0dc0",
            "label": "TIME"
          }
        ],
        [
          {
            "text": "\u0dc0\u0dc3\u0dbb",
            "label": "DATE"
          }
        ],
        [
          {
            "text": "\u0dc0\u0dbb\u0dca\u0dc2\u0dba",
            "label": "DATE"
          },
          {
            "text": "\u0dc0\u0dc3\u0dbb",
            "label": "DATE"
          },
          {
            "text": "\u0dc3\u0dda\u0db4\u0dcf\u0dbd\u0dd2 \u0db8\u0dcf\u0dba\u0dcf\u0daf\u0dd4\u0db1\u0dca\u0db1\u0dda",
            "label": "PERSON"
          },
          {
            "text": "\u0dc3\u0db1\u0dca\u0db0\u0dca\u0dba\u0dcf\u0db1\u0db1\u0dca\u0daf\u0dba",
            "label": "PERSON"
          },
          {
            "text": "\u0d9a\u0dd3\u0dbb\u0dca\u0dad\u0dd2 \u0dc0\u0dd0\u0dbd\u0dd2\u0dc3\u0dbb\u0d9c\u0dda",
            "label": "PERSON"
          },
          {
            "text": "\u0dc1\u0db8\u0dd9\u0dbd\u0dca \u0da2\u0dba\u0d9a\u0ddc\u0da9\u0dd2",
            "label": "PERSON"
          },
          {
            "text": "\u0db4\u0dca\u200d\u0dbb\u0dda\u0db8\u0db1\u0dd2\u0dc1\u0d82\u0dc3",
            "label": "PERSON"
          },
          {
            "text": "\u0da0\u0db1\u0dca\u0daf\u0dca\u200d\u0dbb\u0dbb\u0dad\u0dca\u0db1 \u0db6\u0dab\u0dca\u0da9\u0dcf\u0dbb",
            "label": "PERSON"
          },
          {
            "text": "\u0db1\u0d9a\u0dd4\u0dbd",
            "label": "PERSON"
          },
          {
            "text": "\u0d91\u0dbb\u0dd2\u0d9a\u0dca \u0d89\u0dbd\u0dba\u0db4\u0dca\u0d86\u0dbb\u0da0\u0dca\u0da0\u0dd2",
            "label": "PERSON"
          }
        ],
        [
          {
            "text": "\u0dc0\u0dc3\u0dbb",
            "label": "DATE"
          },
          {
            "text": "'\u0da2\u0dcf\u0dad\u0dca\u200d\u0dba\u0db1\u0dca\u0dad\u0dbb \u0db4\u0dcf\u0db4\u0ddc\u0da0\u0dca\u0da0\u0dcf\u0dbb\u0dab'",
            "label": "ORG"
          },
          {
            "text": "\u0d91\u0dbb\u0dd2\u0d9a\u0dca \u0d89\u0dbd\u0dba\u0db4\u0dca\u0d86\u0dbb\u0da0\u0dca\u0da0\u0dd2",
            "label": "PERSON"
          },
          {
            "text": "\u0db8\u0dc4\u0dd2\u0db1\u0dca\u0daf \u0dbb\u0dad\u0dca\u0db1\u0dcf\u0dba\u0d9a",
            "label": "PERSON"
          },
          {
            "text": "\u0d8b\u0db4\u0dcf\u0dbd\u0dd2 \u0d8b\u0db6\u0dba\u0dc3\u0dda\u0d9a\u0dbb",
            "label": "PERSON"
          },
          {
            "text": "\u0db8\u0dcf\u0dc0\u0dad\u0d9a \u0db8\u0dd2\u0db8\u0dd2\u0db1\u0dd2\u0dbd\u0dca\u0dbd\u0dcf'",
            "label": "PERSON"
          },
          {
            "text": "\u0db8\u0dbd\u0dd2\u0db3\u0dd4 \u0d9a\u0dcf\u0dc0\u0dd2\u0db1\u0dca\u0daf \u0d9a\u0dd4\u0db8\u0dcf\u0dbb\u0dc3\u0dd2\u0d82\u0dc4",
            "label": "PERSON"
          },
          {
            "text": "\u0dc3\u0dda\u0db1\u0dcf\u0db0\u0dd3\u0dbb \u0d9a\u0dd4\u0db8\u0dcf\u0dbb\u0dba\u0dcf",
            "label": "PERSON"
          },
          {
            "text": "\u0d9a\u0dc5\u0dd4 \u0d8b\u0dc3 \u0db8\u0dd2\u0db1\u0dd2\u0dc3\u0dcf'",
            "label": "WORK_OF_ART"
          }
        ],
        [
          {
            "text": "\u0db4\u0dc4",
            "label": "CARDINAL"
          },
          {
            "text": "\u0dc0\u0dc3\u0dbb\u0dda \u0dc3\u0db8\u0dca\u0db8\u0dcf\u0db1\u0dba",
            "label": "DATE"
          },
          {
            "text": "\u0dbd\u0d9a\u0dca\u0dc2\u0dcf\u0db1\u0dca\u0dad \u0d85\u0dad\u0dd4\u0d9a\u0ddd\u0dbb\u0dbd\u0d9c\u0dda",
            "label": "PERSON"
          },
          {
            "text": "\u0dbd\u0dd2\u0dba\u0dc3\u0dc0\u0dca \u0dbd\u0dd2\u0dc4\u0dd2",
            "label": "PERSON"
          },
          {
            "text": "\u0d9c\u0dba\u0dcf \u0d9c\u0dab\u0dc3\u0db8\u0dcf\u0daf\u0dd4\u0dc5\u0dd4'",
            "label": "PERSON"
          },
          {
            "text": "Sureka Samarasena",
            "label": "PERSON"
          },
          {
            "text": "'\u0dc0\u0db8\u0dca \u0db4\u0dd2\u0dba\u0dc0\u0dd4\u0dbb'",
            "label": "WORK_OF_ART"
          },
          {
            "text": "\u0d85\u0db1\u0dd4\u0dbb\u0dcf\u0db0\u0dcf \u0db1\u0dd2\u0dbd\u0dca\u0db8\u0dd2\u0dab\u0dd2",
            "label": "PERSON"
          },
          {
            "text": "'\u0db1\u0dcf\u0dbb\u0dd2 \u0dc3\u0dd6\u0dad\u0dca\u200d\u0dbb\u0dba (\u0d9a\u0dcf\u0dc0\u0dca\u200d\u0dba",
            "label": "WORK_OF_ART"
          },
          {
            "text": "\u0dc3\u0db3\u0dbb\u0dc3\u0dd3 \u0dc3\u0dd4\u0daf\u0dd4\u0dc3\u0dd2\u0d82\u0dc4\u0d9c\u0dda",
            "label": "PERSON"
          },
          {
            "text": "\u0db4\u0dd2\u0dba\u0dcf\u0db4\u0dad\u0dca'",
            "label": "ORG"
          },
          {
            "text": "\u0d91\u0dbb\u0dd2\u0d9a\u0dca \u0d89\u0dbd\u0dba\u0db4\u0dca\u200d\u0dbb\u0da0\u0dca\u0da0\u0dd2\u0d9c\u0dda",
            "label": "PERSON"
          },
          {
            "text": "Prometheus \u0daf\u0dd2\u0dc0\u0dba\u0dd2\u0db1",
            "label": "LOC"
          }
        ],
        [
          {
            "text": "\u0dc0\u0dc3\u0dbb",
            "label": "DATE"
          },
          {
            "text": "\u0dad\u0dd4\u0db1\u0dca",
            "label": "CARDINAL"
          },
          {
            "text": "\u0db4\u0dca\u200d\u0dbb\u0db8\u0ddb \u0db8\u0db1\u0dbb\u0db8\u0dca'",
            "label": "WORK_OF_ART"
          },
          {
            "text": "\u0dba\u0db8\u0dd4\u0db1\u0dcf \u0db8\u0dcf\u0dbd\u0dd2\u0db1\u0dd3 \u0db4\u0dd9\u0dbb\u0dda\u0dbb\u0dcf",
            "label": "PERSON"
          },
          {
            "text": "\u0dc0\u0dc3\u0db1\u0dca\u0dad",
            "label": "PERSON"
          },
          {
            "text": "Kumara Kobawaka",
            "label": "PERSON"
          },
          {
            "text": "\u0dc3\u0db3\u0db8\u0da9\u0dbd \u0dc0\u0dd3'",
            "label": "PERSON"
          },
          {
            "text": "\u0db4\u0dbd\u0dca\u0dbd\u0dda\u0d9c\u0db8",
            "label": "GPE"
          },
          {
            "text": "\u0dc4\u0dda\u0db8\u0dbb\u0dad\u0db1 \u0dc4\u0dd2\u0db8\u0dd2",
            "label": "PERSON"
          },
          {
            "text": "\u0dc0\u0dc3\u0dbb",
            "label": "DATE"
          },
          {
            "text": "\u0dc0\u0db1\u0dca\u0db1\u0dd2\u0d9c\u0dda \u0d9a\u0ddd\u0dbd\u0db8'",
            "label": "PERSON"
          },
          {
            "text": "\u0db1\u0dba\u0db1\u0dc3\u0dda\u0db1 \u0dc0\u0db1\u0dca\u0db1\u0dd2\u0db1\u0dcf\u0dba\u0d9a",
            "label": "PERSON"
          },
          {
            "text": "\u0db6\u0dd4\u0daf\u0dca\u0db0\u0daf\u0dcf\u0dc3 \u0d9c\u0dbd\u0db4\u0dca\u0db4\u0dad\u0dca\u0dad\u0dd2",
            "label": "PERSON"
          },
          {
            "text": "\u0db1\u0dd2\u0db1\u0dca\u0db1\u0dcf\u0daf",
            "label": "PERSON"
          },
          {
            "text": "\u0dc4\u0dbb\u0dca\u0dc2\u0dd2\u0db1\u0dd3 \u0db4\u0dd4\u0dc2\u0dca\u0db4\u0db8\u0dcf\u0dbd\u0dcf \u0d86\u0dbb\u0da0\u0dca\u0da0\u0dd2",
            "label": "PERSON"
          }
        ],
        [
          {
            "text": "\u0dc0\u0dc3\u0dbb\u0dda \u0dc3\u0db8\u0dca\u0db8\u0dcf\u0db1\u0dba",
            "label": "DATE"
          },
          {
            "text": "\u0db4\u0dca\u200d\u0dbb\u0dda\u0db8\u0dc3\u0dd2\u0dbb\u0dd2 \u0db1\u0dcf\u0d9c\u0dc3\u0dd2\u0d82\u0dc4",
            "label": "PERSON"
          },
          {
            "text": "\u0dc3\u0dd2\u0d82\u0dc4\u0dbd \u0d8b\u0db4\u0dcf\u0dc3\u0d9a\u0db4\u0dca\u0db1\u0dcf\u0dbd\u0d82\u0d9a\u0dcf\u0dbb\u0dba \u0dc3\u0d82\u0dc3\u0dca\u0d9a\u0dbb\u0dab\u0dba \u0dc3\u0dc4 \u0dc0\u0dd2\u0da0\u0dcf\u0dbb \u0d85\u0db0\u0dca\u200d\u0dba\u0dba\u0db1\u0dba'",
            "label": "WORK_OF_ART"
          },
          {
            "text": "\u0dc3\u0db8\u0db1\u0dca \u0db4\u0db1\u0dcf\u0db4\u0dd2\u0da7\u0dd2\u0dba",
            "label": "PERSON"
          },
          {
            "text": "\u0db8\u0dc4\u0dd2\u0db1\u0dca\u0daf \u0dc3\u0ddd\u0db8\u0dad\u0dd2\u0dbd\u0d9a\u0d9c\u0dda",
            "label": "PERSON"
          },
          {
            "text": "\u0d9a\u0dd2\u0dba\u0dd4\u0dbd\u0dca\u0d9c\u0db8 \u0daf\u0dc5\u0daf\u0dcf\u0dc0",
            "label": "PERSON"
          },
          {
            "text": "\u0db8\u0dc4\u0dd2\u0db1\u0dca\u0daf \u0d9a\u0dda \u0db4\u0dc4",
            "label": "ORG"
          },
          {
            "text": "\u0dc0\u0dd2\u0db8\u0dbd\u0dc3\u0dd2\u0dbb\u0dd2",
            "label": "PERSON"
          },
          {
            "text": "\u0d9a\u0da9\u0dc0\u0dbb \u0d85\u0da9\u0dc4\u0dd2\u0db8'",
            "label": "PERSON"
          },
          {
            "text": "\u0dc3\u0db1\u0dca\u0db0\u0dca\u200d\u0dba\u0dcf \u0d9a\u0dc4\u0db3\u0d9c\u0db8\u0d9c\u0dda",
            "label": "PERSON"
          },
          {
            "text": "\u0dc3\u0d82\u0d9a\u0dca\u200d\u0dba \u0db4\u0dd4\u0dbb\u0dcf\u0dab\u0dba'",
            "label": "WORK_OF_ART"
          }
        ],
        [
          {
            "text": "\u0db8\u0dcf\u0db1\u0dc0 \u0dc1\u0dcf\u0dc3\u0dca\u0dad\u0dca\u200d\u0dbb \u0dc4\u0dcf \u0dc3\u0db8\u0dcf\u0da2 \u0dc0\u0dd2\u0daf\u0dca\u200d\u0dba\u0dcf \u0db4\u0dd3\u0da8\u0dba\u0dda \u0db4\u0dd3\u0da8 \u0d9a\u0db8\u0dd2\u0da7\u0dd4\u0dc0",
            "label": "ORG"
          },
          {
            "text": "\u0dc1\u0dca\u200d\u0dbb\u0dd3 \u0da2\u0dba\u0dc0\u0dbb\u0dca\u0db0\u0db1\u0db4\u0dd4\u0dbb \u0dc0\u0dd2\u0dc1\u0dca\u0dc0\u0dc0\u0dd2\u0daf\u0dca\u200d\u0dba\u0dcf\u0dbd\u0dba",
            "label": "ORG"
          },
          {
            "text": "13 \u0dc0\u0dd0\u0db1\u0dd2",
            "label": "DATE"
          },
          {
            "text": "\u0db8\u0dda \u0dc0\u0dc3\u0dbb\u0dda",
            "label": "DATE"
          }
        ],
        [
          {
            "text": "\u0d86\u0db1\u0db1\u0dca\u0daf \u0dad\u0dd2\u0dc3\u0dca\u0dc3 \u0d9a\u0dd4\u0db8\u0dcf\u0dbb",
            "label": "PERSON"
          },
          {
            "text": "\u0dc1\u0dca\u200d\u0dbb\u0dd3 \u0da2\u0dba\u0dc0\u0dbb\u0dca\u0db0\u0db1\u0db4\u0dd4\u0dbb \u0dc0\u0dd2\u0dc1\u0dca\u0dc0\u0dc0\u0dd2\u0daf\u0dca\u200d\u0dba\u0dcf\u0dbd\u0dba\u0dda \u0dc3\u0dd2\u0d82\u0dc4\u0dbd \u0d85\u0d82\u0dc1\u0dba",
            "label": "ORG"
          }
        ]
      ]
    },
    "ta": {
      "title": "\u0bb5\u0bbf\u0ba4\u0bcd\u0baf\u0bcb\u0ba4\u0baf\u0bbe \u0b9a\u0bbe\u0b95\u0bbf\u0ba4\u0bcd\u0baf \u0bb5\u0bbf\u0bb0\u0bc1\u0ba4\u0bc1\u0b95\u0bb3\u0bc1\u0b95\u0bcd\u0b95\u0bc1\u0baa\u0bcd \u0baa\u0bb0\u0bbf\u0ba8\u0bcd\u0ba4\u0bc1\u0bb0\u0bc8\u0b95\u0bcd\u0b95\u0baa\u0bcd\u0baa\u0b9f\u0bcd\u0b9f \u0baa\u0b9f\u0bc8\u0baa\u0bcd\u0baa\u0bc1\u0b95\u0bb3\u0bcd \u0b85\u0bb1\u0bbf\u0bb5\u0bbf\u0b95\u0bcd\u0b95\u0baa\u0bcd\u0baa\u0b9f\u0bc1\u0bae\u0bcd",
      "author": "\u0ba4\u0bc6\u0bb0\u0bbf\u0baf\u0bb5\u0bbf\u0bb2\u0bcd\u0bb2\u0bc8",
      "body_lines": [
        "\u0bb5\u0bbf\u0ba4\u0bcd\u0baf\u0bcb\u0ba4\u0baf\u0bbe \u0b9a\u0bbe\u0b95\u0bbf\u0ba4\u0bcd\u0baf \u0bb5\u0bbf\u0bb0\u0bc1\u0ba4\u0bc1 \u0bb5\u0bb4\u0b99\u0bcd\u0b95\u0bc1\u0bae\u0bcd \u0bb5\u0bbf\u0bb4\u0bbe \u0bb8\u0bcd\u0bb0\u0bc0 \u0b9c\u0baf\u0bb5\u0bb0\u0bcd\u0ba4\u0ba9\u0baa\u0bc1\u0bb0 \u0baa\u0bb2\u0bcd\u0b95\u0bb2\u0bc8\u0b95\u0bcd\u0b95\u0bb4\u0b95\u0ba4\u0bcd\u0ba4\u0bbf\u0ba9\u0bcd \u0b9a\u0bc1\u0bae\u0b99\u0bcd\u0b95\u0bb2\u0bbe \u0bae\u0ba3\u0bcd\u0b9f\u0baa\u0ba4\u0bcd\u0ba4\u0bbf\u0bb2\u0bcd \u0b9a\u0bc6\u0baa\u0bcd\u0b9f\u0bae\u0bcd\u0baa\u0bb0\u0bcd 1 \u0b86\u0bae\u0bcd \u0ba4\u0bc7\u0ba4\u0bbf \u0baa\u0bbf\u0bb1\u0bcd\u0baa\u0b95\u0bb2\u0bcd 3:00 \u0bae\u0ba3\u0bbf\u0b95\u0bcd\u0b95\u0bc1 \u0ba8\u0b9f\u0bc8\u0baa\u0bc6\u0bb1\u0bb5\u0bc1\u0bb3\u0bcd\u0bb3\u0ba4\u0bc1\u0b9f\u0ba9\u0bcd, \u0b87\u0bb1\u0bc1\u0ba4\u0bbf\u0b9a\u0bcd \u0b9a\u0bc1\u0bb1\u0bcd\u0bb1\u0bc1 \u0bb5\u0bbf\u0bb0\u0bc1\u0ba4\u0bc1\u0b95\u0bb3\u0bc1\u0b95\u0bcd\u0b95\u0bc1 \u0baa\u0bb0\u0bbf\u0ba8\u0bcd\u0ba4\u0bc1\u0bb0\u0bc8\u0b95\u0bcd\u0b95\u0baa\u0bcd\u0baa\u0b9f\u0bcd\u0b9f \u0baa\u0b9f\u0bc8\u0baa\u0bcd\u0baa\u0bc1\u0b95\u0bb3\u0bcd \u0ba4\u0bb1\u0bcd\u0baa\u0bcb\u0ba4\u0bc1 \u0b85\u0bb1\u0bbf\u0bb5\u0bbf\u0b95\u0bcd\u0b95\u0baa\u0bcd\u0baa\u0b9f\u0bcd\u0b9f\u0bc1\u0bb3\u0bcd\u0bb3\u0ba9.",
        "\u0b86\u0ba3\u0bcd\u0b9f\u0bbf\u0ba9\u0bcd \u0b9a\u0bbf\u0bb1\u0ba8\u0bcd\u0ba4 \u0ba8\u0bbe\u0bb5\u0bb2\u0bcd, \u0b9a\u0bbf\u0bb1\u0bc1\u0b95\u0ba4\u0bc8\u0ba4\u0bcd \u0ba4\u0bca\u0b95\u0bc1\u0baa\u0bcd\u0baa\u0bc1, \u0b95\u0bb5\u0bbf\u0ba4\u0bc8\u0ba4\u0bcd \u0ba4\u0bca\u0b95\u0bc1\u0baa\u0bcd\u0baa\u0bc1, \u0baa\u0bbe\u0b9f\u0bb2\u0bcd \u0ba4\u0bca\u0b95\u0bc1\u0baa\u0bcd\u0baa\u0bc1, \u0baa\u0ba4\u0bcd\u0ba4\u0bbf\u0ba4\u0bcd \u0ba4\u0bca\u0b95\u0bc1\u0baa\u0bcd\u0baa\u0bc1 \u0bae\u0bb1\u0bcd\u0bb1\u0bc1\u0bae\u0bcd \u0b95\u0bb2\u0bcd\u0bb5\u0bbf\u0ba4\u0bcd \u0ba4\u0bca\u0b95\u0bc1\u0baa\u0bcd\u0baa\u0bc1 \u0b86\u0b95\u0bbf\u0baf\u0bb5\u0bb1\u0bcd\u0bb1\u0bc1\u0b95\u0bcd\u0b95\u0bbe\u0ba9 \u0bb5\u0bbf\u0bb0\u0bc1\u0ba4\u0bc1\u0b95\u0bb3\u0bcd \u0bb5\u0bb4\u0b99\u0bcd\u0b95\u0baa\u0bcd\u0baa\u0b9f\u0bc1\u0bae\u0bcd.",
        "\u0ba4\u0bbf\u0bb0\u0bc1\u0bae\u0ba4\u0bbf \u0b9a\u0bc6\u0baa\u0bbe\u0bb2\u0bbf \u0bae\u0bbe\u0baf\u0bbe\u0ba4\u0bc1\u0ba9\u0bcd\u0ba9\u0bc7 \u0b8e\u0bb4\u0bc1\u0ba4\u0bbf\u0baf '\u0bb9\u0bbf\u0ba9\u0bcd \u0b9f\u0bcb\u0bb8\u0bcd \u0bae\u0bbe\u0bb2\u0bc7', \u0ba4\u0bbf\u0bb0\u0bc1. \u0b95\u0bc0\u0bb0\u0bcd\u0ba4\u0bcd\u0ba4\u0bbf \u0bb5\u0bc6\u0bb2\u0bbf\u0b9a\u0bb0\u0b95\u0bc7 \u0b8e\u0bb4\u0bc1\u0ba4\u0bbf\u0baf '\u0b9a\u0ba8\u0bcd\u0ba4\u0bbf\u0baf\u0bbe\u0ba8\u0ba8\u0bcd\u0ba4\u0baf\u0bbe', \u0ba4\u0bbf\u0bb0\u0bc1\u0bae\u0ba4\u0bbf \u0bb7\u0bae\u0bc7\u0bb2\u0bcd \u0b9c\u0baf\u0b95\u0bca\u0b9f\u0bbf \u0b8e\u0bb4\u0bc1\u0ba4\u0bbf\u0baf '\u0bae\u0bc8 \u0b9a\u0bbf\u0b95\u0bbe\u0b95\u0bcb \u0bb9\u0bbe\u0bb0\u0bcd\u0b9f\u0bcd', \u0ba4\u0bbf\u0bb0\u0bc1. \u0b9a\u0ba8\u0bcd\u0ba4\u0bbf\u0bb0\u0bb0\u0ba4\u0bcd\u0ba9 \u0b8e\u0bb4\u0bc1\u0ba4\u0bbf\u0baf '\u0baa\u0bbf\u0bb0\u0bc7\u0bae\u0ba9\u0bbf\u0bb7\u0bbe\u0ba9\u0bcd\u0b9a\u0bbe' \u0b87\u0ba8\u0bcd\u0ba4 \u0b86\u0ba3\u0bcd\u0b9f\u0bbf\u0ba9\u0bcd \u0b9a\u0bbf\u0bb1\u0ba8\u0bcd\u0ba4 \u0ba8\u0bbe\u0bb5\u0bb2\u0bcd. \u0baa\u0ba3\u0bcd\u0b9f\u0bbe\u0bb0 \u0bae\u0bb1\u0bcd\u0bb1\u0bc1\u0bae\u0bcd \u0ba4\u0bbf\u0bb0\u0bc1.\u0b8e\u0bb0\u0bbf\u0b95\u0bcd \u0b87\u0bb3\u0bc8\u0baf\u0baa\u0bcd\u0baa\u0bb0\u0bbe\u0b9a\u0bcd\u0b9a\u0bbf.\u0bae\u0bc1\u0ba9\u0bbf \u0b8e\u0bb4\u0bc1\u0ba4\u0bbf\u0baf '\u0ba8\u0b95\u0bc1\u0bb2' \u0ba8\u0bbe\u0bb5\u0bb2\u0bcd\u0b95\u0bb3\u0bcd \u0baa\u0bb0\u0bbf\u0ba8\u0bcd\u0ba4\u0bc1\u0bb0\u0bc8\u0b95\u0bcd\u0b95\u0baa\u0bcd\u0baa\u0b9f\u0bcd\u0b9f\u0bc1\u0bb3\u0bcd\u0bb3\u0ba9.",
        "\u0bae\u0bc7\u0bb2\u0bc1\u0bae\u0bcd \u0b87\u0bb5\u0bcd\u0bb5\u0bbe\u0ba3\u0bcd\u0b9f\u0bbf\u0ba9\u0bcd \u0b9a\u0bbf\u0bb1\u0ba8\u0bcd\u0ba4 \u0b9a\u0bbf\u0bb1\u0bc1\u0b95\u0ba4\u0bc8\u0ba4\u0bcd \u0ba4\u0bca\u0b95\u0bc1\u0baa\u0bcd\u0baa\u0bbf\u0bb1\u0bcd\u0b95\u0bbe\u0ba9 \u0bb5\u0bbf\u0bb0\u0bc1\u0ba4\u0bc1, \u0ba4\u0bbf\u0bb0\u0bc1 \u0b8e\u0bb0\u0bbf\u0b95\u0bcd \u0b87\u0bb3\u0bc8\u0baf\u0baa\u0bbe\u0bb0\u0bbe\u0b9a\u0bcd\u0b9a\u0bbf\u0baf\u0bbf\u0ba9\u0bcd '\u0b9a\u0bb0\u0bcd\u0bb5\u0ba4\u0bc7\u0b9a \u0bb5\u0bbe\u0b95\u0bcd\u0b95\u0bc1\u0bae\u0bc2\u0bb2\u0b99\u0bcd\u0b95\u0bb3\u0bcd', '\u0b95\u0bb4\u0bbf\u0bb5\u0bb1\u0bc8 \u0b95\u0bb4\u0bc1\u0bb5\u0bc1\u0baa\u0bb5\u0bb0\u0bbf\u0ba9\u0bcd \u0bae\u0b95\u0bb3\u0bcd \u0b8e\u0ba9\u0bcd\u0baa\u0ba4\u0bbe\u0bb2\u0bcd', \u0ba4\u0bbf\u0bb0\u0bc1.\u0bae\u0b95\u0bbf\u0ba8\u0bcd\u0ba4 \u0bb0\u0ba4\u0bcd\u0ba8\u0bbe\u0baf\u0b95\u0bcd\u0b95\u0bb5\u0bbf\u0ba9\u0bcd, '\u0b95\u0bbf\u0ba9\u0bbf \u0b9a\u0bbf\u0bb2 \u0bae\u0bb1\u0bcd\u0bb1\u0bc1\u0bae\u0bcd \u0baa\u0bbf\u0bb1 \u0b9a\u0bbf\u0bb1\u0bc1\u0b95\u0ba4\u0bc8\u0b95\u0bb3\u0bcd' \u0ba4\u0bbf\u0bb0\u0bc1 \u0b89\u0baa\u0bbe\u0bb2\u0bbf \u0b89\u0baa\u0baf\u0b9a\u0bc7\u0b95\u0bb0, \u0ba4\u0bbf\u0bb0\u0bc1.\u0bae\u0bb2\u0bbf\u0ba8\u0bcd\u0ba4\u0bc1 \u0b95\u0bb5\u0bbf\u0ba8\u0bcd\u0ba4 \u0b95\u0bc1\u0bae\u0bbe\u0bb0\u0b9a\u0bbf\u0b99\u0bcd\u0b95\u0bb5\u0bbf\u0ba9\u0bcd '\u0bae\u0ba9\u0bbf\u0ba4\u0ba9\u0bcd \u0bae\u0bbe\u0bb5\u0ba4\u0b95 \u0bae\u0bbf\u0bae\u0bbf\u0ba9\u0bbf\u0bb2\u0bbe\u0bb5\u0bbf\u0ba9\u0bcd \u0ba8\u0bbf\u0ba9\u0bc8\u0bb5\u0bc1\u0b95\u0bb3\u0bcd' \u0bae\u0bb1\u0bcd\u0bb1\u0bc1\u0bae\u0bcd \u0ba4\u0bbf\u0bb0\u0bc1.\u0baa\u0bbf\u0bb0\u0bbf\u0ba9\u0bcd\u0bb8\u0bcd \u0b9a\u0bc7\u0ba9\u0bbe\u0ba4\u0bc0\u0bb0\u0bb5\u0bbf\u0ba9\u0bcd '\u0b95\u0bb0\u0bc1\u0baa\u0bcd\u0baa\u0bc1 \u0b89\u0baf\u0bb0\u0bae\u0bbe\u0ba9 \u0bae\u0ba9\u0bbf\u0ba4\u0ba9\u0bcd' \u0b86\u0b95\u0bbf\u0baf \u0baa\u0b9f\u0bc8\u0baa\u0bcd\u0baa\u0bc1\u0b95\u0bb3\u0bcd \u0baa\u0bb0\u0bbf\u0ba8\u0bcd\u0ba4\u0bc1\u0bb0\u0bc8\u0b95\u0bcd\u0b95\u0baa\u0bcd\u0baa\u0b9f\u0bcd\u0b9f\u0bc1\u0bb3\u0bcd\u0bb3\u0ba9.",
        "\u0ba4\u0bbf\u0bb0\u0bc1.\u0bb2\u0b95\u0bcd\u0bb7\u0bbe\u0ba8\u0bcd\u0ba4 \u0b85\u0ba4\u0bcd\u0ba4\u0bc1\u0b95\u0bcb\u0bb0\u0bb3\u0bb5\u0bbf\u0ba9\u0bcd \u2018\u0bb2\u0bbf\u0baf\u0bbe\u0b9a\u0bb5\u0bcd \u0bb2\u0bbf\u0bb9\u0bbf \u0b95\u0baf \u0b95\u0ba9\u0b9a\u0bae\u0b9f\u0bc1\u0bb2\u0bc1\u2019, \u0ba4\u0bbf\u0bb0\u0bc1\u0bae\u0ba4\u0bbf \u0b9a\u0bc1\u0bb0\u0bc7\u0b95\u0bbe \u0b9a\u0bae\u0bb0\u0b9a\u0bc7\u0ba9\u0bb5\u0bbf\u0ba9\u0bcd \u2018\u0bb5\u0bae\u0bcd \u0baa\u0bbf\u0baf\u0bb5\u0bc1\u0bb0\u2019, \u0ba4\u0bbf\u0bb0\u0bc1\u0bae\u0ba4\u0bbf \u0b85\u0ba9\u0bc1\u0bb0\u0bbe\u0ba4\u0bbe \u0ba8\u0bbf\u0bb2\u0bcd\u0bae\u0bbf\u0ba9\u0bbf\u0baf\u0bbf\u0ba9\u0bcd \u2018\u0ba8\u0bbe\u0bb0\u0bbf \u0b9a\u0bc2\u0ba4\u0bcd\u0bb0\u0bbe (\u0b95\u0bb5\u0bbf\u0ba4\u0bc8), \u0ba4\u0bbf\u0bb0\u0bc1\u0bae\u0ba4\u0bbf.\u0b9a\u0ba8\u0bcd\u0ba4\u0bbe\u0bb0\u0bb8\u0bcd, \u200b\u200b\u0ba4\u0bbf\u0bb0\u0bc1\u0bae\u0ba4\u0bbf. \u0b8e\u0bb0\u0bbf\u0b95\u0bcd \u0b87\u0bb3\u0bc8\u0baf\u0baa\u0bb0\u0bbe\u0b9a\u0bcd\u0b9a\u0bbf\u0baf\u0bbf\u0ba9\u0bcd '\u0baa\u0bc1\u0bb0\u0bcb\u0bae\u0bbf\u0ba4\u0bbf\u0baf\u0bb8\u0bcd \u0ba4\u0bc0\u0bb5\u0bc1' \u0b85\u0ba8\u0bcd\u0ba4 \u0baa\u0b9f\u0bc8\u0baa\u0bcd\u0baa\u0bc1\u0b95\u0bb3\u0bbf\u0bb2\u0bcd \u0b92\u0ba9\u0bcd\u0bb1\u0bc1.",
        "\u0b87\u0ba8\u0bcd\u0ba4 \u0bb5\u0bb0\u0bc1\u0b9f\u0ba4\u0bcd\u0ba4\u0bbf\u0ba9\u0bcd \u0b9a\u0bbf\u0bb1\u0ba8\u0bcd\u0ba4 \u0baa\u0bbe\u0b9f\u0bb2\u0bcd \u0ba4\u0bca\u0b95\u0bc1\u0baa\u0bcd\u0baa\u0bc1\u0b95\u0bcd\u0b95\u0bbe\u0b95 \u0ba4\u0bbf\u0bb0\u0bc1\u0bae\u0ba4\u0bbf \u0baf\u0bae\u0bc1\u0ba9\u0bbe \u0bae\u0bbe\u0bb2\u0bbf\u0ba9\u0bbf \u0baa\u0bc6\u0bb0\u0bc7\u0bb0\u0bbe \u0b8e\u0bb4\u0bc1\u0ba4\u0bbf\u0baf '\u0baa\u0bbf\u0bb0\u0bae\u0bc8\u0baf\u0bc8 \u0bae\u0ba3\u0bb0\u0bae\u0bcd', \u0ba4\u0bbf\u0bb0\u0bc1.\u0bb5\u0b9a\u0ba8\u0bcd\u0ba4 \u0b95\u0bc1\u0bae\u0bbe\u0bb0 \u0b95\u0bcb\u0baa\u0bb5\u0b95 \u0b8e\u0bb4\u0bc1\u0ba4\u0bbf\u0baf '\u0baa\u0bbe\u0bae \u0bb5\u0bc0 \u0baa\u0bbf\u0baa\u0bc1\u0ba9\u0bc1 \u0bae\u0bb2\u0bcd \u0bae\u0bbf\u0bb9\u0bbe\u0ba9\u0bc8', \u0baa\u0bb2\u0bcd\u0bb2\u0bc7\u0b95\u0bae \u0bb9\u0bc7\u0bae\u0bb0\u0ba4\u0bcd\u0ba4\u0ba9 \u0ba4\u0bc7\u0bb0\u0bb0\u0bbf\u0ba9\u0bcd '\u0b9a\u0ba8\u0bcd\u0ba4\u0bae\u0b9f\u0bb2 \u0bb5\u0bc0' \u0b86\u0b95\u0bbf\u0baf \u0bae\u0bc2\u0ba9\u0bcd\u0bb1\u0bc1 \u0baa\u0b9f\u0bc8\u0baa\u0bcd\u0baa\u0bc1\u0b95\u0bb3\u0bc1\u0bae\u0bcd \u0b87\u0b9f\u0bae\u0bcd \u0baa\u0bc6\u0bb1\u0bcd\u0bb1\u0bc1\u0bb3\u0bcd\u0bb3\u0ba9. \u0baa\u0bb0\u0bbf\u0ba8\u0bcd\u0ba4\u0bc1\u0bb0\u0bc8\u0b95\u0bcd\u0b95\u0baa\u0bcd\u0baa\u0b9f\u0bcd\u0b9f, \u0bae\u0bb1\u0bcd\u0bb1\u0bc1\u0bae\u0bcd \u0b86\u0ba3\u0bcd\u0b9f\u0bbf\u0ba9\u0bcd \u0b9a\u0bbf\u0bb1\u0ba8\u0bcd\u0ba4 \u0baa\u0ba4\u0bcd\u0ba4\u0bbf\u0b95\u0bb3\u0bcd.\u0ba4\u0bbf\u0bb0\u0bc1. \u0ba8\u0baf\u0ba9\u0b9a\u0bc7\u0ba9 \u0bb5\u0ba9\u0bcd\u0ba9\u0bbf\u0ba8\u0bbe\u0baf\u0b95\u0bcd\u0b95\u0bb5\u0bbf\u0ba9\u0bcd '\u0bb5\u0ba9\u0bcd\u0ba9\u0bbf\u0b95\u0bc7 \u0b95\u0bcb\u0bb2\u0bae\u0bbe', \u0ba4\u0bbf\u0bb0\u0bc1. \u0baa\u0bc1\u0ba4\u0bcd\u0ba4\u0ba4\u0bbe\u0b9a \u0b95\u0bb2\u0baa\u0bcd\u0baa\u0b9f\u0bcd\u0b9f\u0bbf\u0baf\u0bbf\u0ba9\u0bcd '\u0ba8\u0bc6\u0bb0\u0bc1\u0b95\u0bcd\u0b95\u0bae\u0bbe\u0ba9 \u0baa\u0b9f\u0b99\u0bcd\u0b95\u0bb3\u0bcd' \u0bae\u0bb1\u0bcd\u0bb1\u0bc1\u0bae\u0bcd \u0bb9\u0bb0\u0bcd\u0bb7\u0bbf\u0ba9\u0bbf \u0baa\u0bc1\u0bb7\u0bcd\u0baa\u0bae\u0bbe\u0bb2\u0bbe \u0b86\u0bb0\u0bbe\u0b9a\u0bcd\u0b9a\u0bbf\u0baf\u0bbf\u0ba9\u0bcd '\u0ba8\u0bbf\u0ba9\u0bcd\u0ba9\u0ba4\u0bbe' \u0b86\u0b95\u0bbf\u0baf\u0bb5\u0bc8 \u0ba4\u0bca\u0b95\u0bc1\u0baa\u0bcd\u0baa\u0bc1\u0b95\u0bcd\u0b95\u0bc1 \u0baa\u0bb0\u0bbf\u0ba8\u0bcd\u0ba4\u0bc1\u0bb0\u0bc8\u0b95\u0bcd\u0b95\u0baa\u0bcd\u0baa\u0b9f\u0bcd\u0b9f \u0baa\u0b9f\u0bc8\u0baa\u0bcd\u0baa\u0bc1\u0b95\u0bb3\u0bcd.",
        "\u0b86\u0ba3\u0bcd\u0b9f\u0bbf\u0ba9\u0bcd \u0b9a\u0bbf\u0bb1\u0ba8\u0bcd\u0ba4 \u0b95\u0bb2\u0bcd\u0bb5\u0bbf\u0ba4\u0bcd \u0ba4\u0bca\u0b95\u0bc1\u0baa\u0bcd\u0baa\u0bc1\u0b95\u0bcd\u0b95\u0bbe\u0ba9 \u0bb5\u0bbf\u0bb0\u0bc1\u0ba4\u0bc1, \u0b95\u0bb2\u0bbe\u0ba8\u0bbf\u0ba4\u0bbf \u0baa\u0bbf\u0bb0\u0bc7\u0bae\u0b9a\u0bbf\u0bb1\u0bbf \u0ba8\u0bbe\u0b95\u0b9a\u0bbf\u0b99\u0bcd\u0b95\u0bb5\u0bbf\u0ba9\u0bcd '\u0b9a\u0bbf\u0b99\u0bcd\u0b95\u0bb3 \u0b89\u0baa\u0bbe\u0b9a\u0b95\u0baa\u0bcd\u0ba9\u0bbe\u0bb2\u0b99\u0bcd\u0b95\u0bbe\u0bb0\u0baf \u0baa\u0ba4\u0bbf\u0baa\u0bcd\u0baa\u0bc1\u0bae\u0bcd \u0bb5\u0bbf\u0bae\u0bb0\u0bcd\u0b9a\u0ba9 \u0b86\u0baf\u0bcd\u0bb5\u0bc1\u0bae\u0bcd', \u0ba4\u0bbf\u0bb0\u0bc1.\u0b9a\u0bae\u0ba9\u0bcd \u0baa\u0ba9\u0bbe\u0baa\u0bbf\u0b9f\u0bcd\u0b9f\u0bbf\u0baf\u0bb5\u0bbf\u0ba9\u0bcd '\u0b9a\u0bbf\u0b99\u0bcd\u0b95\u0bb3 \u0ba8\u0bbe\u0b9f\u0bcd\u0b9f\u0bc1\u0baa\u0bcd\u0baa\u0bc1\u0bb1 \u0baa\u0bbe\u0b9f\u0bc1\u0bae\u0bcd \u0baa\u0bbe\u0b99\u0bcd\u0b95\u0bc1\u0b95\u0bb3\u0bcd', \u0b9a\u0bbf\u0bb0\u0bc7\u0bb7\u0bcd\u0b9f \u0baa\u0bc7\u0bb0\u0bbe\u0b9a\u0bbf\u0bb0\u0bbf\u0baf\u0bb0\u0bcd \u0bae\u0bb9\u0bbf\u0ba8\u0bcd\u0ba4 \u0b9a\u0bcb\u0bae\u0ba4\u0bbf\u0bb2\u0b95\u0baf\u0bbf\u0ba9\u0bcd '\u0b95\u0bc6\u0baf\u0bc1\u0bb2\u0bcd\u0b95\u0bae \u0ba4\u0bb2\u0ba4\u0bbe \u0b95\u0bae\u0bcc\u0bb2\u0bcd\u0b95\u0baf\u0bbe', \u0bae\u0b95\u0bbf\u0ba8\u0bcd\u0ba4 \u0bae\u0bb4\u0bb2\u0bbf\u0b95\u0baf, \u0b9a\u0bae\u0bbe\u0bb2\u0bbf\u0b95. \u0ba4\u0bbf\u0bb0\u0bc1.\u0bb5\u0bbf\u0bae\u0bb2\u0b9a\u0bbf\u0bb1\u0bbf\u0baf\u0bbf\u0ba9\u0bcd '\u0b95\u0b9f\u0bb5\u0bb0 \u0b85\u0b9f\u0bb9\u0bbf\u0bae' \u0bae\u0bb1\u0bcd\u0bb1\u0bc1\u0bae\u0bcd \u0ba4\u0bbf\u0bb0\u0bc1\u0bae\u0ba4\u0bbf \u0b9a\u0ba8\u0bcd\u0ba4\u0bbf\u0baf\u0bbe \u0b95\u0bb9\u0ba8\u0bcd\u0ba4\u0b95\u0bae\u0bb5\u0bbf\u0ba9\u0bcd '\u0b9a\u0b99\u0bcd\u0b95\u0bbf\u0baf \u0baa\u0bc1\u0bb0\u0bbe\u0ba3\u0bae\u0bcd' \u0b86\u0b95\u0bbf\u0baf \u0b90\u0ba8\u0bcd\u0ba4\u0bc1 \u0baa\u0b9f\u0bc8\u0baa\u0bcd\u0baa\u0bc1\u0b95\u0bb3\u0bcd \u0baa\u0bb0\u0bbf\u0ba8\u0bcd\u0ba4\u0bc1\u0bb0\u0bc8\u0b95\u0bcd\u0b95\u0baa\u0bcd\u0baa\u0b9f\u0bcd\u0b9f\u0bc1\u0bb3\u0bcd\u0bb3\u0ba9.",
        "\u0bb8\u0bcd\u0bb0\u0bc0 \u0b9c\u0baf\u0bb5\u0bb0\u0bcd\u0ba4\u0ba9\u0baa\u0bc1\u0bb0 \u0baa\u0bb2\u0bcd\u0b95\u0bb2\u0bc8\u0b95\u0bcd\u0b95\u0bb4\u0b95\u0ba4\u0bcd\u0ba4\u0bbf\u0ba9\u0bcd \u0bae\u0ba9\u0bbf\u0ba4\u0ba8\u0bc7\u0baf \u0bae\u0bb1\u0bcd\u0bb1\u0bc1\u0bae\u0bcd \u0b9a\u0bae\u0bc2\u0b95 \u0bb5\u0bbf\u0b9e\u0bcd\u0b9e\u0bbe\u0ba9 \u0baa\u0bc0\u0b9f\u0ba4\u0bcd\u0ba4\u0bbf\u0ba9\u0bcd \u0b86\u0b9a\u0bbf\u0bb0\u0bbf\u0baf \u0b95\u0bc1\u0bb4\u0bc1\u0bb5\u0bbf\u0ba9\u0bbe\u0bb2\u0bcd \u0b8f\u0bb1\u0bcd\u0baa\u0bbe\u0b9f\u0bc1 \u0b9a\u0bc6\u0baf\u0bcd\u0baf\u0baa\u0bcd\u0baa\u0b9f\u0bcd\u0b9f \u0b87\u0ba8\u0bcd\u0ba4 \u0b87\u0bb2\u0b95\u0bcd\u0b95\u0bbf\u0baf \u0bb5\u0bbf\u0bb0\u0bc1\u0ba4\u0bc1 \u0bb5\u0bbf\u0bb4\u0bbe \u0b87\u0bb5\u0bcd\u0bb5\u0bb0\u0bc1\u0b9f\u0bae\u0bcd 13 \u0b86\u0bb5\u0ba4\u0bc1 \u0ba4\u0b9f\u0bb5\u0bc8\u0baf\u0bbe\u0b95 \u0ba8\u0b9f\u0bc8\u0baa\u0bc6\u0bb1\u0bc1\u0b95\u0bbf\u0ba9\u0bcd\u0bb1\u0ba4\u0bc1.",
        "\u0b87\u0bae\u0bcd\u0bae\u0bc1\u0bb1\u0bc8 \u0baa\u0bbf\u0bb0\u0ba4\u0bae \u0b85\u0ba4\u0bbf\u0ba4\u0bbf\u0baf\u0bbe\u0b95 \u0bb8\u0bcd\u0bb0\u0bc0 \u0b9c\u0baf\u0bb5\u0bb0\u0bcd\u0ba4\u0ba9\u0baa\u0bc1\u0bb0 \u0baa\u0bb2\u0bcd\u0b95\u0bb2\u0bc8\u0b95\u0bcd\u0b95\u0bb4\u0b95\u0ba4\u0bcd\u0ba4\u0bbf\u0ba9\u0bcd \u0b9a\u0bbf\u0b99\u0bcd\u0b95\u0bb3\u0baa\u0bcd \u0baa\u0bbf\u0bb0\u0bbf\u0bb5\u0bbf\u0ba9\u0bcd \u0b9a\u0bbf\u0bb0\u0bc7\u0bb7\u0bcd\u0b9f \u0baa\u0bc7\u0bb0\u0bbe\u0b9a\u0bbf\u0bb0\u0bbf\u0baf\u0bb0\u0bcd \u0ba4\u0bbf\u0bb0\u0bc1 \u0b86\u0ba9\u0ba8\u0bcd\u0ba4 \u0ba4\u0bbf\u0bb8\u0bcd\u0bb8 \u0b95\u0bc1\u0bae\u0bbe\u0bb0 \u0b95\u0bb2\u0ba8\u0bcd\u0ba4\u0bc1 \u0b95\u0bca\u0bb3\u0bcd\u0bb3\u0bb5\u0bc1\u0bb3\u0bcd\u0bb3\u0bbe\u0bb0\u0bcd."
      ],
      "title_ents": [],
      "body_line_ents_list": [
        [
          {
            "text": "\u0bb8\u0bcd\u0bb0\u0bc0 \u0b9c\u0baf\u0bb5\u0bb0\u0bcd\u0ba4\u0ba9\u0baa\u0bc1\u0bb0 \u0baa\u0bb2\u0bcd\u0b95\u0bb2\u0bc8\u0b95\u0bcd\u0b95\u0bb4\u0b95\u0ba4\u0bcd\u0ba4\u0bbf\u0ba9\u0bcd \u0b9a\u0bc1\u0bae\u0b99\u0bcd\u0b95\u0bb2\u0bbe \u0bae\u0ba3\u0bcd\u0b9f\u0baa\u0bae\u0bcd",
            "label": "FAC"
          },
          {
            "text": "\u0b9a\u0bc6\u0baa\u0bcd\u0b9f\u0bae\u0bcd\u0baa\u0bb0\u0bcd 1",
            "label": "DATE"
          },
          {
            "text": "3:00 PM",
            "label": "TIME"
          }
        ],
        [
          {
            "text": "\u0b86\u0ba3\u0bcd\u0b9f\u0bc1",
            "label": "DATE"
          }
        ],
        [
          {
            "text": "\u0b86\u0ba3\u0bcd\u0b9f\u0bc1",
            "label": "DATE"
          },
          {
            "text": "\u0b86\u0ba3\u0bcd\u0b9f\u0bc1",
            "label": "DATE"
          },
          {
            "text": "\u0b9a\u0bc6\u0baa\u0bbe\u0bb2\u0bbf \u0bae\u0bbe\u0baf\u0bbe\u0ba4\u0bc1\u0ba9\u0bcd\u0ba9\u0bc7",
            "label": "PERSON"
          },
          {
            "text": "\u0bb8\u0ba8\u0bcd\u0ba4\u0bcd\u0baf\u0bbe\u0ba8\u0ba8\u0bcd\u09a6\u0bbe\u0baf",
            "label": "PERSON"
          },
          {
            "text": "\u0b95\u0bc0\u0bb0\u0bcd\u0ba4\u0bcd\u0ba4\u0bbf \u0bb5\u0bc6\u0bb2\u0bbf\u0b9a\u0bb0\u0b95\u0bc7",
            "label": "PERSON"
          },
          {
            "text": "\u0bb7\u0bbe\u0bae\u0bb2\u0bcd \u0b9c\u0bc6\u0baf\u0b95\u0bcd\u0b95\u0bca\u0b9f\u0bbf",
            "label": "PERSON"
          },
          {
            "text": "\u0baa\u0bbf\u0bb0\u0bc7\u0bae\u0ba9\u0bbf\u0bb7\u0bbe\u0ba9\u0bcd\u0b9a\u0bbe",
            "label": "PERSON"
          },
          {
            "text": "\u0b9a\u0ba8\u0bcd\u0ba4\u0bbf\u0bb0\u0bb0\u0ba4\u0bcd\u0ba9 \u0baa\u0ba3\u0bcd\u0b9f\u0bbe\u0bb0",
            "label": "PERSON"
          },
          {
            "text": "\u0ba8\u0b95\u0bc1\u0bb2\u0ba9\u0bcd",
            "label": "PERSON"
          },
          {
            "text": "\u0b8e\u0bb0\u0bbf\u0b95\u0bcd \u0b87\u0bb3\u0bc8\u0baf\u0baa\u0bbe\u0bb0\u0bbe\u0b9a\u0bcd\u0b9a\u0bbf",
            "label": "PERSON"
          }
        ],
        [
          {
            "text": "\u0b86\u0ba3\u0bcd\u0b9f\u0bc1",
            "label": "DATE"
          },
          {
            "text": "'\u0b9a\u0bb0\u0bcd\u0bb5\u0ba4\u0bc7\u0b9a \u0b92\u0baa\u0bcd\u0baa\u0bc1\u0ba4\u0bb2\u0bcd\u0b95\u0bb3\u0bcd'",
            "label": "ORG"
          },
          {
            "text": "\u0b8e\u0bb0\u0bbf\u0b95\u0bcd \u0b87\u0bb3\u0bc8\u0baf\u0baa\u0bbe\u0bb0\u0bbe\u0b9a\u0bcd\u0b9a\u0bbf",
            "label": "PERSON"
          },
          {
            "text": "\u0bae\u0bb9\u0bbf\u0ba8\u0bcd\u0ba4 \u0bb0\u0ba4\u0bcd\u0ba8\u0bbe\u0baf\u0b95\u0bcd\u0b95",
            "label": "PERSON"
          },
          {
            "text": "\u0b89\u0baa\u0bbe\u0bb2\u0bbf \u0b89\u0baa\u0baf\u0b9a\u0bc7\u0b95\u0bb0",
            "label": "PERSON"
          },
          {
            "text": "\u0bae\u0bbe\u0bb5\u0ba4\u0b95 \u0bae\u0bbf\u0bae\u0bbf\u0ba9\u0bbf\u0bb2\u0bbe'",
            "label": "PERSON"
          },
          {
            "text": "\u0bae\u0bb2\u0bbf\u0ba8\u0bcd\u0ba4\u0bc1 \u0b95\u0bbe\u0bb5\u0bbf\u0ba8\u0bcd\u0ba4 \u0b95\u0bc1\u0bae\u0bbe\u0bb0\u0b9a\u0bbf\u0b99\u0bcd\u0b95",
            "label": "PERSON"
          },
          {
            "text": "\u0b87\u0bb3\u0bb5\u0bb0\u0b9a\u0bb0\u0bcd \u0b9a\u0bc7\u0ba9\u0bbe\u0ba4\u0bc0\u0bb0",
            "label": "PERSON"
          },
          {
            "text": "\u0b95\u0bb0\u0bc1\u0baa\u0bcd\u0baa\u0bc1 \u0b89\u0baf\u0bb0\u0bae\u0bbe\u0ba9 \u0bae\u0ba9\u0bbf\u0ba4\u0ba9\u0bcd",
            "label": "WORK_OF_ART"
          }
        ],
        [
          {
            "text": "\u0b90\u0ba8\u0bcd\u0ba4\u0bc1",
            "label": "CARDINAL"
          },
          {
            "text": "\u0b86\u0ba3\u0bcd\u0b9f\u0bc1 \u0bb5\u0bbf\u0bb0\u0bc1\u0ba4\u0bc1",
            "label": "DATE"
          },
          {
            "text": "\u0bb2\u0b95\u0bcd\u0bb7\u0bbe\u0ba8\u0bcd\u0ba4 \u0b85\u0ba4\u0bcd\u0ba4\u0bc1\u0b95\u0bcb\u0bb0\u0bb2\u0bb5\u0bbf\u0ba9\u0bcd",
            "label": "PERSON"
          },
          {
            "text": "\u0bb2\u0bbf\u0baf\u0bbe\u0b9a\u0bb5\u0bcd \u0bb2\u0bbf\u0bb9\u0bbf",
            "label": "PERSON"
          },
          {
            "text": "\u0b95\u0baf\u0bbe \u0b95\u0ba3\u0b9a\u0bae\u0b9f\u0bc1\u0bb2\u0bc1'",
            "label": "PERSON"
          },
          {
            "text": "Sureka Samarasena",
            "label": "PERSON"
          },
          {
            "text": "'\u0bb5\u0bae\u0bcd \u0baa\u0bbf\u0baf\u0bb5\u0bc1\u0bb0'",
            "label": "WORK_OF_ART"
          },
          {
            "text": "\u0b85\u0ba9\u0bc1\u0bb0\u0bbe\u0ba4\u0bbe \u0ba8\u0bbf\u0bb2\u0bcd\u0bae\u0bbf\u0ba9\u0bbf",
            "label": "PERSON"
          },
          {
            "text": "'\u0ba8\u0bbe\u0bb0\u0bbf \u0b9a\u0bc2\u0ba4\u0bcd\u0bb0\u0bbe (\u0b95\u0bb5\u0bbf\u0ba4\u0bc8",
            "label": "WORK_OF_ART"
          },
          {
            "text": "\u0b9a\u0ba8\u0bcd\u0ba4\u0bb0\u0b9a\u0bc0 \u0b9a\u0bc1\u0ba4\u0bc1\u0b9a\u0bbf\u0b99\u0bcd\u0b95\u0bb5\u0bbf\u0ba9\u0bcd",
            "label": "PERSON"
          },
          {
            "text": "\u0b87\u0bb1\u0b95\u0bcd\u0b95\u0bc8\u0b95\u0bb3\u0bcd'",
            "label": "ORG"
          },
          {
            "text": "\u0b8e\u0bb0\u0bbf\u0b95\u0bcd \u0b87\u0bb3\u0bc8\u0baf\u0baa\u0bb0\u0bbe\u0b9a\u0bcd\u0b9a\u0bbf\u0baf\u0bbf\u0ba9\u0bcd",
            "label": "PERSON"
          },
          {
            "text": "\u0baa\u0bcd\u0bb0\u0bcb\u0bae\u0bbf\u0ba4\u0bbf\u0baf\u0bb8\u0bcd \u0ba4\u0bc0\u0bb5\u0bc1",
            "label": "LOC"
          }
        ],
        [
          {
            "text": "\u0b86\u0ba3\u0bcd\u0b9f\u0bc1",
            "label": "DATE"
          },
          {
            "text": "\u0bae\u0bc2\u0ba9\u0bcd\u0bb1\u0bc1",
            "label": "CARDINAL"
          },
          {
            "text": "\u0baa\u0bbf\u0bb0\u0bae\u0baf\u0bc8 \u0bae\u0ba9\u0bb0\u0bae\u0bcd'",
            "label": "WORK_OF_ART"
          },
          {
            "text": "\u0baf\u0bae\u0bc1\u0ba9\u0bbe \u0bae\u0bbe\u0bb2\u0bbf\u0ba9\u0bbf \u0baa\u0bc6\u0bb0\u0bc7\u0bb0\u0bbe",
            "label": "PERSON"
          },
          {
            "text": "\u0bb5\u0b9a\u0ba8\u0bcd\u0ba4\u0bbe",
            "label": "PERSON"
          },
          {
            "text": "Kumara Kobawaka",
            "label": "PERSON"
          },
          {
            "text": "\u0b9a\u0ba3\u0bcd\u0b9f\u0bae\u0b9f\u0bb2 \u0bb5\u0bc0'",
            "label": "PERSON"
          },
          {
            "text": "\u0baa\u0bb2\u0bcd\u0bb2\u0bc7\u0b95\u0bae",
            "label": "GPE"
          },
          {
            "text": "\u0bb9\u0bc7\u0bae\u0bb0\u0ba4\u0bcd\u0ba4\u0ba9 \u0ba4\u0bc7\u0bb0\u0bcb",
            "label": "PERSON"
          },
          {
            "text": "\u0b86\u0ba3\u0bcd\u0b9f\u0bc1",
            "label": "DATE"
          },
          {
            "text": "\u0bb5\u0ba9\u0bcd\u0ba9\u0bbf\u0b95\u0bc7 \u0b95\u0bcb\u0bb2\u0bae\u0bbe'",
            "label": "PERSON"
          },
          {
            "text": "\u0ba8\u0baf\u0ba9\u0b9a\u0bc7\u0ba9 \u0bb5\u0ba9\u0bcd\u0ba9\u0bbf\u0ba8\u0bbe\u0baf\u0b95\u0bcd\u0b95",
            "label": "PERSON"
          },
          {
            "text": "\u0baa\u0bc1\u0ba4\u0bcd\u0ba4\u0ba4\u0bbe\u0b9a \u0b95\u0bb2\u0baa\u0bcd\u0baa\u0b9f\u0bcd\u0b9f\u0bbf",
            "label": "PERSON"
          },
          {
            "text": "\u0ba8\u0bbf\u0ba9\u0bcd\u0ba9\u0bbe\u0b9f\u0bbe",
            "label": "PERSON"
          },
          {
            "text": "\u0bb9\u0bb0\u0bcd\u0bb7\u0bbf\u0ba9\u0bbf \u0baa\u0bc1\u0bb7\u0bcd\u0baa\u0bae\u0bbe\u0bb2\u0bbe \u0b86\u0bb0\u0bbe\u0b9a\u0bcd\u0b9a\u0bbf",
            "label": "PERSON"
          }
        ],
        [
          {
            "text": "\u0b86\u0ba3\u0bcd\u0b9f\u0bc1 \u0bb5\u0bbf\u0bb0\u0bc1\u0ba4\u0bc1",
            "label": "DATE"
          },
          {
            "text": "\u0baa\u0bbf\u0bb0\u0bc7\u0bae\u0b9a\u0bbf\u0bb1\u0bbf \u0ba8\u0bbe\u0b95\u0b9a\u0bbf\u0b99\u0bcd\u0b95",
            "label": "PERSON"
          },
          {
            "text": "\u0b9a\u0bbf\u0b99\u0bcd\u0b95\u0bb3 \u0b89\u0baa\u0bbe\u0b9a\u0b95\u0baa\u0bcd\u0ba8\u0bb2\u0b99\u0bcd\u0b95\u0bb0\u0bbe\u0baf \u0baa\u0ba4\u0bbf\u0baa\u0bcd\u0baa\u0bc1 \u0bae\u0bb1\u0bcd\u0bb1\u0bc1\u0bae\u0bcd \u0bb5\u0bbf\u0bae\u0bb0\u0bcd\u0b9a\u0ba9 \u0b86\u0baf\u0bcd\u0bb5\u0bc1'",
            "label": "WORK_OF_ART"
          },
          {
            "text": "\u0b9a\u0bae\u0ba9\u0bcd \u0baa\u0ba9\u0bbe\u0baa\u0bbf\u0b9f\u0bcd\u0b9f\u0bbf\u0baf",
            "label": "PERSON"
          },
          {
            "text": "\u0bae\u0bb9\u0bbf\u0ba8\u0bcd\u0ba4 \u0b9a\u0bcb\u0bae\u0ba4\u0bbf\u0bb2\u0b95\u0bcd\u0b95\u0bb5\u0bbf\u0ba9\u0bcd",
            "label": "PERSON"
          },
          {
            "text": "\u0b95\u0bc6\u0baf\u0bc1\u0bb2\u0bcd\u0b95\u0bae \u0ba4\u0bb2\u0ba4\u0bbe",
            "label": "PERSON"
          },
          {
            "text": "\u0bae\u0bb9\u0bbf\u0ba8\u0bcd\u0ba4 \u0b95\u0bc7. \u0b90\u0ba8\u0bcd\u0ba4\u0bc1",
            "label": "ORG"
          },
          {
            "text": "\u0bb5\u0bbf\u0bae\u0bb2\u0b9a\u0bbf\u0bb1\u0bbf",
            "label": "PERSON"
          },
          {
            "text": "\u0b95\u0b9f\u0bb5\u0bb0 \u0b85\u0b9f\u0bb9\u0bbf\u0bae\u0bbe'",
            "label": "PERSON"
          },
          {
            "text": "\u0b9a\u0ba8\u0bcd\u0ba4\u0bbf\u0baf\u0bbe \u0b95\u0bb9\u0ba8\u0bcd\u0ba4\u0b95\u0bae\u0bb5\u0bbf\u0ba9\u0bcd",
            "label": "PERSON"
          },
          {
            "text": "\u0b9a\u0b99\u0bcd\u0b95\u0bbf\u0baf \u0baa\u0bc1\u0bb0\u0bbe\u0ba3\u0bae\u0bcd'",
            "label": "WORK_OF_ART"
          }
        ],
        [
          {
            "text": "\u0bae\u0ba9\u0bbf\u0ba4\u0ba8\u0bc7\u0baf\u0bae\u0bcd \u0bae\u0bb1\u0bcd\u0bb1\u0bc1\u0bae\u0bcd \u0b9a\u0bae\u0bc2\u0b95 \u0b85\u0bb1\u0bbf\u0bb5\u0bbf\u0baf\u0bb2\u0bcd \u0baa\u0bc0\u0b9f\u0ba4\u0bcd\u0ba4\u0bbf\u0ba9\u0bcd \u0b86\u0b9a\u0bbf\u0bb0\u0bbf\u0baf \u0b95\u0bc1\u0bb4\u0bc1",
            "label": "ORG"
          },
          {
            "text": "\u0bb8\u0bcd\u0bb0\u0bc0 \u0b9c\u0bc6\u0baf\u0bb5\u0bb0\u0bcd\u0ba4\u0ba9\u0baa\u0bc1\u0bb0 \u0baa\u0bb2\u0bcd\u0b95\u0bb2\u0bc8\u0b95\u0bcd\u0b95\u0bb4\u0b95\u0bae\u0bcd",
            "label": "ORG"
          },
          {
            "text": "13\u0bb5\u0ba4\u0bc1",
            "label": "DATE"
          },
          {
            "text": "\u0b87\u0ba8\u0bcd\u0ba4 \u0bb5\u0bb0\u0bc1\u0b9f\u0bae\u0bcd",
            "label": "DATE"
          }
        ],
        [
          {
            "text": "\u0b86\u0ba9\u0ba8\u0bcd\u0ba4 \u0ba4\u0bbf\u0bb8\u0bcd\u0bb8 \u0b95\u0bc1\u0bae\u0bbe\u0bb0",
            "label": "PERSON"
          },
          {
            "text": "\u0bb8\u0bcd\u0bb0\u0bc0 \u0b9c\u0baf\u0bb5\u0bb0\u0bcd\u0ba4\u0ba9\u0baa\u0bc1\u0bb0 \u0baa\u0bb2\u0bcd\u0b95\u0bb2\u0bc8\u0b95\u0bcd\u0b95\u0bb4\u0b95\u0ba4\u0bcd\u0ba4\u0bbf\u0ba9\u0bcd \u0b9a\u0bbf\u0b99\u0bcd\u0b95\u0bb3\u0ba4\u0bcd \u0ba4\u0bc1\u0bb1\u0bc8",
            "label": "ORG"
          }
        ]
      ]
    }
  }
}