{
  "newspaper_id": "island-lk",
  "url": "http://island.lk/cipm-6th-research-symposium-adds-value-to-glocal-hrm/",
  "time_ut": 1658249760,
  "original_lang": "en",
  "original_title": "CIPM 6th Research Symposium adds value to \u2018Glocal\u2019 HRM",
  "text_idx": {
    "en": {
      "title": "CIPM 6th Research Symposium adds value to \u2018Glocal\u2019 HRM",
      "author": "Sahan Weerasooriya",
      "body_lines": [
        "CIPM Sri Lanka \u2013 the Nation\u2019s leader in human resource management, held the inauguration ceremony of the 6th Annual Research Symposium \u2018Glocalization of HRM Practices for Business Resilience\u2019 recently in hybrid mode with local and international participants, including Guest of Honor Johnny C. Taylor Jr \u2013 President & CEO SHRM USA, Keynote speaker Professor of HRM & Asia Studies, Monash Business School, Australia \u2013 Fang Lee Cooke together with local and international participants joining the Symposium hosts Jayantha Amerasinghe \u2013 President CIPM, Ken Vijayakumar \u2013 Vice President CIPM, Chris Obeysekera \u2013 CEO CIPM, Conference Chair \u2013 Prof Prasadini Gamage, Dilanjani Weerathunga \u2013 Conference secretary, G Weeratunga \u2013 Director, Professional & Academic Affairs, Himali Dassanayake \u2013 Director Operations, and Kamani Perera \u2013 Manager, Research, at the CIPM head office \u201cHR House\u201d in Colombo 5 via web technology. A very successful pre-symposium workshop on research methodology was conducted on the 25th of May by veteran researcher Dr. Ananda Jayawardene, Senior Lecturer/consultant, Postgraduate Institute of Management (PIM), University of Sri Jayewardenepura, Sri Lanka, which is a new feature to enrich the standard of the Symposium. The inauguration ceremony was followed by a full day of eye-opening research presentations, and technical and panel discussions on the 26th of May. The CIPM Research Symposium is organized by CIPM Standing Committee on Applied Research and Knowledge Centre under the guidance of President CIPM Sri Lanka.",
        "Following the welcome speech delivered by the Symposium Chair, addressing the Symposium, CIPM Sri Lanka President \u2013 Jayantha Amerasinghe said that the amount of primary or applied research conducted in Sri Lanka is very minimal. \u201cSince research is very important to get a first-hand and in-depth view of practical issues pertaining to human resource management, very early in my tenure as President, I requested that an R&D unit be set up at CIPM to add value to our understanding of HR leading to a deeper appreciation of the intricacies involved in managing and motivating people in these unprecedented times. Our aim is to be the leading center in bringing research to the forefront in this country and to be the differentiator in the market,\u201d he said and added that CIPM would be strengthening the research unit in the coming years.",
        "The people should be allowed to express their opinion at the earliest opportunity \u2013 CBEOU",
        "Leave a Reply Cancel replyYour email address will not be published. Required fields are marked *Comment Name *",
        "Save my name, email, and website in this browser for the next time I comment."
      ],
      "title_ents": [
        {
          "text": "CIPM 6th Research Symposium",
          "label": "ORG"
        }
      ],
      "body_line_ents_list": [
        [
          {
            "text": "6th",
            "label": "ORDINAL"
          },
          {
            "text": "Annual Research Symposium \u2018Glocalization of HRM Practices for Business Resilience\u2019",
            "label": "EVENT"
          },
          {
            "text": "Johnny C. Taylor Jr",
            "label": "PERSON"
          },
          {
            "text": "Keynote",
            "label": "ORG"
          },
          {
            "text": "Monash Business School",
            "label": "ORG"
          },
          {
            "text": "Australia",
            "label": "GPE"
          },
          {
            "text": "Fang Lee Cooke",
            "label": "PERSON"
          },
          {
            "text": "CIPM",
            "label": "PERSON"
          },
          {
            "text": "Ken Vijayakumar",
            "label": "PERSON"
          },
          {
            "text": "CIPM",
            "label": "PERSON"
          },
          {
            "text": "Chris Obeysekera",
            "label": "PERSON"
          },
          {
            "text": "CIPM",
            "label": "ORG"
          },
          {
            "text": "Prof Prasadini Gamage",
            "label": "PERSON"
          },
          {
            "text": "Dilanjani",
            "label": "NORP"
          },
          {
            "text": "G Weeratunga",
            "label": "ORG"
          },
          {
            "text": "Professional & Academic Affairs",
            "label": "ORG"
          },
          {
            "text": "Himali Dassanayake",
            "label": "PERSON"
          },
          {
            "text": "Operations",
            "label": "ORG"
          },
          {
            "text": "Kamani Perera",
            "label": "PERSON"
          },
          {
            "text": "CIPM",
            "label": "ORG"
          },
          {
            "text": "House",
            "label": "ORG"
          },
          {
            "text": "the 25th of May",
            "label": "DATE"
          },
          {
            "text": "Ananda Jayawardene",
            "label": "PERSON"
          },
          {
            "text": "Postgraduate Institute of Management",
            "label": "ORG"
          },
          {
            "text": "PIM",
            "label": "ORG"
          },
          {
            "text": "University of Sri Jayewardenepura",
            "label": "ORG"
          },
          {
            "text": "Sri Lanka",
            "label": "GPE"
          },
          {
            "text": "Symposium",
            "label": "ORG"
          },
          {
            "text": "a full day",
            "label": "DATE"
          },
          {
            "text": "26th",
            "label": "ORDINAL"
          },
          {
            "text": "May",
            "label": "DATE"
          },
          {
            "text": "The CIPM Research Symposium",
            "label": "ORG"
          },
          {
            "text": "CIPM Standing Committee on Applied Research and Knowledge Centre",
            "label": "ORG"
          },
          {
            "text": "CIPM Sri Lanka",
            "label": "PERSON"
          }
        ],
        [
          {
            "text": "the Symposium Chair",
            "label": "ORG"
          },
          {
            "text": "Symposium",
            "label": "FAC"
          },
          {
            "text": "Sri Lanka",
            "label": "LOC"
          },
          {
            "text": "Sri Lanka",
            "label": "GPE"
          },
          {
            "text": "first",
            "label": "ORDINAL"
          },
          {
            "text": "CIPM",
            "label": "ORG"
          },
          {
            "text": "CIPM",
            "label": "ORG"
          },
          {
            "text": "the coming years",
            "label": "DATE"
          }
        ],
        [],
        [],
        []
      ]
    },
    "si": {
      "title": "CIPM 6\u0dc0\u0db1 \u0db4\u0dbb\u0dca\u0dba\u0dda\u0dc2\u0dab \u0dc3\u0db8\u0dca\u0db8\u0db1\u0dca\u0dad\u0dca\u200d\u0dbb\u0dab\u0dba 'Glocal' HRM \u0dc0\u0dd9\u0dad \u0dc0\u0da7\u0dd2\u0db1\u0dcf\u0d9a\u0db8\u0d9a\u0dca \u0d91\u0d9a\u0dca \u0d9a\u0dbb\u0dba\u0dd2",
      "author": "\u0dc3\u0dc4\u0db1\u0dca \u0dc0\u0dd3\u0dbb\u0dc3\u0dd6\u0dbb\u0dd2\u0dba",
      "body_lines": [
        "\u0db8\u0dcf\u0db1\u0dc0 \u0dc3\u0db8\u0dca\u0db4\u0dad\u0dca \u0d9a\u0dc5\u0db8\u0db1\u0dcf\u0d9a\u0dbb\u0dab\u0dba\u0dda \u0da2\u0dcf\u0dad\u0dd2\u0dba\u0dda \u0db4\u0dca\u200d\u0dbb\u0db8\u0dd4\u0d9b\u0dba\u0dcf \u0dc0\u0db1 CIPM \u0dc1\u0dca\u200d\u0dbb\u0dd3 \u0dbd\u0d82\u0d9a\u0dcf, 6 \u0dc0\u0dd0\u0db1\u0dd2 \u0dc0\u0dcf\u0dbb\u0dca\u0dc2\u0dd2\u0d9a \u0db4\u0dbb\u0dca\u0dba\u0dda\u0dc2\u0dab \u0dc3\u0db8\u0dca\u0db8\u0db1\u0dca\u0dad\u0dca\u200d\u0dbb\u0dab\u0dba\u0dda \u0dc3\u0db8\u0dcf\u0dbb\u0db8\u0dca\u0db7\u0d9a \u0d8b\u0dad\u0dca\u0dc3\u0dc0\u0dba '\u0dc0\u0dca\u200d\u0dba\u0dcf\u0db4\u0dcf\u0dbb \u0d94\u0dbb\u0ddc\u0dad\u0dca\u0dad\u0dd4 \u0daf\u0dd3\u0db8\u0dda \u0dc4\u0dd0\u0d9a\u0dd2\u0dba\u0dcf\u0dc0 \u0dc3\u0db3\u0dc4\u0dcf HRM \u0db4\u0dd2\u0dc5\u0dd2\u0dc0\u0dd9\u0dad\u0dca \u0d9c\u0ddd\u0dbd\u0dd3\u0dba\u0d9a\u0dbb\u0dab\u0dba' \u0d9c\u0dde\u0dbb\u0dc0\u0db1\u0dd3\u0dba \u0d86\u0dbb\u0dcf\u0db0\u0dd2\u0dad \u0d85\u0db8\u0dd4\u0dad\u0dca\u0dad\u0dcf \u0dc0\u0db1 Johnny C. Taylor Jr \u0d87\u0dad\u0dd4\u0dc5\u0dd4 \u0daf\u0dda\u0dc1\u0dd3\u0dba \u0dc4\u0dcf \u0da2\u0dcf\u0dad\u0dca\u200d\u0dba\u0db1\u0dca\u0dad\u0dbb \u0dc3\u0dc4\u0db7\u0dcf\u0d9c\u0dd3\u0dc0\u0db1\u0dca\u0db1\u0db1\u0dca \u0dc3\u0db8\u0d9f \u0daf\u0dd9\u0db8\u0dd4\u0dc4\u0dd4\u0db1\u0dca \u0d86\u0d9a\u0dcf\u0dbb\u0dba\u0dd9\u0db1\u0dca \u0db4\u0dc3\u0dd4\u0d9c\u0dd2\u0dba\u0daf\u0dcf \u0db4\u0dc0\u0dad\u0dca\u0dc0\u0db1 \u0dbd\u0daf\u0dd3. - \u0dc3\u0db7\u0dcf\u0db4\u0dad\u0dd2 \u0dc3\u0dc4 \u0db4\u0dca\u200d\u0dbb\u0db0\u0dcf\u0db1 \u0dc0\u0dd2\u0db0\u0dcf\u0dba\u0d9a \u0db1\u0dd2\u0dbd\u0db0\u0dcf\u0dbb\u0dd3 SHRM USA, \u0db4\u0dca\u200d\u0dbb\u0db0\u0dcf\u0db1 \u0d9a\u0dae\u0dd2\u0d9a\u0dba\u0dcf HRM \u0dc3\u0dc4 \u0d86\u0dc3\u0dd2\u0dba\u0dcf \u0d85\u0db0\u0dca\u200d\u0dba\u0dba\u0db1\u0dba \u0db4\u0dd2\u0dc5\u0dd2\u0db6\u0db3 \u0db8\u0dc4\u0dcf\u0da0\u0dcf\u0dbb\u0dca\u0dba, \u0db8\u0ddc\u0db1\u0dd1\u0dc2\u0dca \u0dc0\u0dca\u200d\u0dba\u0dcf\u0db4\u0dcf\u0dbb\u0dd2\u0d9a \u0db4\u0dcf\u0dc3\u0dbd, \u0d95\u0dc3\u0dca\u0da7\u0dca\u200d\u0dbb\u0dda\u0dbd\u0dd2\u0dba\u0dcf\u0dc0 - Fang Lee Cooke \u0dc3\u0dc4 \u0daf\u0dda\u0dc1\u0dd3\u0dba \u0dc4\u0dcf \u0da2\u0dcf\u0dad\u0dca\u200d\u0dba\u0db1\u0dca\u0dad\u0dbb \u0dc3\u0dc4\u0db7\u0dcf\u0d9c\u0dd2\u0dc0\u0db1\u0dca\u0db1\u0db1\u0dca \u0dc3\u0db8\u0d9f \u0dc3\u0db8\u0dca\u0db8\u0db1\u0dca\u0dad\u0dca\u200d\u0dbb\u0dab\u0dba\u0da7 \u0dc3\u0db8\u0dca\u0db6\u0db1\u0dca\u0db0 \u0dc0\u0dda \u0da2\u0dba\u0db1\u0dca\u0dad \u0d85\u0db8\u0dbb\u0dc3\u0dd2\u0d82\u0dc4 - \u0dc3\u0db7\u0dcf\u0db4\u0dad\u0dd2 CIPM, Ken Vijayakumar - \u0d8b\u0db4 \u0dc3\u0db7\u0dcf\u0db4\u0dad\u0dd2 CIPM, \u0d9a\u0dca\u200d\u0dbb\u0dd2\u0dc3\u0dca \u0d94\u0db6\u0dda\u0dc3\u0dda\u0d9a\u0dbb - \u0db4\u0dca\u200d\u0dbb\u0db0\u0dcf\u0db1 \u0dc0\u0dd2\u0db0\u0dcf\u0dba\u0d9a \u0db1\u0dd2\u0dbd\u0db0\u0dcf\u0dbb\u0dd3 CIPM, \u0dc3\u0db8\u0dca\u0db8\u0db1\u0dca\u0dad\u0dca\u200d\u0dbb\u0dab \u0db8\u0dd6\u0dbd\u0dcf\u0dc3\u0db1\u0dba - \u0db8\u0dc4\u0dcf\u0da0\u0dcf\u0dbb\u0dca\u0dba \u0db4\u0dca\u200d\u0dbb\u0dc3\u0dcf\u0daf\u0dd2\u0db1\u0dd3 \u0d9c\u0db8\u0d9c\u0dda, \u0da9\u0dd2\u0dbd\u0dcf\u0d82\u0da2\u0db1\u0dd3 \u0dc0\u0dd3\u0dbb\u0dad\u0dd4\u0d82\u0d9c - \u0dc3\u0db8\u0dca\u0db8\u0db1\u0dca\u0dad\u0dca\u200d\u0dbb\u0dab \u0dbd\u0dda\u0d9a\u0db8\u0dca, \u0da2\u0dd3 \u0dc0\u0dd3\u0dbb\u0dad\u0dd4\u0d82\u0d9c - \u0d85\u0db0\u0dca\u200d\u0dba\u0d9a\u0dca\u0dc2, \u0dc0\u0dd8\u0dad\u0dca\u0dad\u0dd3\u0dba \u0dc3\u0dc4 \u0d85\u0db0\u0dca\u200d\u0dba\u0dba\u0db1 \u0d9a\u0da7\u0dba\u0dd4\u0dad\u0dd4, \u0dc4\u0dd2\u0db8\u0dcf\u0dbd\u0dd2 \u0daf\u0dc3\u0db1\u0dcf\u0dba\u0d9a - \u0d85\u0db0\u0dca\u200d\u0dba\u0d9a\u0dca\u0dc2 \u0db8\u0dd9\u0dc4\u0dd9\u0dba\u0dd4\u0db8\u0dca, \u0dc3\u0dc4 \u0d9a\u0db8\u0db1\u0dd2 \u0db4\u0dd9\u0dbb\u0dda\u0dbb\u0dcf - CIPM \u0db4\u0dca\u200d\u0dbb\u0db0\u0dcf\u0db1 \u0d9a\u0dcf\u0dbb\u0dca\u0dba\u0dcf\u0dbd\u0dba\u0dda \"HR House\" \u0dc4\u0dd2 \u0db4\u0dbb\u0dca\u0dba\u0dda\u0dc2\u0dab \u0dc0\u0dd9\u0db6\u0dca \u0dad\u0dcf\u0d9a\u0dca\u0dc2\u0dab\u0dba \u0dc4\u0dbb\u0dc4\u0dcf \u0d9a\u0ddc\u0dc5\u0db9 5 \u0daf\u0dd3. \u0db4\u0dbb\u0dca\u0dba\u0dda\u0dc2\u0dab \u0d9a\u0dca\u200d\u0dbb\u0db8\u0dc0\u0dda\u0daf\u0dba \u0db4\u0dd2\u0dc5\u0dd2\u0db6\u0db3 \u0d89\u0dad\u0dcf \u0dc3\u0dcf\u0dbb\u0dca\u0dae\u0d9a \u0db4\u0dd6\u0dbb\u0dca\u0dc0 \u0dc3\u0db8\u0dca\u0db8\u0db1\u0dca\u0dad\u0dca\u200d\u0dbb\u0dab \u0dc0\u0dd0\u0da9\u0db8\u0dd4\u0dc5\u0dd4\u0dc0\u0d9a\u0dca \u0db8\u0dd0\u0dba\u0dd2 \u0db8\u0dc3 25 \u0dc0\u0db1 \u0daf\u0dd2\u0db1 \u0db4\u0dca\u200d\u0dbb\u0dc0\u0dd3\u0dab \u0db4\u0dbb\u0dca\u0dba\u0dda\u0dc2\u0d9a \u0d86\u0da0\u0dcf\u0dbb\u0dca\u0dba \u0d86\u0db1\u0db1\u0dca\u0daf \u0da2\u0dba\u0dc0\u0dbb\u0dca\u0db0\u0db1, \u0da2\u0dca\u200d\u0dba\u0dd9\u0dc2\u0dca\u0da8 \u0d9a\u0dae\u0dd2\u0d9a\u0dcf\u0da0\u0dcf\u0dbb\u0dca\u0dba/\u0d8b\u0db4\u0daf\u0dda\u0dc1\u0d9a, \u0d9a\u0dc5\u0db8\u0db1\u0dcf\u0d9a\u0dbb\u0dab \u0db4\u0dc1\u0dca\u0da0\u0dcf\u0dad\u0dca \u0d8b\u0db4\u0dcf\u0db0\u0dd2 \u0d86\u0dba\u0dad\u0db1\u0dba (PIM), \u0dc1\u0dca\u200d\u0dbb\u0dd3 \u0dbd\u0d82\u0d9a\u0dcf \u0dc1\u0dca\u200d\u0dbb\u0dd3 \u0da2\u0dba\u0dc0\u0dbb\u0dca\u0db0\u0db1\u0db4\u0dd4\u0dbb \u0dc0\u0dd2\u0dc1\u0dca\u0dc0\u0dc0\u0dd2\u0daf\u0dca\u200d\u0dba\u0dcf\u0dbd\u0dba, \u0dc0\u0dd2\u0dc3\u0dd2\u0db1\u0dca \u0db4\u0dc0\u0dad\u0dca\u0dc0\u0db1 \u0dbd\u0daf\u0dd3. \u0dc3\u0db8\u0dca\u0db8\u0db1\u0dca\u0dad\u0dca\u200d\u0dbb\u0dab\u0dba\u0dda \u0db4\u0dca\u200d\u0dbb\u0db8\u0dd2\u0dad\u0dd2\u0dba \u0db4\u0ddc\u0dc4\u0ddc\u0dc3\u0dad\u0dca \u0d9a\u0dd2\u0dbb\u0dd3\u0db8\u0da7 \u0dc0\u0dd2\u0dc1\u0dda\u0dc2\u0dcf\u0d82\u0d9c\u0dba. \u0dc3\u0db8\u0dcf\u0dbb\u0db8\u0dca\u0db7\u0d9a \u0d8b\u0dad\u0dca\u0dc3\u0dc0\u0dba\u0dd9\u0db1\u0dca \u0db4\u0dc3\u0dd4\u0dc0 \u0db8\u0dd0\u0dba\u0dd2 26 \u0dc0\u0db1 \u0daf\u0dd2\u0db1 \u0db4\u0dd6\u0dbb\u0dca\u0dab \u0daf\u0dd2\u0db1\u0dba\u0d9a\u0dca \u0d87\u0dc3\u0dca \u0d87\u0dbb\u0dd9\u0db1 \u0db4\u0dbb\u0dca\u0dba\u0dda\u0dc2\u0dab \u0d89\u0daf\u0dd2\u0dbb\u0dd2\u0db4\u0dad\u0dca \u0d9a\u0dd2\u0dbb\u0dd3\u0db8\u0dca \u0dc3\u0dc4 \u0dad\u0dcf\u0d9a\u0dca\u0dc2\u0dab\u0dd2\u0d9a \u0dc4\u0dcf \u0dc0\u0dd2\u0daf\u0dca\u0dc0\u0dad\u0dca \u0dc3\u0dcf\u0d9a\u0da0\u0dca\u0da1\u0dcf \u0db4\u0dd0\u0dc0\u0dd0\u0dad\u0dca\u0dc0\u0dd2\u0dab\u0dd2. CIPM \u0db4\u0dbb\u0dca\u0dba\u0dda\u0dc2\u0dab \u0dc3\u0db8\u0dca\u0db8\u0db1\u0dca\u0dad\u0dca\u200d\u0dbb\u0dab\u0dba \u0dc3\u0d82\u0dc0\u0dd2\u0db0\u0dcf\u0db1\u0dba \u0d9a\u0dbb\u0db1\u0dd4 \u0dbd\u0db6\u0db1\u0dca\u0db1\u0dda CIPM \u0dc1\u0dca\u200d\u0dbb\u0dd3 \u0dbd\u0d82\u0d9a\u0dcf \u0dc3\u0db7\u0dcf\u0db4\u0dad\u0dd2\u0dc0\u0dbb\u0dba\u0dcf\u0d9c\u0dda \u0db8\u0d9c\u0db4\u0dd9\u0db1\u0dca\u0dc0\u0dd3\u0db8 \u0dba\u0da7\u0dad\u0dda \u0dc0\u0dca\u200d\u0dba\u0dc0\u0dc4\u0dcf\u0dbb\u0dd2\u0d9a \u0db4\u0dbb\u0dca\u0dba\u0dda\u0dc2\u0dab \u0dc3\u0dc4 \u0daf\u0dd0\u0db1\u0dd4\u0db8 \u0db8\u0db0\u0dca\u200d\u0dba\u0dc3\u0dca\u0dae\u0dcf\u0db1\u0dba \u0db4\u0dd2\u0dc5\u0dd2\u0db6\u0db3 CIPM \u0dc3\u0dca\u0dae\u0dcf\u0dc0\u0dbb \u0d9a\u0db8\u0dd2\u0da7\u0dd4\u0dc0 \u0dc0\u0dd2\u0dc3\u0dd2\u0db1\u0dd2.",
        "\u0dc3\u0db8\u0dca\u0db8\u0db1\u0dca\u0dad\u0dca\u200d\u0dbb\u0dab \u0db8\u0dd6\u0dbd\u0dcf\u0dc3\u0db1\u0dba \u0dc0\u0dd2\u0dc3\u0dd2\u0db1\u0dca \u0db4\u0dc0\u0dad\u0dca\u0dc0\u0db1 \u0dbd\u0daf \u0db4\u0dd2\u0dc5\u0dd2\u0d9c\u0dd0\u0db1\u0dd3\u0db8\u0dda \u0d9a\u0dad\u0dcf\u0dc0\u0dd9\u0db1\u0dca \u0d85\u0db1\u0dad\u0dd4\u0dbb\u0dd4\u0dc0, \u0dc3\u0db8\u0dca\u0db8\u0db1\u0dca\u0dad\u0dca\u200d\u0dbb\u0dab\u0dba \u0d85\u0db8\u0dad\u0db8\u0dd2\u0db1\u0dca, CIPM \u0dc1\u0dca\u200d\u0dbb\u0dd3 \u0dbd\u0d82\u0d9a\u0dcf \u0dc3\u0db7\u0dcf\u0db4\u0dad\u0dd2 - \u0da2\u0dba\u0db1\u0dca\u0dad \u0d85\u0db8\u0dbb\u0dc3\u0dd2\u0d82\u0dc4 \u0db4\u0dd0\u0dc0\u0dc3\u0dd4\u0dc0\u0dda, \u0dc1\u0dca\u200d\u0dbb\u0dd3 \u0dbd\u0d82\u0d9a\u0dcf\u0dc0 \u0dad\u0dd4\u0dc5 \u0dc3\u0dd2\u0daf\u0dd4 \u0d9a\u0dd9\u0dbb\u0dd9\u0db1 \u0db4\u0dca\u200d\u0dbb\u0dcf\u0dae\u0db8\u0dd2\u0d9a \u0dc4\u0ddd \u0dc0\u0dca\u200d\u0dba\u0dc0\u0dc4\u0dcf\u0dbb\u0dd2\u0d9a \u0db4\u0dbb\u0dca\u0dba\u0dda\u0dc2\u0dab \u0db4\u0dca\u200d\u0dbb\u0db8\u0dcf\u0dab\u0dba \u0d89\u0dad\u0dcf \u0d85\u0dc0\u0db8 \u0db6\u0dc0\u0dba\u0dd2. \u201c\u0db8\u0dcf\u0db1\u0dc0 \u0dc3\u0db8\u0dca\u0db4\u0dad\u0dca \u0d9a\u0dc5\u0db8\u0db1\u0dcf\u0d9a\u0dbb\u0dab\u0dba\u0da7 \u0d85\u0daf\u0dcf\u0dc5 \u0db4\u0dca\u200d\u0dbb\u0dcf\u0dba\u0ddd\u0d9c\u0dd2\u0d9a \u0d9c\u0dd0\u0da7\u0dbd\u0dd4 \u0db4\u0dd2\u0dc5\u0dd2\u0db6\u0db3\u0dc0 \u0db4\u0dca\u200d\u0dbb\u0dae\u0db8\u0dba\u0dd9\u0db1\u0dca \u0dc3\u0dc4 \u0d9c\u0dd0\u0db9\u0dd4\u0dbb\u0dd2\u0db1\u0dca \u0db6\u0dd0\u0dbd\u0dd3\u0db8 \u0dc3\u0db3\u0dc4\u0dcf \u0db4\u0dbb\u0dca\u0dba\u0dda\u0dc2\u0dab \u0d89\u0dad\u0dcf \u0dc0\u0dd0\u0daf\u0d9c\u0dad\u0dca \u0dc0\u0db1 \u0db6\u0dd0\u0dc0\u0dd2\u0db1\u0dca, \u0db8\u0dcf \u0da2\u0db1\u0dcf\u0db0\u0dd2\u0db4\u0dad\u0dd2\u0dc0\u0dbb\u0dba\u0dcf \u0dbd\u0dd9\u0dc3 \u0d9a\u0da7\u0dba\u0dd4\u0dad\u0dd4 \u0d9a\u0dc5 \u0db8\u0dd4\u0dbd\u0dca \u0d9a\u0dcf\u0dbd\u0dba\u0dda \u0daf\u0dd3, \u0d85\u0db4\u0d9c\u0dda \u0d85\u0d9c\u0dba \u0d91\u0d9a\u0dad\u0dd4 \u0d9a\u0dd2\u0dbb\u0dd3\u0db8 \u0dc3\u0db3\u0dc4\u0dcf CIPM \u0dc4\u0dd2 \u0db4\u0dbb\u0dca\u0dba\u0dda\u0dc2\u0dab \u0dc3\u0dc4 \u0dc3\u0d82\u0dc0\u0dbb\u0dca\u0db0\u0db1 \u0d92\u0d9a\u0d9a\u0dba\u0d9a\u0dca \u0db4\u0dd2\u0dc4\u0dd2\u0da7\u0dd4\u0dc0\u0db1 \u0dbd\u0dd9\u0dc3 \u0db8\u0db8 \u0d89\u0dbd\u0dca\u0dbd\u0dcf \u0dc3\u0dd2\u0da7\u0dd2\u0dba\u0dd9\u0db8\u0dd2. \u0db8\u0dcf\u0db1\u0dc0 \u0dc3\u0db8\u0dca\u0db4\u0dad\u0dca \u0db4\u0dd2\u0dc5\u0dd2\u0db6\u0db3 \u0d85\u0dc0\u0db6\u0ddd\u0db0\u0dba \u0db8\u0dd9\u0db8 \u0db4\u0dd9\u0dbb \u0db1\u0ddc\u0dc0\u0dd6 \u0dc0\u0dd2\u0dbb\u0dd6 \u0d9a\u0dcf\u0dbd\u0dc0\u0dbd\u0daf\u0dd3 \u0db8\u0dd2\u0db1\u0dd2\u0dc3\u0dd4\u0db1\u0dca \u0d9a\u0dc5\u0db8\u0db1\u0dcf\u0d9a\u0dbb\u0dab\u0dba \u0d9a\u0dd2\u0dbb\u0dd3\u0db8 \u0dc3\u0dc4 \u0d85\u0db7\u0dd2\u0db4\u0dca\u0dbb\u0dda\u0dbb\u0dab\u0dba \u0d9a\u0dd2\u0dbb\u0dd3\u0db8 \u0dc3\u0db8\u0dca\u0db6\u0db1\u0dca\u0db0\u0dc0 \u0d87\u0dad\u0dd2 \u0dc3\u0d82\u0d9a\u0dd3\u0dbb\u0dca\u0dab\u0dad\u0dcf \u0d9c\u0dd0\u0db9\u0dd4\u0dbb\u0dd2\u0db1\u0dca \u0d85\u0d9c\u0dba \u0d9a\u0dd2\u0dbb\u0dd3\u0db8\u0da7 \u0dc4\u0dda\u0dad\u0dd4 \u0dc0\u0dda. \u0d85\u0db4\u0dda \u0d85\u0dbb\u0db8\u0dd4\u0dab \u0db8\u0dda \u0dbb\u0da7\u0dda \u0db4\u0dbb\u0dca\u0dba\u0dda\u0dc2\u0dab \u0db4\u0dca\u200d\u0dbb\u0db8\u0dd4\u0d9b\u0dc3\u0dca\u0dae\u0dcf\u0db1\u0dba\u0da7 \u0d9c\u0dd9\u0db1 \u0d92\u0db8\u0dda \u0db4\u0dca\u200d\u0dbb\u0db8\u0dd4\u0d9b \u0db8\u0db0\u0dca\u200d\u0dba\u0dc3\u0dca\u0dae\u0dcf\u0db1\u0dba \u0dc0\u0dd3\u0db8 \u0dc3\u0dc4 \u0dc0\u0dd9\u0dc5\u0dd9\u0db3 \u0db4\u0ddc\u0dc5\u0dda \u0d85\u0dc0\u0d9a\u0dbd\u0db1\u0dba \u0dc0\u0dd3\u0db8,\u201d \u0d94\u0dc4\u0dd4 \u0db4\u0dca\u200d\u0dbb\u0d9a\u0dcf\u0dc1 \u0d9a\u0dc5 \u0d85\u0dad\u0dbb, \u0d89\u0daf\u0dd2\u0dbb\u0dd2 \u0dc0\u0dc3\u0dbb\u0dc0\u0dbd\u0daf\u0dd3 CIPM \u0db4\u0dbb\u0dca\u0dba\u0dda\u0dc2\u0dab \u0d85\u0d82\u0dc1\u0dba \u0dc1\u0d9a\u0dca\u0dad\u0dd2\u0db8\u0dad\u0dca \u0d9a\u0dd2\u0dbb\u0dd3\u0db8\u0da7 \u0d9a\u0da7\u0dba\u0dd4\u0dad\u0dd4 \u0d9a\u0dbb\u0db1 \u0db6\u0dc0\u0daf \u0db4\u0dd0\u0dc0\u0dc3\u0dd3\u0dba.",
        "\u0da2\u0db1\u0dad\u0dcf\u0dc0\u0da7 \u0dc4\u0dd0\u0d9a\u0dd2 \u0d89\u0d9a\u0dca\u0db8\u0db1\u0dd2\u0db1\u0dca \u0dad\u0db8 \u0db8\u0dad\u0dba \u0db4\u0dca\u200d\u0dbb\u0d9a\u0dcf\u0dc1 \u0d9a\u0dd2\u0dbb\u0dd3\u0db8\u0da7 \u0d89\u0da9 \u0daf\u0dd2\u0dba \u0dba\u0dd4\u0dad\u0dd4\u0dba - CBEOU",
        "\u0db4\u0dd2\u0dc5\u0dd2\u0dad\u0dd4\u0dbb\u0d9a\u0dca \u0daf\u0dd9\u0db1\u0dca\u0db1 \u0db4\u0dd2\u0dc5\u0dd2\u0dad\u0dd4\u0dbb \u0d85\u0dc0\u0dbd\u0d82\u0d9c\u0dd4 \u0d9a\u0dbb\u0db1\u0dca\u0db1 \u0d94\u0db6\u0d9c\u0dda \u0dc0\u0dd2\u0daf\u0dca\u200d\u0dba\u0dd4\u0dad\u0dca \u0dad\u0dd0\u0db4\u0dd0\u0dbd\u0dca \u0dbd\u0dd2\u0db4\u0dd2\u0db1\u0dba \u0db4\u0dca\u200d\u0dbb\u0d9a\u0dcf\u0dc1\u0dba\u0da7 \u0db4\u0dad\u0dca \u0db1\u0ddc\u0d9a\u0dd9\u0dbb\u0dda. \u0d85\u0dc0\u0dc1\u0dca\u200d\u0dba \u0d9a\u0dca\u0dc2\u0dda\u0dad\u0dca\u200d\u0dbb \u0dc3\u0dbd\u0d9a\u0dd4\u0dab\u0dd4 \u0d9a\u0dbb \u0d87\u0dad *\u0d85\u0daf\u0dc4\u0dc3\u0dca \u0db1\u0db8 *",
        "\u0db8\u0db8 \u0d8a\u0dc5\u0d9f \u0dc0\u0dad\u0dcf\u0dc0\u0dda \u0d85\u0daf\u0dc4\u0dc3\u0dca \u0daf\u0dd0\u0d9a\u0dca\u0dc0\u0dd3\u0db8 \u0dc3\u0db3\u0dc4\u0dcf \u0db8\u0d9c\u0dda \u0db1\u0db8, \u0dc0\u0dd2\u0daf\u0dca\u200d\u0dba\u0dd4\u0dad\u0dca \u0dad\u0dd0\u0db4\u0dd1\u0dbd \u0dc3\u0dc4 \u0dc0\u0dd9\u0db6\u0dca \u0d85\u0da9\u0dc0\u0dd2\u0dba \u0db8\u0dd9\u0db8 \u0db6\u0dca\u200d\u0dbb\u0dc0\u0dd4\u0dc3\u0dbb\u0dba\u0dda \u0dc3\u0dd4\u0dbb\u0d9a\u0dd2\u0db1\u0dca\u0db1."
      ],
      "title_ents": [
        {
          "text": "CIPM 6 \u0dc0\u0dd0\u0db1\u0dd2 \u0db4\u0dbb\u0dca\u0dba\u0dda\u0dc2\u0dab \u0dc3\u0db8\u0dca\u0db8\u0db1\u0dca\u0dad\u0dca\u200d\u0dbb\u0dab\u0dba",
          "label": "ORG"
        }
      ],
      "body_line_ents_list": [
        [
          {
            "text": "6 \u0dc0\u0dd0\u0db1\u0dd2",
            "label": "ORDINAL"
          },
          {
            "text": "\u0dc0\u0dcf\u0dbb\u0dca\u0dc2\u0dd2\u0d9a \u0db4\u0dbb\u0dca\u0dba\u0dda\u0dc2\u0dab \u0dc3\u0db8\u0dca\u0db8\u0db1\u0dca\u0dad\u0dca\u200d\u0dbb\u0dab\u0dba '\u0dc0\u0dca\u200d\u0dba\u0dcf\u0db4\u0dcf\u0dbb \u0d94\u0dbb\u0ddc\u0dad\u0dca\u0dad\u0dd4 \u0daf\u0dd3\u0db8\u0dda \u0dc4\u0dd0\u0d9a\u0dd2\u0dba\u0dcf\u0dc0 \u0dc3\u0db3\u0dc4\u0dcf \u0db8\u0dcf\u0db1\u0dc0 \u0dc3\u0db8\u0dca\u0db4\u0dad\u0dca \u0db4\u0dbb\u0dd2\u0da0\u0dba\u0db1\u0dca \u0d9c\u0ddd\u0dbd\u0dd3\u0dba\u0d9a\u0dbb\u0dab\u0dba'",
            "label": "EVENT"
          },
          {
            "text": "\u0da2\u0ddc\u0db1\u0dd3 \u0dc3\u0dd3 \u0da7\u0dda\u0dbd\u0dbb\u0dca \u0da2\u0dd6\u0db1\u0dd2\u0dba\u0dbb\u0dca",
            "label": "PERSON"
          },
          {
            "text": "\u0db4\u0dca\u0dbb\u0db0\u0dcf\u0db1 \u0daf\u0dda\u0dc1\u0db1\u0dba",
            "label": "ORG"
          },
          {
            "text": "\u0db8\u0ddc\u0db1\u0dd1\u0dc2\u0dca \u0dc0\u0dca\u200d\u0dba\u0dcf\u0db4\u0dcf\u0dbb\u0dd2\u0d9a \u0db4\u0dcf\u0dc3\u0dbd",
            "label": "ORG"
          },
          {
            "text": "\u0d95\u0dc3\u0dca\u0da7\u0dca\u0dbb\u0dda\u0dbd\u0dd2\u0dba\u0dcf\u0dc0",
            "label": "GPE"
          },
          {
            "text": "\u0dc6\u0dd0\u0db1\u0dca\u0d9c\u0dca \u0dbd\u0dd3 \u0d9a\u0dd4\u0d9a\u0dca",
            "label": "PERSON"
          },
          {
            "text": "CIPM",
            "label": "PERSON"
          },
          {
            "text": "\u0d9a\u0dd9\u0db1\u0dca \u0dc0\u0dd2\u0da2\u0dba\u0d9a\u0dd4\u0db8\u0dcf\u0dbb\u0dca",
            "label": "PERSON"
          },
          {
            "text": "CIPM",
            "label": "PERSON"
          },
          {
            "text": "\u0d9a\u0dca\u200d\u0dbb\u0dd2\u0dc3\u0dca \u0d94\u0db6\u0dda\u0dc3\u0dda\u0d9a\u0dbb",
            "label": "PERSON"
          },
          {
            "text": "CIPM",
            "label": "ORG"
          },
          {
            "text": "\u0db8\u0dc4\u0dcf\u0da0\u0dcf\u0dbb\u0dca\u0dba \u0db4\u0dca\u200d\u0dbb\u0dc3\u0dcf\u0daf\u0dd2\u0db1\u0dd3 \u0d9c\u0db8\u0d9c\u0dda",
            "label": "PERSON"
          },
          {
            "text": "\u0daf\u0dd2\u0dbd\u0dcf\u0d82\u0da2\u0db1\u0dd3",
            "label": "NORP"
          },
          {
            "text": "\u0da2\u0dd3 \u0dc0\u0dd3\u0dbb\u0dad\u0dd4\u0d82\u0d9c",
            "label": "ORG"
          },
          {
            "text": "\u0dc0\u0dd8\u0dad\u0dca\u0dad\u0dd3\u0dba \u0dc3\u0dc4 \u0dc1\u0dcf\u0dc3\u0dca\u0dad\u0dca\u200d\u0dbb\u0dd3\u0dba \u0d9a\u0da7\u0dba\u0dd4\u0dad\u0dd4",
            "label": "ORG"
          },
          {
            "text": "\u0dc4\u0dd2\u0db8\u0dcf\u0dbd\u0dd2 \u0daf\u0dc3\u0db1\u0dcf\u0dba\u0d9a",
            "label": "PERSON"
          },
          {
            "text": "\u0db8\u0dd9\u0dc4\u0dd9\u0dba\u0dd4\u0db8\u0dca",
            "label": "ORG"
          },
          {
            "text": "\u0d9a\u0db8\u0db1\u0dd2 \u0db4\u0dd9\u0dbb\u0dda\u0dbb\u0dcf",
            "label": "PERSON"
          },
          {
            "text": "CIPM",
            "label": "ORG"
          },
          {
            "text": "\u0db1\u0dd2\u0dc0\u0dc3",
            "label": "ORG"
          },
          {
            "text": "\u0db8\u0dd0\u0dba\u0dd2 25 \u0dc0\u0dd9\u0db1\u0dd2\u0daf\u0dcf",
            "label": "DATE"
          },
          {
            "text": "\u0d86\u0db1\u0db1\u0dca\u0daf \u0da2\u0dba\u0dc0\u0dbb\u0dca\u0db0\u0db1",
            "label": "PERSON"
          },
          {
            "text": "\u0d9a\u0dc5\u0db8\u0db1\u0dcf\u0d9a\u0dbb\u0dab \u0db4\u0dc1\u0dca\u0da0\u0dcf\u0dad\u0dca \u0d8b\u0db4\u0dcf\u0db0\u0dd2 \u0d86\u0dba\u0dad\u0db1\u0dba",
            "label": "ORG"
          },
          {
            "text": "PIM",
            "label": "ORG"
          },
          {
            "text": "\u0dc1\u0dca\u200d\u0dbb\u0dd3 \u0da2\u0dba\u0dc0\u0dbb\u0dca\u0db0\u0db1\u0db4\u0dd4\u0dbb \u0dc0\u0dd2\u0dc1\u0dca\u0dc0\u0dc0\u0dd2\u0daf\u0dca\u200d\u0dba\u0dcf\u0dbd\u0dba",
            "label": "ORG"
          },
          {
            "text": "\u0dc1\u0dca\u0dbb\u0dd3 \u0dbd\u0d82\u0d9a\u0dcf\u0dc0",
            "label": "GPE"
          },
          {
            "text": "\u0dc3\u0db8\u0dca\u0db8\u0db1\u0dca\u0dad\u0dca\u0dbb\u0dab\u0dba",
            "label": "ORG"
          },
          {
            "text": "\u0dc3\u0db8\u0dca\u0db4\u0dd6\u0dbb\u0dca\u0dab \u0daf\u0dc0\u0dc3\u0d9a\u0dca",
            "label": "DATE"
          },
          {
            "text": "26 \u0dc0\u0dd0\u0db1\u0dd2",
            "label": "ORDINAL"
          },
          {
            "text": "\u0db8\u0dd0\u0dba\u0dd2",
            "label": "DATE"
          },
          {
            "text": "CIPM \u0db4\u0dbb\u0dca\u0dba\u0dda\u0dc2\u0dab \u0dc3\u0db8\u0dca\u0db8\u0db1\u0dca\u0dad\u0dca\u200d\u0dbb\u0dab\u0dba",
            "label": "ORG"
          },
          {
            "text": "\u0dc0\u0dca\u200d\u0dba\u0dc0\u0dc4\u0dcf\u0dbb\u0dd2\u0d9a \u0db4\u0dbb\u0dca\u0dba\u0dda\u0dc2\u0dab \u0dc3\u0dc4 \u0daf\u0dd0\u0db1\u0dd4\u0db8 \u0db8\u0db0\u0dca\u200d\u0dba\u0dc3\u0dca\u0dae\u0dcf\u0db1\u0dba \u0db4\u0dd2\u0dc5\u0dd2\u0db6\u0db3 CIPM \u0dc3\u0dca\u0dae\u0dcf\u0dc0\u0dbb \u0d9a\u0db8\u0dd2\u0da7\u0dd4\u0dc0",
            "label": "ORG"
          },
          {
            "text": "CIPM \u0dc1\u0dca\u200d\u0dbb\u0dd3 \u0dbd\u0d82\u0d9a\u0dcf",
            "label": "PERSON"
          }
        ],
        [
          {
            "text": "\u0dc3\u0db8\u0dca\u0db8\u0db1\u0dca\u0dad\u0dca\u200d\u0dbb\u0dab \u0db4\u0dd4\u0da7\u0dd4\u0dc0",
            "label": "ORG"
          },
          {
            "text": "\u0dc3\u0db8\u0dca\u0db8\u0db1\u0dca\u0dad\u0dca\u0dbb\u0dab\u0dba",
            "label": "FAC"
          },
          {
            "text": "\u0dc1\u0dca\u0dbb\u0dd3 \u0dbd\u0d82\u0d9a\u0dcf\u0dc0",
            "label": "LOC"
          },
          {
            "text": "\u0dc1\u0dca\u0dbb\u0dd3 \u0dbd\u0d82\u0d9a\u0dcf\u0dc0",
            "label": "GPE"
          },
          {
            "text": "\u0db4\u0dc5\u0db8\u0dd4\u0dc0\u0db1",
            "label": "ORDINAL"
          },
          {
            "text": "CIPM",
            "label": "ORG"
          },
          {
            "text": "CIPM",
            "label": "ORG"
          },
          {
            "text": "\u0d89\u0daf\u0dd2\u0dbb\u0dd2 \u0dc0\u0dc3\u0dbb",
            "label": "DATE"
          }
        ],
        [],
        [],
        []
      ]
    },
    "ta": {
      "title": "CIPM 6\u0bb5\u0ba4\u0bc1 \u0b86\u0bb0\u0bbe\u0baf\u0bcd\u0b9a\u0bcd\u0b9a\u0bbf \u0b9a\u0bbf\u0bae\u0bcd\u0baa\u0bcb\u0b9a\u0bbf\u0baf\u0bae\u0bcd 'Glocal' HRM\u0b95\u0bcd\u0b95\u0bc1 \u0bae\u0ba4\u0bbf\u0baa\u0bcd\u0baa\u0bc1 \u0b9a\u0bc7\u0bb0\u0bcd\u0b95\u0bcd\u0b95\u0bbf\u0bb1\u0ba4\u0bc1",
      "author": "\u0b9a\u0bb9\u0bbe\u0ba9\u0bcd \u0bb5\u0bc0\u0bb0\u0b9a\u0bc2\u0bb0\u0bbf\u0baf",
      "body_lines": [
        "\u0bae\u0ba9\u0bbf\u0ba4 \u0bb5\u0bb3 \u0bae\u0bc1\u0b95\u0bbe\u0bae\u0bc8\u0ba4\u0bcd\u0ba4\u0bc1\u0bb5\u0ba4\u0bcd\u0ba4\u0bbf\u0bb2\u0bcd \u0ba4\u0bc7\u0b9a\u0ba4\u0bcd\u0ba4\u0bbf\u0ba9\u0bcd \u0ba4\u0bb2\u0bc8\u0bb5\u0bb0\u0bbe\u0ba9 CIPM \u0bb8\u0bcd\u0bb0\u0bc0\u0bb2\u0b99\u0bcd\u0b95\u0bbe, 6\u0bb5\u0ba4\u0bc1 \u0bb5\u0bb0\u0bc1\u0b9f\u0bbe\u0ba8\u0bcd\u0ba4 \u0b86\u0bb0\u0bbe\u0baf\u0bcd\u0b9a\u0bcd\u0b9a\u0bbf \u0b9a\u0bbf\u0bae\u0bcd\u0baa\u0bcb\u0b9a\u0bbf\u0baf\u0bae\u0bcd '\u0bb5\u0ba3\u0bbf\u0b95 \u0baa\u0bbf\u0ba9\u0bcd\u0ba9\u0b9f\u0bc8\u0bb5\u0bc1\u0b95\u0bcd\u0b95\u0bbe\u0ba9 HRM \u0ba8\u0b9f\u0bc8\u0bae\u0bc1\u0bb1\u0bc8\u0b95\u0bb3\u0bbf\u0ba9\u0bcd \u0b89\u0bb2\u0b95\u0bae\u0baf\u0bae\u0bbe\u0b95\u0bcd\u0b95\u0bb2\u0bcd' \u0ba4\u0bca\u0b9f\u0b95\u0bcd\u0b95 \u0bb5\u0bbf\u0bb4\u0bbe\u0bb5\u0bc8, \u0b95\u0bcc\u0bb0\u0bb5 \u0bb5\u0bbf\u0bb0\u0bc1\u0ba8\u0bcd\u0ba4\u0bbf\u0ba9\u0bb0\u0bcd \u0b9c\u0bbe\u0ba9\u0bbf \u0b9a\u0bbf. \u0b9f\u0bc6\u0baf\u0bcd\u0bb2\u0bb0\u0bcd \u0b9c\u0bc2\u0ba9\u0bbf\u0baf\u0bb0\u0bcd \u0b89\u0b9f\u0bcd\u0baa\u0b9f \u0b89\u0bb3\u0bcd\u0bb3\u0bc2\u0bb0\u0bcd \u0bae\u0bb1\u0bcd\u0bb1\u0bc1\u0bae\u0bcd \u0b9a\u0bb0\u0bcd\u0bb5\u0ba4\u0bc7\u0b9a \u0baa\u0b99\u0bcd\u0b95\u0bc7\u0bb1\u0bcd\u0baa\u0bbe\u0bb3\u0bb0\u0bcd\u0b95\u0bb3\u0bc1\u0b9f\u0ba9\u0bcd \u0b95\u0bb2\u0baa\u0bcd\u0baa\u0bbf\u0ba9 \u0bae\u0bc1\u0bb1\u0bc8\u0baf\u0bbf\u0bb2\u0bcd \u0b9a\u0bae\u0bc0\u0baa\u0ba4\u0bcd\u0ba4\u0bbf\u0bb2\u0bcd \u0ba8\u0b9f\u0bc8\u0baa\u0bc6\u0bb1\u0bcd\u0bb1\u0ba4\u0bc1. - \u0ba4\u0bb2\u0bc8\u0bb5\u0bb0\u0bcd \u0bae\u0bb1\u0bcd\u0bb1\u0bc1\u0bae\u0bcd CEO SHRM USA, \u0bae\u0bc1\u0b95\u0bcd\u0b95\u0bbf\u0baf \u0baa\u0bc7\u0b9a\u0bcd\u0b9a\u0bbe\u0bb3\u0bb0\u0bcd HRM & \u0b86\u0b9a\u0bbf\u0baf \u0b86\u0baf\u0bcd\u0bb5\u0bc1\u0b95\u0bb3\u0bcd \u0baa\u0bc7\u0bb0\u0bbe\u0b9a\u0bbf\u0bb0\u0bbf\u0baf\u0bb0\u0bcd, Monash Business School, Australia - Fang Lee Cooke \u0bae\u0bb1\u0bcd\u0bb1\u0bc1\u0bae\u0bcd \u0b89\u0bb3\u0bcd\u0bb3\u0bc2\u0bb0\u0bcd \u0bae\u0bb1\u0bcd\u0bb1\u0bc1\u0bae\u0bcd \u0b9a\u0bb0\u0bcd\u0bb5\u0ba4\u0bc7\u0b9a \u0baa\u0b99\u0bcd\u0b95\u0bc7\u0bb1\u0bcd\u0baa\u0bbe\u0bb3\u0bb0\u0bcd\u0b95\u0bb3\u0bcd \u0b9a\u0bbf\u0bae\u0bcd\u0baa\u0bcb\u0b9a\u0bbf\u0baf\u0ba4\u0bcd\u0ba4\u0bbf\u0bb2\u0bcd \u0b87\u0ba3\u0bc8\u0ba8\u0bcd\u0ba4\u0bc1 \u0b95\u0bca\u0bb3\u0bcd\u0b95\u0bbf\u0ba9\u0bcd\u0bb1\u0ba9\u0bb0\u0bcd \u0b9c\u0bc6\u0baf\u0ba8\u0bcd\u0ba4 \u0b85\u0bae\u0bb0\u0b9a\u0bbf\u0b99\u0bcd\u0b95 - CIPM \u0ba4\u0bb2\u0bc8\u0bb5\u0bb0\u0bcd, \u0b95\u0bc6\u0ba9\u0bcd \u0bb5\u0bbf\u0b9c\u0baf\u0b95\u0bc1\u0bae\u0bbe\u0bb0\u0bcd - CIPM \u0ba4\u0bc1\u0ba3\u0bc8\u0ba4\u0bcd \u0ba4\u0bb2\u0bc8\u0bb5\u0bb0\u0bcd, \u0b95\u0bbf\u0bb1\u0bbf\u0bb8\u0bcd \u0b92\u0baa\u0bc7\u0b9a\u0bc7\u0b95\u0bc7\u0bb0\u0bbe \u2013 CEO CIPM, \u0bae\u0bbe\u0ba8\u0bbe\u0b9f\u0bcd\u0b9f\u0bc1\u0ba4\u0bcd \u0ba4\u0bb2\u0bc8\u0bb5\u0bb0\u0bcd \u2013 \u0baa\u0bc7\u0bb0\u0bbe\u0b9a\u0bbf\u0bb0\u0bbf\u0baf\u0bb0\u0bcd \u0baa\u0bbf\u0bb0\u0b9a\u0bbe\u0ba4\u0bbf\u0ba9\u0bbf \u0b95\u0bae\u0b95\u0bc7, \u0ba4\u0bbf\u0bb2\u0bbe\u0b9e\u0bcd\u0b9a\u0ba9\u0bbf \u0bb5\u0bc0\u0bb0\u0ba4\u0bc1\u0b99\u0bcd\u0b95 \u2013 \u0bae\u0bbe\u0ba8\u0bbe\u0b9f\u0bcd\u0b9f\u0bc1\u0b9a\u0bcd \u0b9a\u0bc6\u0baf\u0bb2\u0bbe\u0bb3\u0bb0\u0bcd, \u0b9c\u0bbf \u0bb5\u0bc0\u0bb0\u0ba4\u0bc1\u0b99\u0bcd\u0b95 \u2013 \u0baa\u0ba3\u0bbf\u0baa\u0bcd\u0baa\u0bbe\u0bb3\u0bb0\u0bcd, \u0ba8\u0bbf\u0baa\u0bc1\u0ba3\u0ba4\u0bcd\u0ba4\u0bc1\u0bb5 \u0bae\u0bb1\u0bcd\u0bb1\u0bc1\u0bae\u0bcd \u0b95\u0bb2\u0bcd\u0bb5\u0bbf \u0bb5\u0bbf\u0bb5\u0b95\u0bbe\u0bb0\u0b99\u0bcd\u0b95\u0bb3\u0bcd, \u0bb9\u0bbf\u0bae\u0bbe\u0bb2\u0bbf \u0ba4\u0b9a\u0ba8\u0bbe\u0baf\u0b95\u0bcd\u0b95 \u2013 \u0baa\u0ba3\u0bbf\u0baa\u0bcd\u0baa\u0bbe\u0bb3\u0bb0\u0bcd \u0b9a\u0bc6\u0baf\u0bb1\u0bcd\u0baa\u0bbe\u0b9f\u0bc1\u0b95\u0bb3\u0bcd, \u0bae\u0bb1\u0bcd\u0bb1\u0bc1\u0bae\u0bcd \u0b95\u0bae\u0bbe\u0ba9\u0bbf \u0baa\u0bc6\u0bb0\u0bc7\u0bb0\u0bbe \u2013 \u0bae\u0bc1\u0b95\u0bbe\u0bae\u0bc8\u0baf\u0bbe\u0bb3\u0bb0\u0bcd, \u0b86\u0bb0\u0bbe\u0baf\u0bcd\u0b9a\u0bcd\u0b9a\u0bbf, CIPM \u0ba4\u0bb2\u0bc8\u0bae\u0bc8 \u0b85\u0bb2\u0bc1\u0bb5\u0bb2\u0b95\u0bae\u0bbe\u0ba9 \u201cHR House\u201d \u0b87\u0bb2\u0bcd \u0bb5\u0bb2\u0bc8 \u0ba4\u0bca\u0bb4\u0bbf\u0bb2\u0bcd\u0ba8\u0bc1\u0b9f\u0bcd\u0baa\u0bae\u0bcd \u0bae\u0bc2\u0bb2\u0bae\u0bcd \u0b95\u0bca\u0bb4\u0bc1\u0bae\u0bcd\u0baa\u0bc1 5 \u0b87\u0bb2\u0bcd. \u0b87\u0bb2\u0b99\u0bcd\u0b95\u0bc8\u0baf\u0bbf\u0ba9\u0bcd \u0bb8\u0bcd\u0bb0\u0bc0 \u0b9c\u0baf\u0bb5\u0bb0\u0bcd\u0ba4\u0ba9\u0baa\u0bc1\u0bb0 \u0baa\u0bb2\u0bcd\u0b95\u0bb2\u0bc8\u0b95\u0bcd\u0b95\u0bb4\u0b95\u0ba4\u0bcd\u0ba4\u0bbf\u0ba9\u0bcd (PIM) \u0bae\u0bc1\u0ba4\u0bc1\u0b95\u0bb2\u0bc8\u0baa\u0bcd \u0baa\u0b9f\u0bcd\u0b9f\u0ba4\u0bbe\u0bb0\u0bbf \u0bae\u0bc7\u0bb2\u0bbe\u0ba3\u0bcd\u0bae\u0bc8 \u0ba8\u0bbf\u0bb1\u0bc1\u0bb5\u0ba9\u0ba4\u0bcd\u0ba4\u0bbf\u0ba9\u0bcd (PIM) \u0bae\u0bc2\u0ba4\u0bcd\u0ba4 \u0bb5\u0bbf\u0bb0\u0bbf\u0bb5\u0bc1\u0bb0\u0bc8\u0baf\u0bbe\u0bb3\u0bb0\u0bcd/\u0b86\u0bb2\u0bcb\u0b9a\u0b95\u0bb0\u0bcd, \u0bae\u0bc2\u0ba4\u0bcd\u0ba4 \u0b86\u0baf\u0bcd\u0bb5\u0bbe\u0bb3\u0bb0\u0bcd \u0b9f\u0bbe\u0b95\u0bcd\u0b9f\u0bb0\u0bcd \u0b86\u0ba9\u0ba8\u0bcd\u0ba4 \u0b9c\u0bc6\u0baf\u0bb5\u0bb0\u0bcd\u0ba4\u0ba9 \u0b85\u0bb5\u0bb0\u0bcd\u0b95\u0bb3\u0bbe\u0bb2\u0bcd, \u0bae\u0bc7 \u0bae\u0bbe\u0ba4\u0bae\u0bcd 25\u0b86\u0bae\u0bcd \u0ba4\u0bc7\u0ba4\u0bbf, \u0b86\u0bb0\u0bbe\u0baf\u0bcd\u0b9a\u0bcd\u0b9a\u0bbf \u0bae\u0bc1\u0bb1\u0bc8 \u0ba4\u0bca\u0b9f\u0bb0\u0bcd\u0baa\u0bbe\u0ba9 \u0bae\u0bbf\u0b95\u0bb5\u0bc1\u0bae\u0bcd \u0bb5\u0bc6\u0bb1\u0bcd\u0bb1\u0bbf\u0b95\u0bb0\u0bae\u0bbe\u0ba9 \u0b95\u0bb0\u0bc1\u0ba4\u0bcd\u0ba4\u0bb0\u0b99\u0bcd\u0b95\u0bbf\u0bb1\u0bcd\u0b95\u0bc1 \u0bae\u0bc1\u0ba8\u0bcd\u0ba4\u0bc8\u0baf \u0baa\u0b9f\u0bcd\u0b9f\u0bb1\u0bc8 \u0b92\u0ba9\u0bcd\u0bb1\u0bc1 \u0ba8\u0b9f\u0ba4\u0bcd\u0ba4\u0baa\u0bcd\u0baa\u0b9f\u0bcd\u0b9f\u0ba4\u0bc1. \u0b9a\u0bbf\u0bae\u0bcd\u0baa\u0bcb\u0b9a\u0bbf\u0baf\u0ba4\u0bcd\u0ba4\u0bbf\u0ba9\u0bcd \u0ba4\u0bb0\u0ba4\u0bcd\u0ba4\u0bc8 \u0bae\u0bc7\u0bae\u0bcd\u0baa\u0b9f\u0bc1\u0ba4\u0bcd\u0ba4\u0bc1\u0bae\u0bcd \u0b85\u0bae\u0bcd\u0b9a\u0bae\u0bcd. \u0ba4\u0bca\u0b9f\u0b95\u0bcd\u0b95 \u0bb5\u0bbf\u0bb4\u0bbe\u0bb5\u0bc8\u0ba4\u0bcd \u0ba4\u0bca\u0b9f\u0bb0\u0bcd\u0ba8\u0bcd\u0ba4\u0bc1 \u0bae\u0bc7 26 \u0b86\u0bae\u0bcd \u0ba4\u0bc7\u0ba4\u0bbf \u0bae\u0bc1\u0bb4\u0bc1 \u0ba8\u0bbe\u0bb3\u0bcd \u0b95\u0ba3\u0bcd \u0ba4\u0bbf\u0bb1\u0b95\u0bcd\u0b95\u0bc1\u0bae\u0bcd \u0b86\u0bb0\u0bbe\u0baf\u0bcd\u0b9a\u0bcd\u0b9a\u0bbf \u0bb5\u0bbf\u0bb3\u0b95\u0bcd\u0b95\u0b95\u0bcd\u0b95\u0bbe\u0b9f\u0bcd\u0b9a\u0bbf\u0b95\u0bb3\u0bcd \u0bae\u0bb1\u0bcd\u0bb1\u0bc1\u0bae\u0bcd \u0ba4\u0bca\u0bb4\u0bbf\u0bb2\u0bcd\u0ba8\u0bc1\u0b9f\u0bcd\u0baa \u0bae\u0bb1\u0bcd\u0bb1\u0bc1\u0bae\u0bcd \u0b95\u0bc1\u0bb4\u0bc1 \u0bb5\u0bbf\u0bb5\u0bbe\u0ba4\u0b99\u0bcd\u0b95\u0bb3\u0bcd \u0ba8\u0b9f\u0bc8\u0baa\u0bc6\u0bb1\u0bcd\u0bb1\u0ba4\u0bc1. CIPM \u0b86\u0bb0\u0bbe\u0baf\u0bcd\u0b9a\u0bcd\u0b9a\u0bbf \u0b9a\u0bbf\u0bae\u0bcd\u0baa\u0bcb\u0b9a\u0bbf\u0baf\u0bae\u0bcd CIPM \u0b87\u0bb2\u0b99\u0bcd\u0b95\u0bc8\u0baf\u0bbf\u0ba9\u0bcd \u0ba4\u0bb2\u0bc8\u0bb5\u0bb0\u0bcd CIPM \u0b87\u0ba9\u0bcd \u0bb5\u0bb4\u0bbf\u0b95\u0bbe\u0b9f\u0bcd\u0b9f\u0bc1\u0ba4\u0bb2\u0bbf\u0ba9\u0bcd \u0b95\u0bc0\u0bb4\u0bcd \u0baa\u0baf\u0ba9\u0bcd\u0baa\u0bbe\u0b9f\u0bcd\u0b9f\u0bc1 \u0b86\u0bb0\u0bbe\u0baf\u0bcd\u0b9a\u0bcd\u0b9a\u0bbf \u0bae\u0bb1\u0bcd\u0bb1\u0bc1\u0bae\u0bcd \u0b85\u0bb1\u0bbf\u0bb5\u0bc1 \u0bae\u0bc8\u0baf\u0ba4\u0bcd\u0ba4\u0bbf\u0ba9\u0bcd CIPM \u0ba8\u0bbf\u0bb2\u0bc8\u0b95\u0bcd\u0b95\u0bc1\u0bb4\u0bc1\u0bb5\u0bbe\u0bb2\u0bcd \u0b8f\u0bb1\u0bcd\u0baa\u0bbe\u0b9f\u0bc1 \u0b9a\u0bc6\u0baf\u0bcd\u0baf\u0baa\u0bcd\u0baa\u0b9f\u0bcd\u0b9f\u0bc1\u0bb3\u0bcd\u0bb3\u0ba4\u0bc1.",
        "\u0b9a\u0bbf\u0bae\u0bcd\u0baa\u0bcb\u0b9a\u0bbf\u0baf\u0bae\u0bcd \u0ba4\u0bb2\u0bc8\u0bb5\u0bb0\u0bcd \u0b86\u0bb1\u0bcd\u0bb1\u0bbf\u0baf \u0bb5\u0bb0\u0bb5\u0bc7\u0bb1\u0bcd\u0baa\u0bc1 \u0b89\u0bb0\u0bc8\u0baf\u0bc8\u0ba4\u0bcd \u0ba4\u0bca\u0b9f\u0bb0\u0bcd\u0ba8\u0bcd\u0ba4\u0bc1, \u0b9a\u0bbf\u0bae\u0bcd\u0baa\u0bcb\u0b9a\u0bbf\u0baf\u0ba4\u0bcd\u0ba4\u0bbf\u0bb2\u0bcd \u0b89\u0bb0\u0bc8\u0baf\u0bbe\u0bb1\u0bcd\u0bb1\u0bbf\u0baf \u0b9a\u0bbf\u0b90\u0baa\u0bbf\u0b8e\u0bae\u0bcd \u0b87\u0bb2\u0b99\u0bcd\u0b95\u0bc8\u0ba4\u0bcd \u0ba4\u0bb2\u0bc8\u0bb5\u0bb0\u0bcd - \u0b9c\u0baf\u0ba8\u0bcd\u0ba4 \u0b85\u0bae\u0bb0\u0b9a\u0bbf\u0b99\u0bcd\u0b95, \u0b87\u0bb2\u0b99\u0bcd\u0b95\u0bc8\u0baf\u0bbf\u0bb2\u0bcd \u0ba8\u0b9f\u0ba4\u0bcd\u0ba4\u0baa\u0bcd\u0baa\u0b9f\u0bc1\u0bae\u0bcd \u0bae\u0bc1\u0ba4\u0ba9\u0bcd\u0bae\u0bc8 \u0b85\u0bb2\u0bcd\u0bb2\u0ba4\u0bc1 \u0baa\u0baf\u0ba9\u0bcd\u0baa\u0bbe\u0b9f\u0bcd\u0b9f\u0bc1 \u0b86\u0bb0\u0bbe\u0baf\u0bcd\u0b9a\u0bcd\u0b9a\u0bbf\u0baf\u0bbf\u0ba9\u0bcd \u0b85\u0bb3\u0bb5\u0bc1 \u0bae\u0bbf\u0b95\u0b95\u0bcd \u0b95\u0bc1\u0bb1\u0bc8\u0bb5\u0bc1. \"\u0bae\u0ba9\u0bbf\u0ba4 \u0bb5\u0bb3 \u0bae\u0bc7\u0bb2\u0bbe\u0ba3\u0bcd\u0bae\u0bc8 \u0ba4\u0bca\u0b9f\u0bb0\u0bcd\u0baa\u0bbe\u0ba9 \u0ba8\u0b9f\u0bc8\u0bae\u0bc1\u0bb1\u0bc8 \u0b9a\u0bbf\u0b95\u0bcd\u0b95\u0bb2\u0bcd\u0b95\u0bb3\u0bc8 \u0bae\u0bc1\u0ba4\u0bb2\u0bcd-\u0ba8\u0bbf\u0bb2\u0bc8 \u0bae\u0bb1\u0bcd\u0bb1\u0bc1\u0bae\u0bcd \u0b86\u0bb4\u0bae\u0bbe\u0ba9 \u0baa\u0bbe\u0bb0\u0bcd\u0bb5\u0bc8\u0baf\u0bc8\u0baa\u0bcd \u0baa\u0bc6\u0bb1\u0bc1\u0bb5\u0ba4\u0bb1\u0bcd\u0b95\u0bc1 \u0b86\u0bb0\u0bbe\u0baf\u0bcd\u0b9a\u0bcd\u0b9a\u0bbf \u0bae\u0bbf\u0b95\u0bb5\u0bc1\u0bae\u0bcd \u0bae\u0bc1\u0b95\u0bcd\u0b95\u0bbf\u0baf\u0bae\u0bbe\u0ba9\u0ba4\u0bc1 \u0b8e\u0ba9\u0bcd\u0baa\u0ba4\u0bbe\u0bb2\u0bcd, \u0ba8\u0bbe\u0ba9\u0bcd \u0ba4\u0bb2\u0bc8\u0bb5\u0bb0\u0bbe\u0b95 \u0b87\u0bb0\u0bc1\u0ba8\u0bcd\u0ba4 \u0b95\u0bbe\u0bb2\u0ba4\u0bcd\u0ba4\u0bbf\u0ba9\u0bcd \u0b86\u0bb0\u0bae\u0bcd\u0baa\u0ba4\u0bcd\u0ba4\u0bbf\u0bb2\u0bcd, \u0b9a\u0bbf\u0b90\u0baa\u0bbf\u0b8e\u0bae\u0bcd\u0bae\u0bbf\u0bb2\u0bcd \u0b92\u0bb0\u0bc1 R&D \u0baa\u0bbf\u0bb0\u0bbf\u0bb5\u0bc8 \u0b89\u0bb0\u0bc1\u0bb5\u0bbe\u0b95\u0bcd\u0b95 \u0bb5\u0bc7\u0ba3\u0bcd\u0b9f\u0bc1\u0bae\u0bcd \u0b8e\u0ba9\u0bcd\u0bb1\u0bc1 \u0b95\u0bc7\u0b9f\u0bcd\u0b9f\u0bc1\u0b95\u0bcd \u0b95\u0bca\u0ba3\u0bcd\u0b9f\u0bc7\u0ba9\u0bcd. \u0bae\u0ba9\u0bbf\u0ba4\u0bb5\u0bb3\u0ba4\u0bcd\u0ba4\u0bc8\u0baa\u0bcd \u0baa\u0bb1\u0bcd\u0bb1\u0bbf\u0baf \u0baa\u0bc1\u0bb0\u0bbf\u0ba4\u0bb2\u0bcd \u0b87\u0ba8\u0bcd\u0ba4 \u0bae\u0bc1\u0ba9\u0bcd\u0ba9\u0bcb\u0b9f\u0bbf\u0baf\u0bbf\u0bb2\u0bcd\u0bb2\u0bbe\u0ba4 \u0b95\u0bbe\u0bb2\u0b99\u0bcd\u0b95\u0bb3\u0bbf\u0bb2\u0bcd \u0bae\u0b95\u0bcd\u0b95\u0bb3\u0bc8 \u0ba8\u0bbf\u0bb0\u0bcd\u0bb5\u0b95\u0bbf\u0ba4\u0bcd\u0ba4\u0bb2\u0bcd \u0bae\u0bb1\u0bcd\u0bb1\u0bc1\u0bae\u0bcd \u0b8a\u0b95\u0bcd\u0b95\u0bc1\u0bb5\u0bbf\u0baa\u0bcd\u0baa\u0ba4\u0bbf\u0bb2\u0bcd \u0b89\u0bb3\u0bcd\u0bb3 \u0b9a\u0bbf\u0b95\u0bcd\u0b95\u0bb2\u0bcd\u0b95\u0bb3\u0bc8 \u0b86\u0bb4\u0bae\u0bbe\u0b95\u0baa\u0bcd \u0baa\u0bbe\u0bb0\u0bbe\u0b9f\u0bcd\u0b9f\u0bc1\u0bb5\u0ba4\u0bb1\u0bcd\u0b95\u0bc1 \u0bb5\u0bb4\u0bbf\u0bb5\u0b95\u0bc1\u0ba4\u0bcd\u0ba4\u0ba4\u0bc1. \u0b87\u0ba8\u0bcd\u0ba4 \u0ba8\u0bbe\u0b9f\u0bcd\u0b9f\u0bbf\u0bb2\u0bcd \u0b86\u0bb0\u0bbe\u0baf\u0bcd\u0b9a\u0bcd\u0b9a\u0bbf\u0baf\u0bc8 \u0bae\u0bc1\u0ba9\u0bcd\u0ba9\u0bc1\u0b95\u0bcd\u0b95\u0bc1\u0b95\u0bcd \u0b95\u0bca\u0ba3\u0bcd\u0b9f\u0bc1 \u0bb5\u0bb0\u0bc1\u0bb5\u0ba4\u0bbf\u0bb2\u0bcd \u0bae\u0bc1\u0ba9\u0bcd\u0ba9\u0ba3\u0bbf \u0bae\u0bc8\u0baf\u0bae\u0bbe\u0b95 \u0b87\u0bb0\u0bc1\u0baa\u0bcd\u0baa\u0ba4\u0bc1\u0bae\u0bcd, \u0b9a\u0ba8\u0bcd\u0ba4\u0bc8\u0baf\u0bbf\u0bb2\u0bcd \u0bb5\u0bc7\u0bb1\u0bc1\u0baa\u0b9f\u0bc1\u0ba4\u0bcd\u0ba4\u0bbf\u0b95\u0bcd \u0b95\u0bbe\u0b9f\u0bcd\u0b9f\u0bc1\u0bb5\u0ba4\u0bc1\u0bae\u0bcd \u0b8e\u0b99\u0bcd\u0b95\u0bb3\u0bcd \u0ba8\u0bcb\u0b95\u0bcd\u0b95\u0bae\u0bcd,\u201d \u0b8e\u0ba9\u0bcd\u0bb1\u0bc1 \u0b85\u0bb5\u0bb0\u0bcd \u0b95\u0bc2\u0bb1\u0bbf\u0ba9\u0bbe\u0bb0\u0bcd, \u0bae\u0bc7\u0bb2\u0bc1\u0bae\u0bcd \u0bb5\u0bb0\u0bc1\u0bae\u0bcd \u0b86\u0ba3\u0bcd\u0b9f\u0bc1\u0b95\u0bb3\u0bbf\u0bb2\u0bcd \u0b9a\u0bbf\u0b90\u0baa\u0bbf\u0b8e\u0bae\u0bcd \u0b86\u0bb0\u0bbe\u0baf\u0bcd\u0b9a\u0bcd\u0b9a\u0bbf \u0baa\u0bbf\u0bb0\u0bbf\u0bb5\u0bc8 \u0bb5\u0bb2\u0bc1\u0baa\u0bcd\u0baa\u0b9f\u0bc1\u0ba4\u0bcd\u0ba4\u0bc1\u0bae\u0bcd \u0b8e\u0ba9\u0bcd\u0bb1\u0bc1\u0bae\u0bcd \u0b95\u0bc2\u0bb1\u0bbf\u0ba9\u0bbe\u0bb0\u0bcd.",
        "\u0bae\u0b95\u0bcd\u0b95\u0bb3\u0bcd \u0ba4\u0b99\u0bcd\u0b95\u0bb3\u0bcd \u0b95\u0bb0\u0bc1\u0ba4\u0bcd\u0ba4\u0bc8 \u0bae\u0bbf\u0b95 \u0bb5\u0bbf\u0bb0\u0bc8\u0bb5\u0bbf\u0bb2\u0bcd \u0bb5\u0bc6\u0bb3\u0bbf\u0baa\u0bcd\u0baa\u0b9f\u0bc1\u0ba4\u0bcd\u0ba4 \u0b85\u0ba9\u0bc1\u0bae\u0ba4\u0bbf\u0b95\u0bcd\u0b95\u0baa\u0bcd\u0baa\u0b9f \u0bb5\u0bc7\u0ba3\u0bcd\u0b9f\u0bc1\u0bae\u0bcd - CBEOU",
        "\u0b92\u0bb0\u0bc1 \u0baa\u0ba4\u0bbf\u0bb2\u0bc8 \u0bb5\u0bbf\u0b9f\u0bc1\u0b99\u0bcd\u0b95\u0bb3\u0bcd \u0baa\u0ba4\u0bbf\u0bb2\u0bc8 \u0bb0\u0ba4\u0bcd\u0ba4\u0bc1\u0b9a\u0bc6\u0baf\u0bcd \u0b89\u0b99\u0bcd\u0b95\u0bb3\u0bcd \u0bae\u0bbf\u0ba9\u0bcd\u0ba9\u0b9e\u0bcd\u0b9a\u0bb2\u0bcd \u0bae\u0bc1\u0b95\u0bb5\u0bb0\u0bbf \u0bb5\u0bc6\u0bb3\u0bbf\u0baf\u0bbf\u0b9f\u0baa\u0bcd\u0baa\u0b9f\u0bbe\u0ba4\u0bc1. \u0ba4\u0bc7\u0bb5\u0bc8\u0baf\u0bbe\u0ba9 \u0baa\u0bc1\u0bb2\u0b99\u0bcd\u0b95\u0bb3\u0bcd \u0b95\u0bc1\u0bb1\u0bbf\u0b95\u0bcd\u0b95\u0baa\u0bcd\u0baa\u0b9f\u0bcd\u0b9f\u0bc1\u0bb3\u0bcd\u0bb3\u0ba9 *\u0b95\u0bb0\u0bc1\u0ba4\u0bcd\u0ba4\u0bc1 \u0baa\u0bc6\u0baf\u0bb0\u0bcd *",
        "\u0b85\u0b9f\u0bc1\u0ba4\u0bcd\u0ba4 \u0bae\u0bc1\u0bb1\u0bc8 \u0ba8\u0bbe\u0ba9\u0bcd \u0b95\u0bb0\u0bc1\u0ba4\u0bcd\u0ba4\u0bc1 \u0ba4\u0bc6\u0bb0\u0bbf\u0bb5\u0bbf\u0b95\u0bcd\u0b95, \u0b8e\u0ba9\u0ba4\u0bc1 \u0baa\u0bc6\u0baf\u0bb0\u0bcd, \u0bae\u0bbf\u0ba9\u0bcd\u0ba9\u0b9e\u0bcd\u0b9a\u0bb2\u0bcd \u0bae\u0bb1\u0bcd\u0bb1\u0bc1\u0bae\u0bcd \u0b87\u0ba3\u0bc8\u0baf\u0ba4\u0bb3\u0ba4\u0bcd\u0ba4\u0bc8 \u0b87\u0ba8\u0bcd\u0ba4 \u0b89\u0bb2\u0bbe\u0bb5\u0bbf\u0baf\u0bbf\u0bb2\u0bcd \u0b9a\u0bc7\u0bae\u0bbf\u0b95\u0bcd\u0b95\u0bb5\u0bc1\u0bae\u0bcd."
      ],
      "title_ents": [
        {
          "text": "CIPM 6\u0bb5\u0ba4\u0bc1 \u0b86\u0bb0\u0bbe\u0baf\u0bcd\u0b9a\u0bcd\u0b9a\u0bbf \u0b95\u0bb0\u0bc1\u0ba4\u0bcd\u0ba4\u0bb0\u0b99\u0bcd\u0b95\u0bae\u0bcd",
          "label": "ORG"
        }
      ],
      "body_line_ents_list": [
        [
          {
            "text": "6\u0bb5\u0ba4\u0bc1",
            "label": "ORDINAL"
          },
          {
            "text": "\u0bb5\u0bb0\u0bc1\u0b9f\u0bbe\u0ba8\u0bcd\u0ba4\u0bbf\u0bb0 \u0b86\u0bb0\u0bbe\u0baf\u0bcd\u0b9a\u0bcd\u0b9a\u0bbf \u0b9a\u0bbf\u0bae\u0bcd\u0baa\u0bcb\u0b9a\u0bbf\u0baf\u0bae\u0bcd '\u0bb5\u0ba3\u0bbf\u0b95 \u0ba8\u0bc6\u0b95\u0bbf\u0bb4\u0bcd\u0b9a\u0bcd\u0b9a\u0bbf\u0b95\u0bcd\u0b95\u0bbe\u0ba9 HRM \u0ba8\u0b9f\u0bc8\u0bae\u0bc1\u0bb1\u0bc8\u0b95\u0bb3\u0bbf\u0ba9\u0bcd \u0b89\u0bb2\u0b95\u0bb3\u0bbe\u0bb5\u0bbf\u0baf\u0bae\u0baf\u0bae\u0bbe\u0b95\u0bcd\u0b95\u0bb2\u0bcd'",
            "label": "EVENT"
          },
          {
            "text": "\u0b9c\u0bbe\u0ba9\u0bbf \u0b9a\u0bbf. \u0b9f\u0bc6\u0baf\u0bcd\u0bb2\u0bb0\u0bcd \u0b9c\u0bc2\u0ba9\u0bbf\u0baf\u0bb0\u0bcd",
            "label": "PERSON"
          },
          {
            "text": "\u0bae\u0bc1\u0b95\u0bcd\u0b95\u0bbf\u0baf \u0b95\u0bc1\u0bb1\u0bbf\u0baa\u0bcd\u0baa\u0bc1",
            "label": "ORG"
          },
          {
            "text": "\u0bae\u0bcb\u0ba9\u0bbe\u0bb7\u0bcd \u0bb5\u0ba3\u0bbf\u0b95 \u0baa\u0bb3\u0bcd\u0bb3\u0bbf",
            "label": "ORG"
          },
          {
            "text": "\u0b86\u0bb8\u0bcd\u0ba4\u0bbf\u0bb0\u0bc7\u0bb2\u0bbf\u0baf\u0bbe",
            "label": "GPE"
          },
          {
            "text": "\u0b83\u0baa\u0bbe\u0b99\u0bcd \u0bb2\u0bc0 \u0b95\u0bc1\u0b95\u0bcd",
            "label": "PERSON"
          },
          {
            "text": "\u0b9a\u0bbf\u0b90\u0baa\u0bbf\u0b8e\u0bae\u0bcd",
            "label": "PERSON"
          },
          {
            "text": "\u0b95\u0bc6\u0ba9\u0bcd \u0bb5\u0bbf\u0b9c\u0baf\u0b95\u0bc1\u0bae\u0bbe\u0bb0\u0bcd",
            "label": "PERSON"
          },
          {
            "text": "\u0b9a\u0bbf\u0b90\u0baa\u0bbf\u0b8e\u0bae\u0bcd",
            "label": "PERSON"
          },
          {
            "text": "\u0b95\u0bbf\u0bb1\u0bbf\u0bb8\u0bcd \u0b92\u0baa\u0bc7\u0b9a\u0bc7\u0b95\u0bb0",
            "label": "PERSON"
          },
          {
            "text": "\u0b9a\u0bbf\u0b90\u0baa\u0bbf\u0b8e\u0bae\u0bcd",
            "label": "ORG"
          },
          {
            "text": "\u0baa\u0bc7\u0bb0\u0bbe\u0b9a\u0bbf\u0bb0\u0bbf\u0baf\u0bb0\u0bcd \u0baa\u0bbf\u0bb0\u0b9a\u0bbe\u0ba4\u0bbf\u0ba9\u0bbf \u0b95\u0bae\u0b95\u0bc7",
            "label": "PERSON"
          },
          {
            "text": "\u0ba4\u0bbf\u0bb2\u0bbe\u0b9e\u0bcd\u0b9a\u0ba9\u0bbf",
            "label": "NORP"
          },
          {
            "text": "\u0b9c\u0bbf \u0bb5\u0bc0\u0bb0\u0ba4\u0bc1\u0b99\u0bcd\u0b95",
            "label": "ORG"
          },
          {
            "text": "\u0ba4\u0bca\u0bb4\u0bbf\u0bb2\u0bcd\u0bae\u0bc1\u0bb1\u0bc8 & \u0b95\u0bb2\u0bcd\u0bb5\u0bbf \u0bb5\u0bbf\u0bb5\u0b95\u0bbe\u0bb0\u0b99\u0bcd\u0b95\u0bb3\u0bcd",
            "label": "ORG"
          },
          {
            "text": "\u0bb9\u0bbf\u0bae\u0bbe\u0bb2\u0bbf \u0ba4\u0b9a\u0ba8\u0bbe\u0baf\u0b95\u0bcd\u0b95",
            "label": "PERSON"
          },
          {
            "text": "\u0b9a\u0bc6\u0baf\u0bb2\u0bcd\u0baa\u0bbe\u0b9f\u0bc1\u0b95\u0bb3\u0bcd",
            "label": "ORG"
          },
          {
            "text": "\u0b95\u0bae\u0bbe\u0ba9\u0bbf \u0baa\u0bc6\u0bb0\u0bc7\u0bb0\u0bbe",
            "label": "PERSON"
          },
          {
            "text": "\u0b9a\u0bbf\u0b90\u0baa\u0bbf\u0b8e\u0bae\u0bcd",
            "label": "ORG"
          },
          {
            "text": "\u0bb5\u0bc0\u0b9f\u0bc1",
            "label": "ORG"
          },
          {
            "text": "\u0bae\u0bc7 25 \u0b86\u0bae\u0bcd \u0ba4\u0bc7\u0ba4\u0bbf",
            "label": "DATE"
          },
          {
            "text": "\u0b86\u0ba9\u0ba8\u0bcd\u0ba4 \u0b9c\u0bc6\u0baf\u0bb5\u0bb0\u0bcd\u0ba4\u0ba9",
            "label": "PERSON"
          },
          {
            "text": "\u0bae\u0bc7\u0bb2\u0bbe\u0ba3\u0bcd\u0bae\u0bc8 \u0bae\u0bc1\u0ba4\u0bc1\u0b95\u0bb2\u0bc8 \u0ba8\u0bbf\u0bb1\u0bc1\u0bb5\u0ba9\u0bae\u0bcd",
            "label": "ORG"
          },
          {
            "text": "PIM",
            "label": "ORG"
          },
          {
            "text": "\u0bb8\u0bcd\u0bb0\u0bc0 \u0b9c\u0baf\u0bb5\u0bb0\u0bcd\u0ba4\u0ba9\u0baa\u0bc1\u0bb0 \u0baa\u0bb2\u0bcd\u0b95\u0bb2\u0bc8\u0b95\u0bcd\u0b95\u0bb4\u0b95\u0bae\u0bcd",
            "label": "ORG"
          },
          {
            "text": "\u0b87\u0bb2\u0b99\u0bcd\u0b95\u0bc8",
            "label": "GPE"
          },
          {
            "text": "\u0b9a\u0bbf\u0bae\u0bcd\u0baa\u0bcb\u0b9a\u0bbf\u0baf\u0bae\u0bcd",
            "label": "ORG"
          },
          {
            "text": "\u0b92\u0bb0\u0bc1 \u0bae\u0bc1\u0bb4\u0bc1 \u0ba8\u0bbe\u0bb3\u0bcd",
            "label": "DATE"
          },
          {
            "text": "26 \u0b86\u0bae\u0bcd \u0ba4\u0bc7\u0ba4\u0bbf",
            "label": "ORDINAL"
          },
          {
            "text": "\u0bae\u0bc7",
            "label": "DATE"
          },
          {
            "text": "\u0b9a\u0bbf\u0b90\u0baa\u0bbf\u0b8e\u0bae\u0bcd \u0b86\u0bb0\u0bbe\u0baf\u0bcd\u0b9a\u0bcd\u0b9a\u0bbf \u0b9a\u0bbf\u0bae\u0bcd\u0baa\u0bcb\u0b9a\u0bbf\u0baf\u0bae\u0bcd",
            "label": "ORG"
          },
          {
            "text": "\u0baa\u0baf\u0ba9\u0bcd\u0baa\u0bbe\u0b9f\u0bcd\u0b9f\u0bc1 \u0b86\u0bb0\u0bbe\u0baf\u0bcd\u0b9a\u0bcd\u0b9a\u0bbf \u0bae\u0bb1\u0bcd\u0bb1\u0bc1\u0bae\u0bcd \u0b85\u0bb1\u0bbf\u0bb5\u0bc1 \u0bae\u0bc8\u0baf\u0ba4\u0bcd\u0ba4\u0bbf\u0bb1\u0bcd\u0b95\u0bbe\u0ba9 CIPM \u0ba8\u0bbf\u0bb2\u0bc8\u0b95\u0bcd\u0b95\u0bc1\u0bb4\u0bc1",
            "label": "ORG"
          },
          {
            "text": "\u0b9a\u0bbf\u0b90\u0baa\u0bbf\u0b8e\u0bae\u0bcd \u0b87\u0bb2\u0b99\u0bcd\u0b95\u0bc8",
            "label": "PERSON"
          }
        ],
        [
          {
            "text": "\u0b9a\u0bbf\u0bae\u0bcd\u0baa\u0bcb\u0b9a\u0bbf\u0baf\u0bae\u0bcd \u0ba8\u0bbe\u0bb1\u0bcd\u0b95\u0bbe\u0bb2\u0bbf",
            "label": "ORG"
          },
          {
            "text": "\u0b9a\u0bbf\u0bae\u0bcd\u0baa\u0bcb\u0b9a\u0bbf\u0baf\u0bae\u0bcd",
            "label": "FAC"
          },
          {
            "text": "\u0b87\u0bb2\u0b99\u0bcd\u0b95\u0bc8",
            "label": "LOC"
          },
          {
            "text": "\u0b87\u0bb2\u0b99\u0bcd\u0b95\u0bc8",
            "label": "GPE"
          },
          {
            "text": "\u0bae\u0bc1\u0ba4\u0bb2\u0bbf\u0bb2\u0bcd",
            "label": "ORDINAL"
          },
          {
            "text": "\u0b9a\u0bbf\u0b90\u0baa\u0bbf\u0b8e\u0bae\u0bcd",
            "label": "ORG"
          },
          {
            "text": "\u0b9a\u0bbf\u0b90\u0baa\u0bbf\u0b8e\u0bae\u0bcd",
            "label": "ORG"
          },
          {
            "text": "\u0bb5\u0bb0\u0bc1\u0bae\u0bcd \u0b86\u0ba3\u0bcd\u0b9f\u0bc1\u0b95\u0bb3\u0bcd",
            "label": "DATE"
          }
        ],
        [],
        [],
        []
      ]
    }
  }
}